Workbook
Name _dFin: 42735
Name _soNumFisc: 3201201523617
Name _soSigle: "PYTHAGORE CONSULTAN"

Sheet Balance
A1: N° compte | B1: Libellés | C1: Débit | D1: Crédit | E1: Débit | F1: Crédit | G1: Débit | H1: Crédit
A2: 101200 | B2: Capital souscrit, appelé, non | C2: 0 | D2: 0 | E2: 193000000 | F2: 193000000 | G2: 0 | H2: 0
A3: 101300 | B3: Capital souscrit, appelé, vers | C3: 0 | D3: 100000000 | E3: 0 | F3: 1e+10 | G3: 0 | H3: 10100000000
A4: 129000 | B4: REPORT À NOUVEAU DÉBITEUR | C4: 2748292 | D4: 0 | E4: 20055904 | F4: 0 | G4: 22804196 | H4: 0
A5: 139000 | B5: RÉSULTAT NET : PERTE | C5: 20055904 | D5: 0 | E5: 0 | F5: 20055904 | G5: 0 | H5: 0
A6: 160000 | B6: EMPRUNTS ET DETTES ASSIMILÉES | C6: 0 | D6: 5125000000 | E6: 5125000000 | F6: 0 | G6: 0 | H6: 0
A7: 161100 | B7: Emprunts obligataires ordinair | C7: 0 | D7: 7500000000 | E7: 7500000000 | F7: 0 | G7: 0 | H7: 0
A8: 162010 | B8: EMPRUNT CORIS BANK | C8: 0 | D8: 0 | E8: 247062318 | F8: 500000000 | G8: 0 | H8: 252937682
A9: 162020 | B9: EMPRUNT VISTA | C9: 0 | D9: 0 | E9: 0 | F9: 15000000000 | G9: 0 | H9: 15000000000
A10: 162030 | B10: EMPRUNT WBI | C10: 0 | D10: 0 | E10: 539354385 | F10: 5e+09 | G10: 0 | H10: 4.4606456e+09
A11: 213100 | B11: LOGICIELS | C11: 0 | D11: 0 | E11: 64245912 | F11: 0 | G11: 64245912 | H11: 0
A12: 221800 | B12: AUTRES TERRAINS | C12: 0 | D12: 0 | E12: 962734139 | F12: 0 | G12: 962734139 | H12: 0
A13: 222800 | B13: TERRAINS RIVERAINS | C13: 3000000 | D13: 0 | E13: 437179000 | F13: 4400000 | G13: 435779000 | H13: 0
... A286: 779000 | B286: REPRISES DE CHARGES POUR DEPRE | C286: 0 | D286: 0 | E286: 0 | F286: 925930 | G286: 0 | H286: 925930
A287: Total bilan | C287: 0 | D287: 3.0517578e-07 | E287: 2.1757276e+11 | F287: 2.1704661e+11 | G287: 5.2614863e+08 | H287: 0
A288: Total gestion | C288: 0 | D288: 0 | E288: 3.0379781e+10 | F288: 30905929932 | G288: 0 | H288: 5.2614863e+08
A289: Total hors-bilan | C289: 0 | D289: 0 | E289: 0 | F289: 0 | G289: 0 | H289: 0
A290: TOTAL SOCIETE | C290: 0 | D290: 3.0517578e-07 | E290: 2.4795254e+11 | F290: 2.4795254e+11 | G290: 0 | H290: 0
D292: =SUM(D2:D291) | E292: =SUM(E2:E291)

Sheet COUVERTURE
F4: BURKINA FASO
C6: MINISTERE DE L'ECONOMIE DES FINANCES ET DU DEVELOPPEMENT
F8: DIRECTION GENERALE DES IMPOTS
E31: LIASSE SYSTEME NORMAL

Sheet GARDE
B2: BURKINA FASO
B3: MINISTERE DE L'ECONOMIE DES FINANCES ET DU DEVELOPPEMENT
B4: DIRECTION GENERALE DES IMPOTS
C8: DGE
C12: ETATS FINANCIERS NORMALISES SYSTEME COMPTABLE OHADA (SYSCOHADA)
E16: EXERCICE CLOS LE
E17: 45291
D20: DESIGNATION DE L'ENTITE
B22: DENOMINATION SOCIALE :
B23: (ou nom et prénoms de l'exploitant)
B26: SIGLE USUEL :
B28: ADRESSE COMPLETE : | C28: 01 BP 4928 OUAGADOUGOU 01
B30: N° IFU DU CONTRIBUABLE : | D30: 00124780J
B31: N° DE TELEDECLARANT (NES): | D31: 0
B32: SYSTEME NORMAL
B33: Documents déposés | H33: Réservé à la Direction Générale des Impôts
B35: Fiche d'identification et renseignements divers | F35: x | H35: Date de dépôt
B36: Bilan | F36: x
B37: Compte de résultat | F37: x
B38: Tableau des flux de trésorerie | F38: x
B39: Notes annexes | F39: x | H39: Nom de l'agent de la DGI ayant réceptionné le dépôt
B40: Etats supplémentaires DGI | F40: x
B44: Nombre de pages déposées par exemplaire : | F44: 58 | H44: Signature de l'agent et cachet du service
B45: Nombre d'exemplaires déposés : | F45: 3

Sheet RECEVABILITE
A1: - 0 -
A3: CONDITIONS DE RECEVABILITE
B5: Entités utilisant des imprimés:
B7: * N'utilisez que des imprimés normalisés
B9: * Remplir chaque page de façon parfaitement lisible sans décalage de lignes
B11: * Ne créer aucune rubrique
B13: * Eviter toute surcharge et donner les explications sur une feuille séparée
B15: * N'utilisez que des codes indiqués dans les tables
B17: * N'utilisez que des imprimés en noir et blanc
B20: Entités produisant les états financiers à l'aide de l'outil informatique
B22: * Reproduire à l'identique la contexture des imprimés normalisés
B24: * Fournir une liasse comprenant à la fois : la fiche d'identification et renseignements divers et les états financiers correspondant au système comptable
B26: * Ne créer aucune rubrique
B28: * N'utilisez que des codes indiqués dans les tables
... B37: Les Notes annexes non chiffrées doivent êtres supprimées. Cependant, elles devront être indiquées dans la Fiche récapitulative des Notes Annexes.

Sheet NOTE36 (TABLE DES CODES)
A1: - 0 -
H2: NOTE 36 SYSTEME NORMAL
A3: Dénomination sociale de l'entité : | C3: =GARDE!D22
A4: Adresse : | B4: =GARDE!C28 | H4: Sigle usuel: | I4: =GARDE!C26
A5: N° IFU du contribuable : | C5: =GARDE!D30 | E5: Exercice clos le : | G5: =GARDE!E17 | H5: Durée (en mois) : | I5: ='FICHE R1'!U5
A6: N° de télédéclarant (NES): | C6: =GARDE!D31
A7: NOTE 36 : TABLE DES CODES
A9: 1- Code forme juridique (1) | F9: 3- Code pays du siège social
A11: Société Anonyme (SA) à participation publique | D11: 0 | E11: 0
F12: Pays UEMOA (2)
A13: Société Anonyme (SA) | D13: 0 | E13: 1
F14: Pays CEMAC (3)
A15: Société par Actions Simplifiée (SAS) | D15: 0 | E15: 2
F16: Autres pays OHADA (4)
A17: Société à Responsabilité Limitée (SARL) | D17: 0 | E17: 3 | F17: Afrique du Sud | I17: 2 | J17: 0
F18: Autres pays africains | I18: 2 | J18: 1
A19: Société en Commandite Simple (SCS) | D19: 0 | E19: 4
F20: Suisse | I20: 2 | J20: 2
A21: Société en Nom Collectif (SNC) | D21: 0 | E21: 5
F22: France | I22: 2 | J22: 3
A23: Société en Participation (SP) | D23: 0 | E23: 6
F24: Autres pays de l'Union Européenne | I24: 3 | J24: 9
A25: Groupement d'Intérêt Economique (GIE) | D25: 0 | E25: 7
F26: U.S.A. | I26: 4 | J26: 0
A27: Association | D27: 0 | E27: 8
F28: Canada | I28: 4 | J28: 1
A29: Autre forme juridique (à préciser) | D29: 0 | E29: 9 | F29: Brésil | I29: 4 | J29: 3
F30: Autres pays américains | I30: 4 | J30: 9
A31: 2 - Code régime fiscal
F32: Chine | I32: 5 | J32: 0
A33: Réel normal | E33: 1 | F33: Inde | I33: 5 | J33: 2
F34: Liban | I34: 5 | J34: 3
A35: Réel simplifié | E35: 2 | F35: Autres pays asiatiques | I35: 5 | J35: 9
F36: Russie | I36: 6 | J36: 0
A37: CME | E37: 3
F38: Autres pays | I38: 9 | J38: 9
A39: AUTRE | E39: 4
F40: (Zone monétaire = Zone franc CFA)
A42: (1) Remplacer le premier 0 par 1 si l'entreprise bénéficie d'un agrément prioritaire
A43: (2) Bénin = 01 ; Burkina = 02 ; Côte d'Ivoire = 03 ; Guinée Bissau = 04 ; Mali = 05 ; Niger = 06 ; Sénégal = 07 ; Togo = 08
A44: (3) Cameroun = 09 ; Centrafrique = 10 ; Congo = 11 ; Gabon = 12 ; Guinée Equatoriale = 13 ; Tchad = 14
A45: (4) Comores = 15 ; Guinée Conakry = 16

Sheet NOTE36 Suite (nomenclature)
A1: NOTE 36 (suite Nomenclature)
A2: Sélectionner la ou les codes activités selon le découpage de votre chiffre d'affaires pour le renseignement de la fiche R2
A6: CODES ACTIVITES ECONOMIQUES
A7: Agriculture vivrière | H7: Industries du caoutchouc et des plastiques
A8: 001 001 Culture céréalière | H8: 022 001 Fabrication du caoutchouc naturel
A9: 001 002 Culture de tubercules et plantains | H9: 022 002 Industries du caoutchouc
A10: 001 003 Culture de légumes | H10: 022 003 Fabrication de matières plastiques
A11: 001 004 Culture de condiments | H11: Fabrication d’autres produits minéraux non métalliques et de matériaux
A12: 001 005 Culture de fruits | H12: de construction
A13: 001 006 Culture d’autres produits de l’Agriculture vivrière | H13: 023 001 Industrie du verre
A14: Agriculture industrielle et d’exportation | H14: 023 002 Fabrication de produits minéraux pour la construction
A15: 002 001 Culture de canne à sucre | H15: 023 003 Fabrication d’autres produits minéraux non métalliques
A16: 002 002 Culture d’arachide d’huilerie | H16: Métallurgie et travail des métaux
A17: 002 003 Culture d’arachide de bouche | H17: 024 001 Métallurgie
A18: 002 004 Culture de tabac | H18: 024 002 Travail des métaux
... A56: 012 000 Industries laitières | H56: Postes, télécommunications

Sheet FICHE R1
A1: - 1 -
R2: FICHE R1
A3: Dénomination sociale de l'entité : | E3: =GARDE!D22
A4: Adresse : | P4: Sigle usuel : | S4: =GARDE!C26
A5: N° IFU du contribuable : | H5: Exercice clos le : | Q5: Durée (en mois) : | U5: 12
A6: N° de télédéclarant (NES) : | E6: =GARDE!D31
A7: FICHE R1 : FICHE D'IDENTIFICATION ET RENSEIGNEMENTS DIVERS 1
A8: ZA | C8: EXERCICE COMPTABLE : | M8: DU: | N8: 44927 | R8: AU: | S8: 45291
A10: ZB | C10: DATE D'ARRETE EFFECTIF DES COMPTES : | T10: ZD
A12: ZC | C12: EXERCICE PRECEDENT CLOS LE : | K12: DUREE EXERCICE PRECEDENT EN MOIS : | U12: 12
A14: ZE | J14: ZF
C15: Greffe | D15: N°Registre du Commerce | K15: N° Répertoire des entités
A17: ZG | E17: ZH | P17: ZI
C18: N° de caisse sociale | F18: N° Code Importateur | Q18: Code activité principale
A20: ZJ | C20: =+E3 | Q20: =+S4
C21: Désignation de l'entité | Q21: Sigle
A23: ZK | Q23: OUAGADOUGOU
E24: Adresse e-mail | K24: Code | N24: Boîte Postale | Q24: Ville
A26: ZL
C27: Adresse géographique complète (Immeuble, rue, quartier, ville, pays)
P28: ZN
A29: ZM
C30: Désignation précise de l'activité principale exercée par l'entité | P30: % Capacité production utile
A32: ZO
C33: Nom, adresse, téléphone, adresse e-mail et qualité de la personne à contacter en cas de demande
A35: ZP
C36: Nom, adresse, téléphone et e-mail du salarié de l'entité ou
C37: du professionnel comptable inscrit à l'Ordre des Experts-comptables ayant établi les états financiers
A39: ZQ
A43: ZR
C44: Nom, adresse, téléphone, e-mail et numéro d'inscription à l'Ordre des Experts-comptables
C45: de l'Expert comptablble ayant délivré l'attestation d'exécution de la mission du commissariat aux comptes
A47: ZS | O47: Non | T47: Oui
N48: Etats financiers approuvés par l'Assemblée Générale (cocher la case)
J49: ZW
A50: ZT | J50: Domiciliations bancaires
C51: Nom du signataire des états financiers | J51: Banque | Q51: Numéro de compte
A53: ZU
C54: Qualité du signataire des états financiers
A56: ZV
C57: Date de signature
C64: Signature

Sheet FICHE R2
A1: - 2 -
AG2: FICHE R2
A3: Dénomination sociale de l'entité :
A4: Adresse : | AC4: Sigle usuel :
A5: N° IFU du contribuable : | Q5: Exercice clos le : | AC5: Durée (en mois) : | AI5: ='FICHE R1'!U5
A6: N° de télédéclarant (NES) :
A7: FICHE R2 : FICHE D'IDENTIFICATION ET RENSEIGNEMENTS DIVERS 2
V8: Contrôle de l'Entité (cocher la case)
A9: ZX | D9: Forme juridique (1) : | Q9: 0 | R9: 1 | V9: ZZ5 | X9: Entité sous contrôle public
A11: ZY | D11: Régime fiscal (1) : | Q11: 1 | V11: ZZ6 | X11: Entité sous contrôle privé national | AK11: X
A13: ZZ1 | D13: Pays du siège social (1) : | Q13: 0 | R13: 2 | V13: ZZ7 | X13: Entité sous contrôle privé étranger
A15: ZZ2 | D15: Nombre d'établissements dans le pays : | Q15: 0 | R15: 1
A17: ZZ3 | D17: Nombre d'établissements hors du pays pour | Q17: 0 | R17: 0
D18: lesquels une comptabilité distincte est tenue :
A20: ZZ4 | D20: Première année d'exercice dans le pays : | Q20: 2 | R20: 0 | S20: 2 | T20: 1
A23: ACTIVITE DE L'ENTITE
A25: Désignation de l'activité (2) | P25: Code nomenclature d'activité (1) | Y25: Chiffre d'affaires HT (CA HT) ou Valeur ajoutée (VA) (3) (4) | AI25: % activité dans le CA HT ou la VA
A52: Divers (4)
P54: TOTAL | Z54: =Z29+Z32+Z35+Z38+Z41+Z44+Z47+Z50+Z52
A57: (1) Note 36 Suite (Nomenclature)
A58: (2) Lister de manière précise les activités dans l'ordre décroissant du C.A.HT ou de la valeur ajoutée (V.A).
A59: (3) Rayer la mention inutile - Au Burkina Faso, pour les besoins de l'INSD, on préfèrera le chiffre d'affaires.
A60: (4) Indiquer dans la note annexe n°21 "Chiffre d'affaires et autres produits", la liste détaillée des activités classées dans la rubrique "Divers"

Sheet FICHE R3
A1: - 3 -
I2: FICHE R3
A3: Dénomination sociale de l'entité : | C3: ='FICHE R1'!E3
A4: Adresse : | B4: ='FICHE R1'!D4 | H4: Sigle usuel : | J4: ='FICHE R1'!S4
A5: N° IFU du contribuable : | C5: ='FICHE R1'!E5 | E5: Exercice clos le : | F5: ='FICHE R1'!J5 | H5: Durée (en mois) : | J5: ='FICHE R1'!U5
A6: N° de télédéclarant (NES) : | C6: ='FICHE R1'!E6
A7: FICHE R3 : FICHE D'IDENTIFICATION ET RENSEIGNEMENTS DIVERS 3
A8: DIRIGEANTS (1)
A10: Nom et Prénoms | C10: Nationalité | D10: Autres nationalités (à préciser) (2) | E10: Qualité | F10: N° d'identification fiscale | H10: Adresse (BP, ville, pays, adresse géographique et adresse email)
A22: (1) Dirigeants = Président Directeur Général, Directeur Général, Administrateur Général, Gérant, Autres.
A23: (2) En cas de double nationalité
A24: MEMBRES DU CONSEIL D'ADMINISTRATION
A26: Nom et Prénoms | C26: Structure représentée | E26: Qualité | G26: Adresse (BP, ville, pays, adresse géographique et adresse email)

Sheet FICHE R4
I2: FICHE R4
A3: Dénomination sociale de l'entité : | C3: =GARDE!D22
A4: Adresse : | H4: Sigle usuel : | I4: =GARDE!C26
A5: N° IFU du contribuable : | E5: Exercice clos le : | H5: Durée (en mois) : | I5: =TFT!J5
A6: N° de télédéclarant (NES): | C6: =GARDE!D31
A7: FICHE R4 : FICHE RECAPITULATIVE DES NOTES ANNEXES PRESENTEES (1)
A8: NOTES | B8: INTITULES | I8: A | J8: N/A
A9: NOTE 1 | B9: DETTES GARANTIES PAR DES SURETES REELLES ET LES ENGAGEMENTS FINANCIERS
A10: NOTE 2 | B10: INFORMATIONS OBLIGATOIRES
A11: NOTE 3A | B11: IMMOBILISATIONS BRUTES
A12: NOTE 3B | B12: BIENS PRIS EN LOCATION-ACQUISITION
A13: NOTE 3C | B13: IMMOBILISATIONS : AMORTISSEMENTS
A14: NOTE 3C bis | B14: IMMOBILISATIONS : DEPRECIATIONS
A15: NOTE 3D | B15: IMMOBILISATIONS : PLUS-VALUES ET MOINS VALUE DE CESSION
A16: NOTE 3E | B16: INFORMATIONS SUR LES REEVALUATIONS EFFECTUEES PAR L'ENTITE
A17: NOTE 4 | B17: IMMOBILISATIONS FINANCIERES
A18: NOTE 5 | B18: ACTIF CIRCULANT ET DETTES CIRCULANTES HAO
A19: NOTE 6 | B19: STOCKS ET ENCOURS
A20: NOTE 7 | B20: CLIENTS
... A61: ETATS DGI | B61: ETATS SUPPLEMENTAIRES DGI
A63: (1) les Notes non documentées ne doivent pas être jointes aux états financiers. Leur contenu peut être amélioré par les entités Par ailleurs, dans une note, les lignes non chiffrées doivent être supprimées. Par exemple, dans la note 24 Services Extérieurs, lorsque la ligne sous-traitance générale n'est pas chiffrée, elle ne doit pas figurer dans les notes.
A64: (2) A : Applicable A/N : Non applicable.
A65: Par exemple pour une entité qui n'a pas de stocks et en-cours, elle doit cocher à l'intersection ('ligne NOTE 6' & 'colonne N/A')

Sheet BILAN
A1: - 4 -
L2: BILAN SYSTEME NORMAL PAGE 1/1
A3: Dénomination sociale de l'entité : | C3: =+GARDE!D22
A4: Adresse : | C4: =+GARDE!C28 | L4: Sigle usuel : | N4: =GARDE!C26
A5: N° IFU du contribuable : | C5: =GARDE!D30 | I5: Exercice clos le : | K5: =GARDE!E17 | L5: Durée (en mois) : | N5: 12
A6: N° de télédéclarant (NES): | C6: =GARDE!D31
A7: BILAN
A8: REF | B8: ACTIF | E8: NOTE | F8: EXERCICE au 31/12/ N | I8: EXERCICE AU 31/12/N-1 | J8: REF | K8: PASSIF | L8: NOTE | M8: EXERCICE AU 31/12/N | N8: EXERCICE AU 31/12/N-1
F10: BRUT | G10: AMORT et DEPREC. | H10: NET | I10: NET | M10: NET | N10: NET
A11: AD | B11: IMMOBILISATIONS INCORPORELLES | E11: 3 | F11: =CtaCptSolde("20*","21*") | G11: =-CtaCptSolde("280*","281*")-CtaCptSolde("290*","291*") | H11: =[A_AD.EtLoc]=CtaCptSolde("20*","21*")+CtaCptSolde("280*","281*")+CtaCptSolde("290*","291*") | I11: =[A_AD_N1.EtLoc]=CtaCptSoldeNm1("20*","21*")+CtaCptSoldeNm1("280*","281*")+CtaCptSoldeNm1("290*","291*") | J11: CA | K11: Capital | L11: 13 | M11: =[P_CA.EtLoc]=CtaCptSoldeCrédit("10*") | N11: =[P_CA_N1.EtLoc]=CtaCptSoldeCréditNm1("10*")
A12: AE | B12: Frais de développement et de prospection | F12: =CtaCptSolde("20*") | G12: =-CtaCptSolde("280*")-CtaCptSolde("290*") | H12: =CtaCptSolde("20*")+CtaCptSolde("280*")+CtaCptSolde("290*") | I12: =CtaCptSoldeNm1("20*")+CtaCptSoldeNm1("280*")+CtaCptSoldeNm1("290*") | J12: CB | K12: Apporteurs capital non appelé (-) | L12: 13
A13: AF | B13: Brevets, licences, logiciels et droits similaires | F13: =CtaCptSolde("21*") | G13: =-CtaCptSolde("281*")-CtaCptSolde("291*") | H13: =CtaCptSolde("21*")+CtaCptSolde("281*")+CtaCptSolde("291*") | I13: =CtaCptSoldeNm1("21*")+CtaCptSoldeNm1("281*")+CtaCptSoldeNm1("291*") | J13: CD | K13: Primes liées au capital social | L13: 14
A14: AG | B14: Fonds commercial et droit au bail | J14: CE | K14: Ecarts de réévaluation | L14: 3e
A15: AH | B15: Autres immobilisations incorporelles | J15: CF | K15: Réserves indisponibles | L15: 14
A16: AI | B16: IMMOBILISATIONS CORPORELLES | E16: 3 | F16: =CtaCptSolde("22*","245*") | G16: =-CtaCptSolde("282*","2849*")-CtaCptSolde("292*","2949*") | H16: =[A_AI.EtLoc]=CtaCptSolde("22*","245*")+CtaCptSolde("282*","2849*")+CtaCptSolde("292*","2949*") | I16: =[A_AI_N1.EtLoc]=CtaCptSoldeNm1("22*","245*")+CtaCptSoldeNm1("282*","2849*")+CtaCptSoldeNm1("292*","2949*") | J16: CG | K16: Réserves libres | L16: 14 | M16: =[P_CG.EtLoc]=CtaCptSoldeCrédit("11*") | N16: =[P_CG_N1.EtLoc]=CtaCptSoldeCréditNm1("11*")
A17: AJ | B17: Terrains (1) dont Placement Net : | F17: =CtaCptSolde("22*") | G17: =-CtaCptSolde("282*")-CtaCptSolde("292*") | H17: =CtaCptSolde("22*")+CtaCptSolde("282*")+CtaCptSolde("292*") | I17: =CtaCptSoldeNm1("22*")+CtaCptSoldeNm1("282*")+CtaCptSoldeNm1("292*") | J17: CH | K17: Report à nouveau (+ ou -) | L17: 14 | M17: =[P_CH.EtLoc]=-CtaCptSolde("12*") | N17: =[P_CH_N1.EtLoc]=-CtaCptSoldeNm1("12*")
A18: AK | B18: Bâtiments(1) dont Placement Net : | F18: =CtaCptSolde("231*","233*") | G18: =-CtaCptSolde("2831*","2833*")-CtaCptSolde("2931*","2933*") | H18: =CtaCptSolde("231*","233*")+CtaCptSolde("2831*","2833*")+CtaCptSolde("2931*","2933*") | I18: =CtaCptSoldeNm1("231*","233*")+CtaCptSoldeNm1("2831*","2833*")+CtaCptSoldeNm1("2931*","2933*") | J18: CJ | K18: Résultat net de l'exercice (bénéfice + ou perte -) | M18: =[P_CJ.EtLoc]=-CtaCptSolde("7*")-CtaCptSolde("6*") | N18: =[P_CJ_N1.EtLoc]=-CtaCptSoldeNm1("7*")-CtaCptSoldeNm1("6*")
A19: AL | B19: Aménagements, agencements et installations | F19: =CtaCptSolde("234*","239*") | G19: =-CtaCptSolde("2834*","2839*")-CtaCptSolde("2934*","2939*") | H19: =CtaCptSolde("234*","239*")+CtaCptSolde("2834*","2839*")+CtaCptSolde("2934*","2939*") | I19: =CtaCptSoldeNm1("234*","239*")+CtaCptSoldeNm1("2834*","2839*")+CtaCptSoldeNm1("2934*","2939*") | J19: CL | K19: Subventions d'investissement | L19: 15 | M19: =[P_CL.EtLoc]=CtaCptSoldeCrédit("14*") | N19: =[P_CL_N1.EtLoc]=CtaCptSoldeCréditNm1("14*")
A20: AM | B20: Matériel, mobilier et actifs biologiques | F20: =CtaCptSolde("240*","244*") | G20: =-CtaCptSolde("2840*","2844*")-CtaCptSolde("2940*","2944*") | H20: =CtaCptSolde("240*","244*")+CtaCptSolde("2840*","2844*")+CtaCptSolde("2940*","2944*") | I20: =CtaCptSoldeNm1("240*","244*")+CtaCptSoldeNm1("2840*","2844*")+CtaCptSoldeNm1("2940*","2944*") | J20: CM | K20: Provisions réglementées | L20: 15 | M20: =[P_CM.EtLoc]=CtaCptSoldeCrédit("15*") | N20: =[P_CM_N1.EtLoc]=CtaCptSoldeCréditNm1("15*")
A21: AN | B21: Matériel de transport | F21: =CtaCptSolde("245*") | G21: =-CtaCptSolde("2845*","2849*")-CtaCptSolde("2945*","2949*") | H21: =CtaCptSolde("245*")+CtaCptSolde("2845*","2849*")+CtaCptSolde("2945*","2949*") | I21: =CtaCptSoldeNm1("245*")+CtaCptSoldeNm1("2845*","2849*")+CtaCptSoldeNm1("2945*","2949*") | J21: CP | K21: TOTAL CAPITAUX PROPRES ET RESSOURCES ASSIMILEES | M21: =[P_CP.EtLoc]=[P_CA.EtLoc]+[P_CG.EtLoc]+[P_CH.EtLoc]+[P_CJ.EtLoc]+[P_CL.EtLoc]+[P_CM.EtLoc] | N21: =[P_CP_N1.EtLoc]=[P_CA_N1.EtLoc]+[P_CG_N1.EtLoc]+[P_CH_N1.EtLoc]+[P_CJ_N1.EtLoc]+[P_CL_N1.EtLoc]+[P_CM_N1.EtLoc]
A22: AP | B22: AVANCES ET ACOMPTES VERSES SUR IMMOBILISATIONS | E22: 3 | F22: =CtaCptSolde("25*") | G22: =-CtaCptSolde("2850*","2859*")-CtaCptSolde("2950*","2959*") | H22: =[A_AP.EtLoc]=CtaCptSolde("25*")+CtaCptSolde("2850*","2859*")+CtaCptSolde("2950*","2959*") | I22: =[A_AP_N1.EtLoc]=CtaCptSoldeNm1("25*")+CtaCptSoldeNm1("2850*","2859*")+CtaCptSoldeNm1("2950*","2959*") | J22: DA | K22: Emprunts et dettes financières diverses | L22: 16 | M22: =[P_DA.EtLoc]=CtaCptSoldeCrédit("16*","17*") | N22: =[P_DA_N1.EtLoc]=CtaCptSoldeCréditNm1("16*","17*")
A23: AQ | B23: IMMOBILISATIONS FINANCIERES | E23: 4 | F23: =CtaCptSolde("26*","27*") | G23: =-CtaCptSolde("2860*","2869*")-CtaCptSolde("2960*","2969*") | H23: =[A_AQ.EtLoc]=CtaCptSolde("26*","27*")+CtaCptSolde("2860*","2869*")+CtaCptSolde("2960*","2969*") | I23: =[A_AQ_N1.EtLoc]=CtaCptSoldeNm1("26*","27*")+CtaCptSoldeNm1("2860*","2869*")+CtaCptSoldeNm1("2960*","2969*") | J23: DB | K23: Dettes de location-acquisition | L23: 16
A24: AR | B24: Titres de participation | F24: =CtaCptSolde("26*") | G24: =-CtaCptSolde("2860*","2865*")-CtaCptSolde("2960*","2965*") | H24: =CtaCptSolde("26*")+CtaCptSolde("2860*","2865*")+CtaCptSolde("2960*","2965*") | I24: =CtaCptSoldeNm1("26*")+CtaCptSoldeNm1("2860*","2865*")+CtaCptSoldeNm1("2960*","2965*") | J24: DC | K24: Provisions pour risques et charges | L24: 16 | M24: =[P_DC.EtLoc]=CtaCptSolde("19*") | N24: =[P_DC_N1.EtLoc]=CtaCptSoldeNm1("19*")
A25: AS | B25: Autres immobilisations financières | F25: =CtaCptSolde("27*") | G25: =-CtaCptSolde("2866*","2869*")-CtaCptSolde("2966*","2969*") | H25: =CtaCptSolde("27*")+CtaCptSolde("2866*","2869*")+CtaCptSolde("2966*","2969*") | I25: =CtaCptSoldeNm1("27*")+CtaCptSoldeNm1("2866*","2869*")+CtaCptSoldeNm1("2966*","2969*") | J25: DD | K25: TOTAL DETTES FINANCIERES ET RESSOURCES ASSIMILEES | M25: =[P_DD.EtLoc]=[P_DA.EtLoc]+[P_DC.EtLoc] | N25: =[P_DD_N1.EtLoc]=[P_DA_N1.EtLoc]+[P_DC_N1.EtLoc]
A26: AZ | B26: TOTAL ACTIF IMMOBILISE | F26: =CtaCptSolde("20*","27*") | G26: =-CtaCptSolde("280*","2869*")-CtaCptSolde("290*","2969*") | H26: =[A_AZ.EtLoc]=[A_AD.EtLoc]+[A_AI.EtLoc]+[A_AP.EtLoc]+[A_AQ.EtLoc] | I26: =[A_AZ_N1.EtLoc]=[A_AD_N1.EtLoc]+[A_AI_N1.EtLoc]+[A_AP_N1.EtLoc]+[A_AQ_N1.EtLoc] | J26: DF | K26: TOTAL RESSOURCES STABLES | M26: =[P_DF.EtLoc]=[P_CP.EtLoc]+[P_DD.EtLoc] | N26: =[P_DF_N1.EtLoc]=[P_CP_N1.EtLoc]+[P_DD_N1.EtLoc]
A27: BA | B27: ACTIF CIRCULANT HAO | E27: 5 | F27: =CtaCptSoldeDébit("47*","49*") | H27: =[A_BA.EtLoc]=CtaCptSoldeDébit("47*","49*") | I27: =[A_BA_N1.EtLoc]=CtaCptSoldeDébitNm1("47*","49*") | J27: DH | K27: Dettes circulantes HAO | L27: 5 | M27: =[P_DH.EtLoc]=CtaCptSoldeCrédit("47*","49*") | N27: =[P_DH_N1.EtLoc]=CtaCptSoldeCréditNm1("47*","49*")
A28: BB | B28: STOCKS ET ENCOURS | E28: 6 | F28: =CtaCptSoldeDébit("3*","39*")-CtaCptSoldeCrédit("3*","39*") | H28: =[A_BB.EtLoc]=CtaCptSoldeDébit("3*","39*")-CtaCptSoldeCrédit("3*","39*") | I28: =[A_BB_N1.EtLoc]=CtaCptSoldeDébitNm1("3*","39*")-CtaCptSoldeCréditNm1("3*","39*") | J28: DI | K28: Clients, avances reçues | L28: 7 | M28: =[P_DI.EtLoc]=CtaCptSoldeCrédit("41*") | N28: =[P_DI_N1.EtLoc]=CtaCptSoldeCréditNm1("41*")
A29: BG | B29: CREANCES ET EMPLOIS ASSIMILES | F29: =CtaCptSoldeDébit("40*","46*") | H29: =[A_BH.EtLoc]+[A_BI.EtLoc]+[A_BJ.EtLoc] | I29: =[A_BH_N1.EtLoc]+[A_BI_N1.EtLoc]+[A_BJ_N1.EtLoc] | J29: DJ | K29: Fournisseurs d'exploitation | L29: 17 | M29: =[P_DJ.EtLoc]=CtaCptSoldeCrédit("40*") | N29: =[P_DJ_N1.EtLoc]=CtaCptSoldeCréditNm1("40*")
A30: BH | B30: Fournisseurs avances versées | E30: 17 | F30: =CtaCptSoldeDébit("40*") | H30: =[A_BH.EtLoc]=CtaCptSoldeDébit("40*") | I30: =[A_BH_N1.EtLoc]=CtaCptSoldeDébitNm1("40*") | J30: DK | K30: Dettes fiscales et sociales | L30: 18 | M30: =[P_DK.EtLoc]=CtaCptSoldeCrédit("42*","45*") | N30: =[P_DK_N1.EtLoc]=CtaCptSoldeCréditNm1("42*","45*")
A31: BI | B31: Clients | E31: 7 | F31: =CtaCptSoldeDébit("41*") | H31: =[A_BI.EtLoc]=CtaCptSoldeDébit("41*") | I31: =[A_BI_N1.EtLoc]=CtaCptSoldeDébitNm1("41*") | J31: DM | K31: Autres dettes | L31: 19 | M31: =[P_DM.EtLoc]=CtaCptSoldeCrédit("46*") | N31: =[P_DM_N1.EtLoc]=CtaCptSoldeCréditNm1("46*")
A32: BJ | B32: Autres créances | E32: 8 | F32: =CtaCptSoldeDébit("42*","46*") | H32: =[A_BJ.EtLoc]=CtaCptSoldeDébit("42*","46*") | I32: =[A_BJ_N1.EtLoc]=CtaCptSoldeDébitNm1("42*","46*") | J32: DN | K32: Provisions pour risques et charges à court terme | L32: 19
A33: BK | B33: TOTAL ACTIF CIRCULANT | F33: =CtaCptSoldeDébit("3*","46*") | H33: =[A_BK.EtLoc]=[A_BA.EtLoc]+[A_BB.EtLoc]+[A_BH.EtLoc]+[A_BI.EtLoc]+[A_BJ.EtLoc] | I33: =[A_BK_N1.EtLoc]=[A_BA_N1.EtLoc]+[A_BB_N1.EtLoc]+[A_BH_N1.EtLoc]+[A_BI_N1.EtLoc]+[A_BJ_N1.EtLoc] | J33: DP | K33: TOTAL PASSIF CIRCULANT | M33: =[P_DP.EtLoc]=[P_DH.EtLoc]+[P_DI.EtLoc]+[P_DJ.EtLoc]+[P_DK.EtLoc]+[P_DM.EtLoc] | N33: =[P_DP_N1.EtLoc]=[P_DH_N1.EtLoc]+[P_DI_N1.EtLoc]+[P_DJ_N1.EtLoc]+[P_DK_N1.EtLoc]+[P_DM_N1.EtLoc]
A34: BQ | B34: Titres de placement | E34: 9 | F34: =CtaCptSoldeDébit("50*") | H34: =[A_BQ.EtLoc]=CtaCptSoldeDébit("50*") | I34: =[A_BQ_N1.EtLoc]=CtaCptSoldeDébitNm1("50*")
A35: BR | B35: Valeurs à encaisser | E35: 10 | F35: =CtaCptSoldeDébit("51*") | H35: =[A_BR.EtLoc]=CtaCptSoldeDébit("51*") | I35: =[A_BR_N1.EtLoc]=CtaCptSoldeDébitNm1("51*") | J35: DQ | K35: Banques, crédits d'escompte | L35: 20 | M35: =[P_DQ.EtLoc]=CtaCptSoldeCrédit("50*","56*") | N35: =[P_DQ_N1.EtLoc]=CtaCptSoldeCréditNm1("50*","56*")
A36: BS | B36: Banques, chèques postaux, caisse et assimilés | E36: 11 | F36: =CtaCptSoldeDébit("52*","59*") | H36: =[A_BS.EtLoc]=CtaCptSoldeDébit("52*","59*") | I36: =[A_BS_N1.EtLoc]=CtaCptSoldeDébitNm1("52*","59*") | J36: DR | K36: Banques, établissements financiers et crédits de trésorerie | L36: 20 | M36: =[P_DR.EtLoc]=CtaCptSoldeCrédit("57*","59*") | N36: =[P_DR_N1.EtLoc]=CtaCptSoldeCréditNm1("57*","59*")
A37: BT | B37: TOTAL TRESORERIE-ACTIF | F37: =CtaCptSoldeDébit("50*","59*") | H37: =[A_BT.EtLoc]=[A_BQ.EtLoc]+[A_BR.EtLoc]+[A_BS.EtLoc] | I37: =[A_BT_N1.EtLoc]=[A_BQ_N1.EtLoc]+[A_BR_N1.EtLoc]+[A_BS_N1.EtLoc] | J37: DT | K37: TOTAL TRESORERIE-PASSIF | M37: =[P_DT.EtLoc]=[P_DQ.EtLoc]+[P_DR.EtLoc] | N37: =[P_DT_N1.EtLoc]=[P_DQ_N1.EtLoc]+[P_DR_N1.EtLoc]
A38: BU | B38: Ecart de conversion-Actif | E38: 12 | J38: DV | K38: Ecart de conversion-Passif | L38: 12
A39: BZ | B39: TOTAL GENERAL | F39: =CtaCptSoldeDébit("20*","59*") | H39: =[A_BZ.EtLoc]=[A_AZ.EtLoc]+[A_BK.EtLoc]+[A_BT.EtLoc] | I39: =[A_BZ_N1.EtLoc]=[A_AZ_N1.EtLoc]+[A_BK_N1.EtLoc]+[A_BT_N1.EtLoc] | J39: DZ | K39: TOTAL GENERAL | M39: =[P_DZ.EtLoc]=[P_DF.EtLoc]+[P_DP.EtLoc]+[P_DT.EtLoc] | N39: =[P_DZ_N1.EtLoc]=[P_DF_N1.EtLoc]+[P_DP_N1.EtLoc]+[P_DT_N1.EtLoc]

Sheet RESULTAT
A1: - 5 -
H2: COMPTE DE RESULTAT SYSTEME NORMAL PAGE 1/1
A3: Dénomination sociale de l'entité : | C3: =BILAN!C3
A4: Adresse : | C4: =BILAN!C4 | I4: Sigle usuel : | J4: =BILAN!N4
A5: N° IFU du contribuable : | C5: =BILAN!C5 | E5: Exercice clos le : | F5: =BILAN!K5 | I5: Durée (en mois) : | J5: =BILAN!N5
A6: N° de télédéclarant (NES): | C6: ='FICHE R1'!E6
A7: COMPTE DE RESULTAT
A8: REF | B8: LIBELLES | G8: (1) | H8: NOTE | I8: EXERCICE AU 31/12/N | J8: EXERCICE AU 31/12/N-1
I10: NET | J10: NET
A11: TA | B11: Ventes de marchandises | F11: A | G11: + | H11: 21 | I11: =[011.EtLoc]=-CtaCptSolde("70*","701*") | J11: =[011N1.EtLoc]=-CtaCptSoldeNm1("70*","701*")
A12: RA | B12: Achats de marchandises | G12: - | H12: 22 | I12: =[021.EtLoc]=CtaCptSolde("601*") | J12: =[021N1.EtLoc]=CtaCptSoldeNm1("601*")
A13: RB | B13: Variation de stocks de marchandises | G13: -/+ | H13: 6 | I13: =[022.EtLoc]=CtaCptSolde("6031*") | J13: =[022N1.EtLoc]=CtaCptSoldeNm1("6031*")
A14: XA | B14: MARGE COMMERCIALE (Somme TA à RB) | I14: =[031.EtLoc]=[011.EtLoc]-[021.EtLoc]-[022.EtLoc] | J14: =[031N1.EtLoc]=[011N1.EtLoc]-[021N1.EtLoc]-[022N1.EtLoc]
A15: TB | B15: Ventes de produits fabriqués | F15: B | G15: + | H15: 21 | I15: =[041.EtLoc]=-CtaCptSolde("702*","704*") | J15: =[041N1.EtLoc]=-CtaCptSoldeNm1("702*","704*")
A16: TC | B16: Travaux, services vendus | F16: C | G16: + | H16: 21 | I16: =[051.EtLoc]=-CtaCptSolde("705*","706*") | J16: =[051N1.EtLoc]=-CtaCptSoldeNm1("705*","706*")
A17: TD | B17: Produits accessoires | F17: D | G17: + | H17: 21 | I17: =[061.EtLoc]=-CtaCptSolde("707*") | J17: =[061N1.EtLoc]=-CtaCptSoldeNm1("707*")
A18: XB | B18: CHIFFRE D'AFFAIRES (A + B + C + D) | I18: =[071.EtLoc]=[041.EtLoc]+[051.EtLoc]+[061.EtLoc]+[011.EtLoc] | J18: =[071N1.EtLoc]=[041N1.EtLoc]+[051N1.EtLoc]+[061N1.EtLoc]+[011N1.EtLoc]
A19: TE | B19: Production stockée (ou déstockage) | G19: -/+ | H19: 6 | I19: =[062.EtLoc]=-CtaCptSolde("713*") | J19: =[062N1.EtLoc]=-CtaCptSoldeNm1("713*")
A20: TF | B20: Production immobilisée | H20: 21 | I20: =[052.EtLoc]=-CtaCptSolde("72*","73*") | J20: =[052N1.EtLoc]=-CtaCptSoldeNm1("72*","73*")
A21: TG | B21: Subventions d’exploitation | H21: 21 | I21: =[072.EtLoc]=-CtaCptSolde("71*") | J21: =[072N1.EtLoc]=-CtaCptSoldeNm1("71*")
A22: TH | B22: Autres produits | G22: + | H22: 21 | I22: =[082.EtLoc]=-CtaCptSolde("74*","76*") | J22: =[082N1.EtLoc]=-CtaCptSoldeNm1("74*","76*")
A23: TI | B23: Transferts de charges d'exploitation | G23: + | H23: 12 | I23: =[092.EtLoc]=-CtaCptSolde("781*") | J23: =[092N1.EtLoc]=-CtaCptSoldeNm1("781*")
A24: RC | B24: Achats de matières premières et fournitures liées | G24: - | H24: 22 | I24: =[101.EtLoc]=-CtaCptSolde("601*","602*") | J24: =[101N1.EtLoc]=-CtaCptSoldeNm1("601*","602*")
A25: RD | B25: Variation de stocks de matières premières et fournitures liées | G25: -/+ | H25: 6 | I25: =[102.EtLoc]=-CtaCptSolde("6032*") | J25: =[102N1.EtLoc]=-CtaCptSoldeNm1("6032*")
A26: RE | B26: Autres achats | G26: - | H26: 22 | I26: =[201.EtLoc]=-CtaCptSolde("604*","609*") | J26: =[201N1.EtLoc]=-CtaCptSoldeNm1("604*","609*")
A27: RF | B27: Variation de stocks d’autres approvisionnements | G27: -/+ | H27: 6 | I27: =[202.EtLoc]=-CtaCptSolde("6033*","6038*") | J27: =[202N1.EtLoc]=-CtaCptSoldeNm1("6033*","6038*")
A28: RG | B28: Transports | G28: - | H28: 23 | I28: =[301.EtLoc]=-CtaCptSolde("61*") | J28: =[301N1.EtLoc]=-CtaCptSoldeNm1("61*")
A29: RH | B29: Services extérieurs | G29: - | H29: 24 | I29: =[302.EtLoc]=-CtaCptSolde("62*","63*") | J29: =[302N1.EtLoc]=-CtaCptSoldeNm1("62*","63*")
A30: RI | B30: Impôts et taxes | G30: - | H30: 25 | I30: =[401.EtLoc]=-CtaCptSolde("64*") | J30: =[401N1.EtLoc]=-CtaCptSoldeNm1("64*")
A31: RJ | B31: Autres charges | G31: - | H31: 26 | I31: =[402.EtLoc]=-CtaCptSolde("65*") | J31: =[402N1.EtLoc]=-CtaCptSoldeNm1("65*")
A32: XC | B32: VALEUR AJOUTEE (XB +RA+RB) + (somme TE à RJ) | I32: =[091.EtLoc]=[071.EtLoc]+[062.EtLoc]+[052.EtLoc]+[072.EtLoc]+[082.EtLoc]+[092.EtLoc]+[101.EtLoc]+[102.EtLoc]+[201.EtLoc]+[202.EtLoc]+[301.EtLoc]+[302.EtLoc]+[401.EtLoc]+[402.EtLoc] | J32: =[091N1.EtLoc]=[071N1.EtLoc]+[062N1.EtLoc]+[052N1.EtLoc]+[072N1.EtLoc]+[082N1.EtLoc]+[092N1.EtLoc]+[101N1.EtLoc]+[102N1.EtLoc]+[201N1.EtLoc]+[202N1.EtLoc]+[301N1.EtLoc]+[302N1.EtLoc]+[401N1.EtLoc]+[402N1.EtLoc]
A33: RK | B33: Charges de personnel | G33: - | H33: 27 | I33: =[121.EtLoc]=CtaCptSolde("66*") | J33: =[121N1.EtLoc]=CtaCptSoldeNm1("66*")
A34: XD | B34: EXCEDENT BRUT D'EXPLOITATION (XC+RK) | I34: =[131.EtLoc]=[091.EtLoc]-([121.EtLoc]) | J34: =[131N1.EtLoc]=[091N1.EtLoc]-([121N1.EtLoc])
A35: TJ | B35: Reprises d’amortissements, provisions et dépréciations | G35: + | H35: 28 | I35: =[141.EtLoc]=-CtaCptSolde("78*") | J35: =[141N1.EtLoc]=-CtaCptSoldeNm1("78*")
A36: RL | B36: Dotations aux amortissements, aux provisions et dépréciations | G36: - | H36: 3C&28 | I36: =[171.EtLoc]=CtaCptSolde("68*") | J36: =[171N1.EtLoc]=CtaCptSoldeNm1("68*")
A37: XE | B37: RESULTAT D'EXPLOITATION (XD+TJ+ RL) | I37: =[191.EtLoc]=[131.EtLoc]+[141.EtLoc]-[171.EtLoc] | J37: =[191N1.EtLoc]=[131N1.EtLoc]+[141N1.EtLoc]-[171N1.EtLoc]
A38: TK | B38: Revenus financiers et assimilés | G38: + | H38: 29 | I38: =[211.EtLoc]=-CtaCptSolde("77*") | J38: =[211N1.EtLoc]=-CtaCptSoldeNm1("77*")
A39: TL | B39: Reprises de provisions et dépréciations financières | G39: + | H39: 28 | I39: =[212.EtLoc]=-CtaCptSolde("797*") | J39: =[212N1.EtLoc]=-CtaCptSoldeNm1("797*")
A40: TM | B40: Transferts de charges financières | G40: + | H40: 12 | I40: =[221.EtLoc]=-CtaCptSolde("787*") | J40: =[221N1.EtLoc]=-CtaCptSoldeNm1("787*")
A41: RM | B41: Frais financiers et charges assimilées | G41: - | H41: 29 | I41: =[231.EtLoc]=CtaCptSolde("67*") | J41: =[231N1.EtLoc]=CtaCptSoldeNm1("67*")
A42: RN | B42: Dotations aux provisions et aux dépréciations financières | G42: - | H42: 3C&28 | I42: =[232.EtLoc]=CtaCptSolde("687*") | J42: =[232N1.EtLoc]=CtaCptSoldeNm1("687*")
A43: XF | B43: RESULTAT FINANCIER (somme TK à RN) | I43: =[241.EtLoc]=[211.EtLoc]+[212.EtLoc]+[221.EtLoc]-[231.EtLoc]-[232.EtLoc] | J43: =[241N1.EtLoc]=[211N1.EtLoc]+[212N1.EtLoc]+[221N1.EtLoc]-[231N1.EtLoc]-[232N1.EtLoc]
A44: XG | B44: RESULTAT DES ACTIVITES ORDINAIRES (XE+XF) | I44: =[242.EtLoc]=[191.EtLoc]+[241.EtLoc] | J44: =[242N1.EtLoc]=[191N1.EtLoc]+[241N1.EtLoc]
A45: TN | B45: Produits des cessions d'immobilisations | G45: + | H45: 3D | I45: =[271.EtLoc]=-CtaCptSolde("84*") | J45: =[271N1.EtLoc]=-CtaCptSoldeNm1("84*")
A46: TO | B46: Autres Produits HAO | G46: + | H46: 30 | I46: =[251.EtLoc]=-CtaCptSolde("82*") | J46: =[251N1.EtLoc]=-CtaCptSoldeNm1("82*")
A47: RO | B47: Valeurs comptables des cessions d'immobilisations | G47: - | H47: 3D | I47: =[261.EtLoc]=CtaCptSolde("81*")+CtaCptSolde("83*") | J47: =[261N1.EtLoc]=CtaCptSoldeNm1("81*")+CtaCptSoldeNm1("83*")
A48: RP | B48: Autres Charges HAO | G48: - | H48: 30 | I48: =[262.EtLoc]=CtaCptSolde("85*") | J48: =[262N1.EtLoc]=CtaCptSoldeNm1("85*")
A49: XH | B49: RESULTAT HORS ACTIVITES ORDINAIRES (somme TN à RP) | I49: =[272.EtLoc]=[271.EtLoc]+[251.EtLoc]-[261.EtLoc]-[262.EtLoc] | J49: =[272N1.EtLoc]=[271N1.EtLoc]+[251N1.EtLoc]-[261N1.EtLoc]-[262N1.EtLoc]
A50: RQ | B50: Participation des travailleurs | G50: - | H50: 30 | I50: =[281.EtLoc]=CtaCptSolde("87*") | J50: =[281N1.EtLoc]=CtaCptSoldeNm1("87*")
A51: RS | B51: Impôts sur le résultat | G51: - | H51: 37 | I51: =[291.EtLoc]=CtaCptSolde("89*") | J51: =[291N1.EtLoc]=CtaCptSoldeNm1("89*")
A52: XI | B52: RESULTAT NET (XG+XH+RQ+RS) | I52: =[332.EtLoc]=[191.EtLoc]+[241.EtLoc]+[272.EtLoc]-[281.EtLoc]-[291.EtLoc] | J52: =[332N1.EtLoc]=[191N1.EtLoc]+[241N1.EtLoc]+[272N1.EtLoc]-[281N1.EtLoc]-[291N1.EtLoc]
A53: (1) (+/-) : Solde débiteur "(-)", solde créditeur "(+)"

Sheet TFT
A1: - 6 -
H2: FLUX DE TRESORERIE SYSTEME NORMAL PAGE 1/1
A3: Dénomination sociale de l'entité : | C3: =BILAN!C3
A4: Adresse : | C4: =BILAN!C4 | I4: Sigle usuel : | J4: =BILAN!N4
A5: N° IFU du contribuable : | C5: =BILAN!C5 | E5: Exercice clos le : | F5: =BILAN!K5 | I5: Durée (en mois) : | J5: =BILAN!N5
A6: N° de télédéclarant (NES): | C6: =GARDE!D31
A7: TABLEAU DES FLUX DE TRESORERIE
A8: REF | B8: LIBELLES | H8: NOTE | I8: EXERCICE | J8: EXERCICE
I9: N | J9: N-1
A10: ZA | B10: Trésorerie nette au 1er janvier (Trésorerie actif N-1 - Trésorerie passif N-1) | G10: A | I10: =[ZZA.EtLoc]=CtaCptSoldeNm1("50*","58*") | J10: 2945092497
B11: Flux de trésorerie provenant des activités opérationnelles
A12: FA | B12: Capacité d'Autofinancement Globale (CAFG) | I12: =[ZFA.EtLoc]=[T_CAFG.EtLoc]
A13: FB | B13: - Variation d'actif circulant HAO (1) | I13: =[ZFB.EtLoc]=-CtaCptSoldeDébit("46*","49*")+CtaCptSoldeDébitNm1("46*","49*")
A14: FC | B14: - Variation des stocks | I14: =[ZFC.EtLoc]=-CtaCptSoldeDébit("3*")+CtaCptSoldeDébitNm1("3*")
A15: FD | B15: - Variation des créances | I15: =[ZFD.EtLoc]=-CtaCptSoldeDébit("4*","45*")+CtaCptSoldeDébitNm1("4*","45*")
A16: FE | B16: + Variation du passif circulant (1) | I16: =[ZFE.EtLoc]=CtaCptSoldeCrédit("40*")+CtaCptSoldeCrédit("41*")+CtaCptSoldeCrédit("42*")+CtaCptSoldeCrédit("43*")+CtaCptSoldeCrédit("44*")+CtaCptSoldeCrédit("45*","49*")-CtaCptSoldeCréditNm1("40*")-CtaCptSoldeCréditNm1("41*")-CtaCptSoldeCréditNm1("42*")-CtaCptSoldeCréditNm1("43*")-CtaCptSoldeCréditNm1("44*")-CtaCptSoldeCréditNm1("45*","49*")
B17: Variation du BF lié aux activités opérationnelles
B18: FB+FC+FD+FE : | C18: =I13+I14+I15+I16 | E18: =IFERROR(J13+J14+J15+J16,"")
A19: ZB | B19: Flux de trésorerie provenant des activités opérationnelles (Somme FA à FE) | G19: B | I19: =[ZZB.EtLoc]=[ZFA.EtLoc]+[ZFB.EtLoc]+[ZFC.EtLoc]+[ZFD.EtLoc]+[ZFE.EtLoc]
B20: Flux de trésorerie provenant des activités d’investissements
A21: FF | B21: - Décaissements liés aux acquisitions d'immobilisations incorporelles | I21: =[ZFF.EtLoc]=-CtaCptSolde("21*")+CtaCptSoldeNm1("21*")
A22: FG | B22: - Décaissements liés aux acquisitions d'immobilisations corporelles | I22: =[ZFG.EtLoc]=-CtaCptSolde("22*","25*")+CtaCptSoldeNm1("22*","25*")
A23: FH | B23: - Décaissements liés aux acquisitions d'immobilisations financières | I23: =[ZFH.EtLoc]=-CtaCptSolde("26*","27*")+CtaCptSoldeNm1("26*","27*")
A24: FI | B24: + Encaissements liés aux cessions d’immobilisations incorporelles et corporelles
A25: FJ | B25: + Encaissements liés aux cessions d’immobilisations financières
A26: ZC | B26: Flux de trésorerie provenant des activités d’investissement (somme FF à FJ) | G26: C | I26: =[ZZC.EtLoc]=[ZFF.EtLoc]+[ZFG.EtLoc]+[ZFH.EtLoc]
B27: Flux de trésorerie provenant du financement par les capitaux propres
A28: FK | B28: + Augmentations de capital par apports nouveaux | I28: =[ZFK.EtLoc]=-CtaCptSolde("10*")+CtaCptSoldeNm1("10*")
A29: FL | B29: + Subventions d'investissement reçues | I29: =[ZFL.EtLoc]=-CtaCptSolde("14*")+CtaCptSoldeNm1("14*")
A30: FM | B30: - Prélèvements sur le capital
A31: FN | B31: - Dividendes versés
A32: ZD | B32: Flux de trésorerie provenant des capitaux propres (somme FK à FN) | G32: D | I32: =[ZZD.EtLoc]=[ZFK.EtLoc]+[ZFL.EtLoc]
B33: Trésorerie provenant du financement par les capitaux étrangers
A34: FO | B34: + Emprunts | I34: =[ZFO.EtLoc]=-CtaCptSolde("16*")+CtaCptSoldeNm1("16*")
A35: FP | B35: + Autres dettes financières diverses
A36: FQ | B36: - Remboursements des emprunts et autres dettes financières
A37: ZE | B37: Flux de trésorerie provenant des capitaux étrangers (somme FO à FQ) | G37: E | I37: =[ZZE.EtLoc]=[ZFO.EtLoc]
A38: ZF | B38: Flux de trésorerie provenant des activités de financement (D+E) | G38: F | I38: =[ZZF.EtLoc]=[ZZD.EtLoc]+[ZZE.EtLoc]
A39: ZG | B39: VARIATION DE LA TRÉSORERIE NETTE DE LA PÉRIODE (B+C+F) | G39: G | I39: =[ZZG.EtLoc]=[ZZB.EtLoc]+[ZZC.EtLoc]+[ZZF.EtLoc]
A40: ZH | B40: Trésorerie nette au 31 Décembre (G+A) | G40: H | I40: =[ZZH.EtLoc]=[ZZG.EtLoc]+[ZZA.EtLoc]
B41: Contrôle : Trésorerie actif N - Trésorerie passif N | I41: =CtaCptSolde("50*","58*")
A42: [1] à l’exclusion des variations des créances et dettes liées aux activités d’investissement (variation des créances sur cession d’immobilisation et des dettes sur acquisition ou production d’immobilisation) et de financement (par exemple variation des créances sur subventions d’investissements reçues).
A60: T_EBE | B60: =[T_EBE.EtLoc]=-CtaCptSolde("701*")+CtaCptSolde("601*")-CtaCptSolde("702*","704*")-CtaCptSolde("705*","706*")-CtaCptSolde("707")-CtaCptSolde("713*")-CtaCptSolde("72*","73*")-CtaCptSolde("71*")-CtaCptSolde("74*","76*")-CtaCptSolde("781*")-CtaCptSolde("601*","602*")-CtaCptSolde("6032*")-CtaCptSolde("604*","609*")-CtaCptSolde("6033*","6038*")-CtaCptSolde("61*")-CtaCptSolde("62*","63*")-CtaCptSolde("64*")-CtaCptSolde("65*")-CtaCptSolde("66*")
A61: T_VCEC | B61: =[T_VCEC.EtLoc]=-CtaCptSolde("654*")
A62: T_PCEC | B62: =[T_PCEC.EtLoc]=CtaCptSolde("754*")
A63: T_TCE | B63: =[T_TCE.EtLoc]=CtaCptSolde("781*")
A64: T_CAFE | B64: =[T_CAFE.EtLoc]=[T_EBE.EtLoc]+[T_VCEC.EtLoc]+[T_PCEC.EtLoc]+[T_TCE.EtLoc]
A65: T_REVFIN | B65: =[T_REVFIN.EtLoc]=-CtaCptSolde("77*")
A66: T_TCF | B66: =[T_TCF.EtLoc]=CtaCptSolde("787*")
A67: T_PHAO | B67: =[T_PHAO.EtLoc]=CtaCptSolde("84*")
A68: T_FRAISFIN | B68: =[T_FRAISFIN.EtLoc]=-CtaCptSolde("67*")
A69: T_PART | B69: =[T_PART.EtLoc]=-CtaCptSolde("87*")
A70: T_IMPOTS | B70: =[T_IMPOTS.EtLoc]=-CtaCptSolde("89*")
A71: T_CAFG | B71: =[T_CAFG.EtLoc]=[T_CAFE.EtLoc]+[T_REVFIN.EtLoc]+[T_TCF.EtLoc]+[T_PHAO.EtLoc]+[T_FRAISFIN.EtLoc]+[T_PART.EtLoc]+[T_IMPOTS.EtLoc]

Sheet TAB BORD
A1: TABLEAU DE BORD DE CONTRÔLE DES FLUX DE TRESORERIE
C3: MONTANT
C4: EXERCICE N | D4: EXERCICE N-1
A5: Trésorerie actif de N-1 | B5: + | C5: =BILAN!I37
A6: Compte 472 versements restant à effectuer sur titres de placement non libérés de l'année N-1 | B6: - / +
A7: Trésorerie passif de N-1 | B7: - | C7: =-BILAN!N37
A8: Trésorerie au 1 er janvier (A) | C8: =+C5-C7 | D8: =SUM(D5:D7)
C11: MONTANT
C12: EXERCICE N | D12: EXERCICE N-1
A13: Excédent brut d'exploitation (poste XD compte de résultat) | B13: + | C13: =RESULTAT!I34
A14: Compte 654 solde débiteur balance N | B14: +
A15: Compte 754 solde créditeur balance N | B15: -
A16: Résultat financier (poste XF compte de résultat) | B16: + | C16: =-RESULTAT!I43
A17: Autres produits HAO (poste TO compte de résultat) | B17: + | C17: =+RESULTAT!I46
A18: Autres charges HAO (poste RP compte de résultat) | B18: - | C18: =-RESULTAT!I48
A19: Participation des trvailleurs (poste RQ du compte résultat) | B19: - | C19: =+RESULTAT!I50
A20: Impôts sur le résultat (poste RS du compte de résultat) | B20: - | C20: =+RESULTAT!I51
A21: Capacité d'Autfinancement Globale (CAFG) | C21: =SUM(C13:C20) | D21: =SUM(D13:D20)
A22: Actif circulant HAO (poste BA des bilans) | B22: + | C22: =BILAN!H27-BILAN!I27
A23: Compte 485 (exclure) | B23: -
A24: Montant affecté au poste FB du TFT | C24: =SUM(C22:C23) | D24: =SUM(D22:D23)
A25: Variation des stocks (poste BB des bilans) poste FC du TFT | B25: - / + | C25: =BILAN!H28-BILAN!I28
A26: Variation des créances et emplois assimilé (poste BG des bilans) | B26: - / + | C26: =BILAN!H29-BILAN!I29
A27: Variation du compte 478 | B27: - / +
A28: Variation du compte 419 | B28: - / +
A29: Variation du compte 414 | B29: - / +
A30: Variation du compte 467 | B30: - / +
A31: Variation du compte 458 | B31: - / +
A32: Variation du compte 4494 | B32: - / +
A33: Variation du compte 4751 | B33: - / +
A34: Montant affecté au poste FD du TFT | C34: =SUM(C25:C33) | D34: =SUM(D25:D33)
A35: Variation du passif circulant (poste DP des bilans) | B35: - / + | C35: =BILAN!M33-BILAN!N33
A36: Variation du compte 409 | B36: - / + | C36: =BILAN!H30-BILAN!I30
A37: Variation du compte 404 | B37: - / +
A38: Variation du compte 481 | B38: - / + | C38: =BILAN!M27-BILAN!N27
A39: Variation du compte 482 | B39: - / +
A40: Variation du compte 467 | B40: - / +
A41: Variation du compte 4752 | B41: - / +
A42: Variation du compte 472 | B42: - / +
A43: Montant affecté au poste FE du TFT | C43: =SUM(C35:C42) | D43: =SUM(D35:D42)
A44: Variation du BF lié aux activités opérationnelles | C44: =C34+C43+C24 | D44: =-D34+D43-D25
A45: LES FLUX DE TRESORERIE PROVENANT DES ACTIVITES OPERATIONNELLES (B) | C45: =C21+C44 | D45: =D21+D44
C49: MONTANT
C50: EXERCICE N | D50: EXERCICE N-1
A51: Variation des immobilisations incorporelles nettes (poste (AD) | B51: - / + | C51: =BILAN!H11-BILAN!I11
A52: Compte 6812 | B52: +
A53: Compte 6913 | B53: +
A54: Compte 6541 | B54: +
A55: Compte 811 | B55: +
A56: Compte 251 | B56: +
A57: Comptes 4811, 4821, 4041, 4046 | B57: +
A58: Comptes 4811, 4821, 4041, 4046 | B58: -
A59: Comptes 48161, 48171, 48181 | B59: +
A60: Comptes 48161, 48171, 48181 | B60: -
A61: Décaissements liés aux acquisitions d'immobilisations incorporelles | C61: =SUM(C51:C60) | D61: =SUM(D51:D60)
A62: Variation des immobilisations corporelles nettes (poste AI) | B62: - / + | C62: =BILAN!H16-BILAN!I16
A63: Compte 6813 | B63: + | C63: =-RESULTAT!I36
A64: Compte 6914 | B64: +
A65: Compte 6542 | B65: +
A66: Compte 812 | B66: +
A67: Compte 1061 | B67: -
A68: Compte 1062 | B68: -
A69: Compte 154 | B69: -
A70: Compte 1984 | B70: -
A71: Comptes 2286, 2316, 2326, 2416, 2426, 2446, 2456 | B71: -
A72: Compte 2714 | B72: -
A73: Compte 252 | B73: + | C73: =BILAN!H22-BILAN!I22
A74: Comptes 4812, 4822, 4042, 4047 | B74: +
A75: Comptes 4812, 4822, 4042, 4047 | B75: -
A76: Comptes 48162, 48172, 48182 | B76: +
A77: Comptes 48162, 48172, 48182 | B77: -
A78: Décaissements liés aux acquisitions d'immobilisations corporelles | C78: =SUM(C62:C77) | D78: =SUM(D62:D77)
A79: Compte 26,27 | B79: + | C79: =BILAN!H23-BILAN!I23
A80: Compte 4813 | B80: +
A81: Compte 4813 | B81: -
A82: Décaissements liés aux acquisitions d'immobilisations financières | C82: =SUM(C79:C81) | D82: =SUM(D79:D81)
A83: Comptes 821, 822 ou 7541, 7542 | B83: +
A84: Comptes 4851, 4852, ou 4141, 4142 | B84: -
A85: Comptes 4851, 4852, ou 4141, 4142 | B85: +
A86: Décaissements liés aux cessions d'immobilisatins incorporelles et corporelles | C86: =SUM(C83:C85) | D86: =SUM(D83:D85)
A87: Comptes 826 | B87: +
A88: Comptes 4856 ou 4143 | B88: -
A89: Comptes 4856 ou 4143 | B89: +
A90: Compte 2714 | B90: +
A91: Décaissements liés aux cessions d'immobilisations financières | C91: =SUM(C87:C90) | D91: =SUM(D87:D90)
A92: LES FLUX DE TRESORERIE PROVENANT DES ACTIVITES D'INVESTISSEMENT ( C ) | C92: =C78+C82+C86+C91+C61 | D92: =-D78+D82+D86+D91
C96: MONTANT
C97: EXERCICE N | D97: EXERCICE N-1
A98: Variation du compte 10 | B98: - / + | C98: =-BILAN!M11+BILAN!N11
A99: Variation du compte 106 | B99: -
A100: Variation du compte 109 | B100: -
A101: Variation du compte 467 | B101: - / +
A102: Varaition du compte 4581 | B102: - / +
A103: Augmentation de capital par apport à nouveaux | C103: =SUM(C98:C102) | D103: =SUM(D98:D102)
A104: Variation du compte 14 | B104: - / +
A105: Variation du compte 799 | B105: -
A106: Variation du compte 4582 | B106: - / +
A107: Variation du compte 4494 | B107: - / +
A108: Variation du compte 4497 | B108: - / +
A109: Subventions d'investissements reçues | C109: =SUM(C104:C108) | D109: =SUM(D104:D108)
...

Sheet NOTE 1
A1: - 8 -
H2: NOTE 1 SYSTEME NORMAL
A3: Dénomination sociale de l'entité : | C3: ='FICHE R4'!C3
A4: Adresse : | B4: ='FICHE R4'!B4 | H4: Sigle usuel : | I4: ='FICHE R4'!I4
A5: N° IFU du contribuable : | C5: ='FICHE R4'!C5 | F5: Exercice clos le : | H5: Durée (en mois) : | I5: ='FICHE R4'!I5
A6: N° de télédéclarant (NES): | C6: ='FICHE R4'!C6
A7: NOTE 1: DETTES GARANTIES PAR DES SURETES REELLES ET LES ENGAGEMENTS FINANCIERS
A8: LIBELLES | E8: Note | F8: Montant brut (1) | G8: SURETES REELLES (2)
G9: Hypothèques | H9: Nantissements | I9: Gages/autres
A10: Emprunts et dettes financières diverses : | E10: 16
A11: Emprunts obligataires convertibles
A12: Autres emprunts obligataires
A13: Emprunts et dettes des établissements de crédit | F13: =+BILAN!M22
A14: Autres dettes financières
A15: SOUS TOTAL (1) | F15: =SUM(F11:F14)
A16: Dettes de location-acquisition : | E16: 16
A17: Dettes de crédit-bail immobilier
A18: Dettes de crédit-bail mobilier
A19: Dettes sur contrats de location-vente
A20: Autres dettes sur contrats de location-acquisition
A21: SOUS TOTAL (2) | F21: =SUM(F17:F20)
A22: Dettes du passif circulant :
A23: Fournisseurs et comptes rattachés | E23: 17
A24: Clients | E24: 7
A25: Personnel | E25: 18
A26: Sécurité sociale et organismes sociaux | E26: 18
A27: Etat | E27: 18
A28: Organismes internationaux | E28: 19
A29: Associés et groupe | E29: 19
A30: Créditeurs divers | E30: 19
A31: SOUS TOTAL (3)
A32: TOTAL (1) + (2) + (3)
A33: ENGAGEMENTS FINANCIERS | G33: Engagements réciproques | H33: Engagements donnés | I33: Engagements reçus
A34: Engagements consentis à des entités liées
A35: Primes de remboursement des obligations non échues
A36: Avals, cautions, garanties
A37: Hypothèques, nantissements, gages, autres
A38: Effets escomptés non échus
A39: Créances commerciales et professionnelles cédées
A40: Abandons de créances conditionnels
A41: Achats de marchandises à terme
A42: Achats à terme de devises non couverts
A43: Commandes fermes des clients
A44: Autres engagements réciproques
A45: TOTAL | G45: =SUM(G34:G44) | H45: =SUM(H34:H40) | I45: =SUM(I34:I40)
A46: (1) indiquer le montant de la garantie
A47: (2) indiquer les références de la sûreté
A48: Commentaire :
A49: ● Indiquer la raison d'être des suretés.
A50: ● Pour les actifs et passifs externes frappés de réserve de propriété(R/P), indiquer les informations prévues dans le chapitre Opérations et problèmes spécifiques.
A51: ● Pour les transactions entre les parties liées, indiquer :
A52: - la nature et le montant des transactions effectuées avec chaque partie liée (entité mère,autres filiales du groupe,etc.)
A53: - les transactions avec les principaux dirigeants (prêts aux dirigeants,salaires bruts et avantages en nature,atribution gratuite d'actions etc.).

Sheet NOTE 2
A1: - 0 -
H2: NOTE 2 SYSTEME NORMAL
A3: Dénomination sociale de l'entité : | C3: ='NOTE 1'!C3
A4: Adresse : | B4: ='NOTE 1'!B4 | H4: Sigle usuel : | I4: ='NOTE 1'!I4
A5: N° IFU du contribuable : | C5: ='NOTE 1'!C5 | F5: Exercice clos le : | H5: Durée (en mois) : | I5: ='NOTE 1'!I5
A6: N° de télédéclarant (NES): | C6: ='NOTE 1'!C6
A7: NOTE 2: INFORMATIONS OBLIGATOIRES
A8: A - DECLARATION DE CONFORMITE AU SYSCOHADA ET FAITS MARQUANTS DE L'EXERCICE
A9: Les états financiers sont établis conformément au système comptable OHADA et à l'acte uniforme relatif au droit comptable et à l'information financière.
A10: B - REGLES ET METHODES COMPTABLES
A11: Les postultas, les conventions et règles d'évaluation édictées par le SYSCOHADA et l'acte uniforme ont été respectés dans l'élaboration des états financiers.
A12: C- DEROGATION AUX POSTULATS ET CONVENTIONS COMPTABLES
A13: Les postultas et conventions ont été tous respectés sans aucune dérogation.
A14: D - INFORMATIONS COMPLEMENTAIRES RELATIVES AU BILAN, AU COMPTE DE RESULTAT ET AU TABLEAU DES FLUX DE TRESORERIE
A15: Il n'y a pas d'informations complémentaires relatives aux autres états financiers.
A17: Commentaire :
A18: ● Mentionner les faits marquants après la déclaration de conformité.
A19: Seuls les éléments ayant une incidence comptable significative ou qui misent à la comparabilité des exercices doivent être mentionnés. Par exemple, le lancement d'un produit sur le marché, ou la perte du principal client de l'entité.
A20: ● Décrire les régles et méthodes utilisées pour l'établissement des états financiers et celles utilisées dans le cas de contrat pluri- exercices, de contrats de concession, de l'établissement de comptes intermédiaires, de fusion et opérations assimilées comme indiquées dans les opérations et problèmes spécifiques.

Sheet NOTE 3A
A1: - 9 -
I2: NOTE 3A SYSTEME NORMAL
A3: Dénomination sociale de l'entité : | C3: ='NOTE 1'!C3
A4: Adresse : | B4: ='NOTE 1'!B4 | I4: Sigle usuel : | J4: ='NOTE 1'!I4
A5: N° IFU : | C5: ='NOTE 1'!C5 | F5: Exercice clos le : | G5: ='NOTE 1'!G5 | I5: Durée (en mois) : | J5: ='NOTE 1'!I5
A6: N° de télédéclarant (NES): | C6: ='NOTE 1'!C6
A7: NOTE 3A : IMMOBILISATIONS (BRUTES)
A8: SITUATIONS ET MOUVEMENTS | D8: A | E8: AUGMENTATIONS B | H8: DIMINUTIONS C | J8: D = A + B - C
D9: MONTANT BRUT A L'OUVERTURE DE L'EXERCICE | E9: Acquisitions Apports Créations | F9: Virements de poste à poste | G9: Suite à une réévaluation pratiquée au cours de l'exercice | H9: Cessions Scissions Hors service | I9: Virements de poste à poste | J9: MONTANT BRUT A LA CLOTURE DE L'EXERCICE
A10: RUBRIQUES
A11: IMMOBILISATIONS INCORPORELLES | D11: =SUM(D12:D15) | E11: =SUM(E12:E15) | F11: =SUM(F12:F15) | G11: =SUM(G12:G15) | H11: =SUM(H12:H15) | I11: =SUM(I12:I15) | J11: =D11+E11+F11+G11-H11-I11
A12: Frais de développement et de prospection | J12: =D12+E12+F12+G12-H12-I12
A13: Brevets, licences, logiciels, et droits similaires | E13: =+BILAN!F13 | J13: =D13+E13+F13+G13-H13-I13
A14: Fonds commercial et droit au bail | J14: =D14+E14+F14+G14-H14-I14
A15: Autres immobilisations incorporelles | J15: =D15+E15+F15+G15-H15-I15
A16: IMMOBILISATIONS CORPORELLES
A17: Terrains hors immeuble de placement
A18: Terrains - immeuble de placement
A19: Bâtiments hors immeuble de placement
A20: Bâtiments - immeuble de placement
A21: Aménagements, agencements et installations
A22: Matériel, mobilier et actifs biologiques
A23: Matériel de transport
A24: AVANCES ET ACOMPTES VERSES SUR IMMOBILISATIONS
A25: Avances et acomptes sur immobilisations incorporelles
A26: Avances et acomptes sur immobilisations corporelles
A27: IMMOBILISATIONS FINANCIERES
... A31: Commentaire :
A32: ● Toute variation significative doit être commentée. | E32: ● Indiquer les créances du groupe avec nature et date d'échéance.
A33: ● Détailler les éléments constitutifs du fonds commercial et indiquer la date d'acquisition. | E33: ● Pour les banques, DAT indiquer le nom de la banque le montant et la date d'échéance.
A34: ● Pour l'immobilisation incorporelle relative à la concession faire un descriptif de l'accord. | E34: ● Pour les frais de développement, donner toutes les informations mentionnées dans la partie Opérations et problèmes spécifiques.
A35: ● Indiquer : | E35: ● Donner le détail des produits et charges liés aux immeubles de placement.
A36: - la nature de la créance ;
A37: - la durée de la concession ;
A38: - l'échéance.

Sheet NOTE 3B
A1: - 0 -
K2: NOTE 3B SYSTEME NORMAL
A3: Dénomination sociale de l'entité : | C3: ='NOTE 1'!C3
A4: Adresse : | B4: ='NOTE 1'!B4 | K4: Sigle usuel : | L4: ='NOTE 1'!I4
A5: N° IFU : | C5: ='NOTE 1'!C5 | H5: Exercice clos le : | I5: ='NOTE 1'!G5 | K5: Durée (en mois) : | L5: ='NOTE 1'!I5
A6: N° de télédéclarant (NES): | C6: ='NOTE 1'!C6
A7: NOTE 3B : BIENS PRIS EN LOCATION ACQUISITION
A8: SITUATIONS ET MOUVEMENTS | F8: A | G8: AUGMENTATIONS B | J8: DIMINUTIONS C | L8: D = A + B - C
E9: NATURE DU CONTRAT (I ; M ; A) [1] | F9: MONTANT BRUT A L'OUVERTURE DE L'EXERCICE | G9: Acquisitions Apports Créations | H9: Virements de poste à poste | I9: Suite à une réévaluation pratiquée au cours de l'exercice | J9: Cessions Scissions Hors service | K9: Virements de poste à poste | L9: MONTANT BRUT A LA CLOTURE DE L'EXERCICE
A10: RUBRIQUES
A11: Terrains | L11: =F11+G11+H11+I11-J11-K11
A12: Bâtiments | L12: =F12+G12+H12+I12-J12-K12
A13: Matériel, mobilier | L13: =F13+G13+H13+I13-J13-K13
A14: Matériel de transport | L14: =F14+G14+H14+I14-J14-K14
A15: TOTAL IMMOBILISATIONS EN LOCATION-ACQUISITION | F15: =SUM(F11:F14) | G15: =SUM(G11:G14) | H15: =SUM(H11:H14) | I15: =SUM(I11:I14) | J15: =SUM(J11:J14) | K15: =SUM(K11:K14) | L15: =SUM(L11:L14)
A16: [1] I : Crédit-bail immobilier ; M : Crédit-bail mobilier ; A : Autres contrats (dédoubler le poste si montants
A17: Commentaire:
A18: ● Indiquer la nature du bien, le nom du bailleur et la durée du bail.

Sheet NOTE 3C
A1: - 10 -
N2: NOTE 3C SYSTEME NORMAL
A3: Dénomination sociale de l'entité : | C3: ='NOTE 1'!C3
A4: Adresse : | B4: ='NOTE 1'!B4 | L4: Sigle usuel : | N4: ='NOTE 1'!I4
A5: N° IFU : | C5: ='NOTE 1'!C5 | H5: Exercice clos le : | J5: ='NOTE 1'!G5 | L5: Durée (en mois) : | N5: ='NOTE 1'!I5
A6: N° de télédéclarant (NES): | C6: ='NOTE 1'!C6
A7: NOTE 3C : IMMOBILISATIONS (AMORTISSEMENTS)
A8: SITUATIONS ET MOUVEMENTS | D8: A | F8: B | H8: C | L8: D | N8: E = A + B - C - D
D9: AMORTISSEMENTS CUMULES A L'OUVERTURE DE L'EXERCICE | F9: AUGMENTATIONS: | H9: DIMINUTIONS : | L9: Virements de poste à poste | N9: CUMUL DES AMORTISSEMENTS A LA CLOTURE DE L'EXERCICE
A10: RUBRIQUES | F10: DOTATIONS DE L'EXERCICE | H10: Amortissements relatifs aux éléments sortis de l'actif | J10: Reprises d'amortissements
A11: Frais de développement et de prospection | N11: =D11+F11-H11-J11-L11
A12: Brevets, licences, logiciels et droits similaires | F12: =+BILAN!G13 | N12: =D12+F12-H12-J12-L12
A13: Fonds commercial et droit au bail | N13: =D13+F13-H13-J13-L13
A14: Autres immobilisations incorporelles | N14: =D14+F14-H14-J14-L14
A15: IMMOBILISATIONS INCORPORELLES
A16: Terrains hors immeuble de placement
A17: Terrains - immeuble de placement
A18: Bâtiments hors immeuble de placement
A19: Bâtiments - immeuble de placement
A20: Aménagements, agencements et installations
A21: Matériel, mobilier et actifs biologiques
A22: Matériel de transport
A23: IMMOBILISATIONS CORPORELLES
A24: TOTAL GENERAL
A25: Commentaire :
A26: ● Indiquer
... A28: - la durée d'utilité ou les taux d'amortissements utilisés.

Sheet NOTE 3C BIS
A1: - 0 -
J2: NOTE 3C BIS SYSTEME NORMAL
A3: Dénomination sociale de l'entité : | C3: ='NOTE 1'!C3
A4: Adresse : | B4: ='NOTE 1'!B4 | J4: Sigle usuel : | K4: ='NOTE 1'!I4
A5: N° IFU : | C5: ='NOTE 1'!C5 | E5: Exercice clos le : | J5: Durée (mois) : | K5: ='NOTE 1'!I5
A6: N° de télédéclarant (NES): | C6: ='NOTE 1'!C6
A7: NOTE 3C BIS : IMMOBILISATIONS (DEPRECIATIONS)
A8: SITUATIONS ET MOUVEMENTS | D8: A | F8: B | H8: C | J8: D = A + B - C
D9: DEPRECIATIONS CUMULES A L'OUVERTURE DE L'EXERCICE | F9: AUGMENTATIONS: DOTATIONS DE L'EXERCICE | H9: DIMINUTIONS : REPRISES DE L'EXERCICE | J9: CUMUL DES DEPRECIATIONS A LA CLOTURE DE L'EXERCICE
A10: RUBRIQUES
A11: Frais de développement et de prospection | J11: =D11+F11-H11
A12: Brevets, licences, logiciels et droits similaires | J12: =D12+F12-H12
A13: Fonds commercial et droit au bail | J13: =D13+F13-H13
A14: Autres immobilisations incorporelles | J14: =D14+F14-H14
A15: IMMOBILISATIONS INCORPORELLES | D15: =SUM(D11:E14) | F15: =SUM(F11:G14) | H15: =SUM(H11:I14) | J15: =SUM(J11:K14)
A16: Terrains hors immeuble de placement | J16: =D16+F16-H16
A17: Terrains - immeuble de placement | J17: =D17+F17-H17
A18: Bâtiments hors immeuble de placement | J18: =D18+F18-H18
A19: Bâtiments - immeuble de placement | J19: =D19+F19-H19
A20: Aménagements, agencements et installations | J20: =D20+F20-H20
A21: Matériel, mobilier et actifs biologiques | J21: =D21+F21-H21
A22: Matériel de transport | J22: =D22+F22-H22
A23: IMMOBILISATIONS CORPORELLES | D23: =SUM(D16:E22) | F23: =SUM(F16:G22) | H23: =SUM(H16:I22) | J23: =SUM(J16:K22)
A24: TOTAL GENERAL | D24: =D15+D23 | F24: =F15+F23 | H24: =H15+H23 | J24: =J15+J23
A25: Commentaire :
A26: ● Indiquer les événements et circonstances qui ont conduit à la dépréciation et à la reprise.

Sheet NOTE 3D
A1: - 0 -
G2: NOTE 3D SYSTEME NORMAL
A3: Dénomination sociale de l'entité : | C3: ='NOTE 1'!C3
A4: Adresse : | B4: ='NOTE 1'!B4 | G4: Sigle usuel : | H4: ='NOTE 1'!I4
A5: N° IFU : | C5: ='NOTE 1'!C5 | D5: Exercice clos le : | G5: Durée (en mois) : | H5: ='NOTE 1'!I5
A6: N° de télédéclarant (NES): | C6: ='NOTE 1'!C6
A7: NOTE 3D : IMMOBILISATIONS (PLUS-VALUES ET MOINS- VALUES DE CESSION)
A8: SITUATIONS ET MOUVEMENTS | D8: MONTANT BRUT | E8: AMORTISSEMENTS PRATIQUES | F8: VALEUR COMPTABLE NETTE | G8: PRIX DE CESSION | H8: PLUS-VALUE OU MOINS-VALUE
A9: RUBRIQUES | D9: A | E9: B | F9: C = A - B | G9: D | H9: E = D - C
A10: Frais de développement et de prospection | F10: =D10-E10 | H10: =G10-F10
A11: Brevets, licences, logiciels et droits similaires | F11: =D11-E11 | H11: =G11-F11
A12: Fonds commercial et droit au bail | F12: =D12-E12 | H12: =G12-F12
A13: Autres immobilisations incorporelles | F13: =D13-E13 | H13: =G13-F13
A14: IMMOBILISATIONS INCORPORELLES | D14: =SUM(D10:D13) | E14: =SUM(E10:E13) | F14: =SUM(F10:F13) | G14: =SUM(G10:G13) | H14: =SUM(H10:H13)
A15: Terrains | F15: =D15-E15 | H15: =G15-F15
A16: Bâtiments | F16: =D16-E16 | H16: =G16-F16
A17: Aménagements, agencements et installations | F17: =D17-E17 | H17: =G17-F17
A18: Matériel, mobilier et actifs biologiques | F18: =D18-E18 | H18: =G18-F18
A19: Matériel de transport | F19: =D19-E19 | H19: =G19-F19
A20: IMMOBILISATIONS CORPORELLES | D20: =SUM(D15:D19) | E20: =SUM(E15:E19) | F20: =SUM(F15:F19) | G20: =SUM(G15:G19) | H20: =SUM(H15:H19)
A21: Titres de participations | F21: =D21-E21 | H21: =G21-F21
A22: Autres immobilisations financières | F22: =D22-E22 | H22: =G22-F22
A23: IMMOBILISATIONS FINANCIERES | D23: =SUM(D21:D22) | E23: =SUM(E21:E22) | F23: =SUM(F21:F22) | G23: =SUM(G21:G22) | H23: =SUM(H21:H22)
A24: TOTAL GENERAL | D24: =D14+D20+D23 | E24: =E14+E20+E23 | F24: =F14+F20+F23 | G24: =G14+G20+G23 | H24: =H14+H20+H23
A25: Commentaire :
A26: ● Mentionner la justification de la cession ainsi que la date d'acquisition et la date de sortie.

Sheet NOTE 3E
A1: - 0 -
H2: NOTE 3E SYSTEME NORMAL
A3: Dénomination sociale de l'entité : | C3: ='NOTE 1'!C3
A4: Adresse : | B4: ='NOTE 1'!B4 | H4: Sigle usuel : | I4: ='NOTE 1'!I4
A5: N° IFU : | C5: ='NOTE 1'!C5 | D5: Exercice clos le : | H5: Durée (en mois) : | I5: ='NOTE 1'!I5
A6: N° de télédéclarant (NES): | C6: ='NOTE 1'!C6
A7: NOTE 3E : INFORMATIONS SUR LES REEVALUATIONS EFFECTUEES PAR L'ENTITE
A8: Nature et date des réévaluations :
A10: Eléments réévalués par postes du bilan | F10: Montants en coûts historiques | G10: Montant réévalués | H10: Ecarts de réévaluation | I10: Amortissements supplémentaires
A18: TOTAL GENERAL | F18: =SUM(F11:F17) | G18: =SUM(G11:G17) | H18: =SUM(H11:H17) | I18: =SUM(I11:I17)
A19: Méthode de réévaluation utilisée :
A21: Traitement fiscal de l'écart de réévaluation et des amortissements supplémentaires :
A23: Montant de l'écart incorporé au capital :

Sheet NOTE 4
A1: - 0 -
J2: NOTE 4 SYSTEME NORMAL
A3: Dénomination sociale de l'entité : | C3: ='NOTE 1'!C3
A4: Adresse : | B4: ='NOTE 1'!B4 | I4: Sigle usuel : | J4: ='NOTE 1'!I4
A5: N° IFU : | C5: ='NOTE 1'!C5 | F5: Exercice clos le : | G5: ='NOTE 1'!G5 | I5: Durée (en mois) : | J5: ='NOTE 1'!I5
A6: N° de télédéclarant (NES): | C6: ='NOTE 1'!C6
A7: NOTE 4 : IMMOBILISATIONS FINANCIERES
A8: Libellés | F8: Année N | G8: Année N-1 | H8: Variation en % | I8: Créances à un an au plus | J8: Créances à plus d'un an et à deux ans au plus | K8: Créances à plus de deux ans
A9: Titres de participation | H9: =IF(G9,(F9-G9)/ABS(G9),IF(ISBLANK(G9),"",IF(F9,IF( F9 > 0,1,-1),"")))
A10: Prêts et créances | H10: =IF(G10,(F10-G10)/ABS(G10),IF(ISBLANK(G10),"",IF(F10,IF( F10 > 0,1,-1),"")))
A11: Prêt au personnel | H11: =IF(G11,(F11-G11)/ABS(G11),IF(ISBLANK(G11),"",IF(F11,IF( F11 > 0,1,-1),"")))
A12: Créances sur l'état | H12: =IF(G12,(F12-G12)/ABS(G12),IF(ISBLANK(G12),"",IF(F12,IF( F12 > 0,1,-1),"")))
A13: Titres immobilisés | H13: =IF(G13,(F13-G13)/ABS(G13),IF(ISBLANK(G13),"",IF(F13,IF( F13 > 0,1,-1),"")))
A14: Dépôts et cautionnements
A15: Intérêts courus
A16: Créances rattachées à des avances et participations à des GIE
A17: Immobilisations financières diverses
A18: TOTAL BRUT
A19: Dépréciations des titres de participation | H19: =IF(G19,(F19-G19)/ABS(G19),IF(ISBLANK(G19),"",IF(F19,IF( F19 > 0,1,-1),"")))
A20: Dépréciations des autres immobilisations financières | H20: =IF(G20,(F20-G20)/ABS(G20),IF(ISBLANK(G20),"",IF(F20,IF( F20 > 0,1,-1),"")))
A21: TOTAL NET DE DEPRECIATION | F21: =F18+F19+F20 | G21: =G18+G19+G20 | H21: =IF(G21,(F21-G21)/G21,IF(ISBLANK(G21),"",IF(F21,1,"")))
A23: Liste des filiales et participations :
A24: Dénomination sociale | E24: Localisation (ville / pays) | G24: Valeur d'acquisition | H24: % Détenu | I24: Montant des capitaux propres filiale | J24: Résultat dernier exercice filiale (1) | K24: Part de bénéfice reçue de la filiale (2)
A31: (1): Préciser s'il s'agit du résultat de l'exercice N ou du résultat de l'exercice N-1 | E31: (2): S'il s'agit du résultat de l'exercice n-1, renseigner la colonne "part du bénéfice reçue de la filiale"
A32: Commentaire :
A33: ● Justifier toute variation significative. | F33: ● Indiquer le nombre et la date d'acquisition des actions ou parts propres.
A34: ● Commenter toutes les créances anciennes. | F34: ● Dépréciation : indiquer les évènements et les circonstances qui ont motivé la dépréciation ou la reprise.
A35: ● Pour les créances relatives à la concession, faire un descriptif de l'accord.
A36: ● Indiquer :
A37: - la nature de la créance ;
A38: - la durée de la concession ;
A39: - l'échéance.

Sheet NOTE 5
A1: - 0 -
H2: NOTE 5 SYSTEME NORMAL
A3: Dénomination sociale de l'entité : | C3: ='NOTE 1'!C3
A4: Adresse : | B4: ='NOTE 1'!B4 | H4: Sigle usuel : | I4: ='NOTE 1'!I4
A5: N° IFU : | C5: ='NOTE 1'!C5 | E5: Exercice clos le : | F5: ='NOTE 1'!G5 | H5: Durée (en mois) : | I5: ='NOTE 1'!I5
A6: N° de télédéclarant (NES): | C6: ='NOTE 1'!C6
A7: NOTE 5 : ACTIF CIRCULANT ET DETTES CIRCULANTES HAO
A8: ACTIF CIRCULANT HAO
A9: Libellés | E9: Année N | G9: Année N-1 | I9: Variation en %
A10: Créances sur cessions d'immobilisations | I10: =IF(G10,(E10-G10)/G10,IF(ISBLANK(G10),"",IF(E10,IF( E10 > 0,1,-1),"")))
A11: Autres créances hors activités ordinaires | E11: =+BILAN!F27 | G11: 0 | I11: =IF(G11,(E11-G11)/G11,IF(ISBLANK(G11),"",IF(E11,IF( E11 > 0,1,-1),"")))
A12: TOTAL BRUT | E12: =SUM(E10:F11) | G12: =SUM(G10:H11) | I12: =IF(G12,(E12-G12)/G12,IF(ISBLANK(G12),"",IF(E12,IF( E12 > 0,1,-1),"")))
A13: Dépréciations des créances HAO | I13: =IF(G13,(E13-G13)/G13,IF(ISBLANK(G13),"",IF(E13,IF( E13 > 0,1,-1),"")))
A14: TOTAL NET DE DEPRECIATIONS | E14: =E12+E13 | G14: =G12+G13 | I14: =IF(G14,(E14-G14)/G14,IF(ISBLANK(G14),"",IF(E14,IF( E14 > 0,1,-1),"")))
A15: Commentaire:
A16: • Commenter toute variation significative.
A17: • Dépréciation : indiquer les évènements et les circonstances qui ont motivé la dépréciation ou la reprise.
A19: DETTES CIRCULANTES HAO
A21: Libellés | E21: Année N | G21: Année N-1 | I21: Variation en %
A22: Fournisseurs d'investissements | E22: =+BILAN!M27
A23: Fournisseurs d'investissements effets à payer
A24: Versements restant à effectuer sur titres de participation et titres immobilisés non libérés | I24: =IF(G24,(E24-G24)/G24,IF(ISBLANK(G24),"",IF(E24,IF( E24 > 0,1,-1),"")))
A25: Autres dettes hors activités ordinaires | I25: =IF(G25,(E25-G25)/G25,IF(ISBLANK(G25),"",IF(E25,IF( E25 > 0,1,-1),"")))
A26: TOTAL | E26: =SUM(E22:F25) | G26: =SUM(G22:H25) | I26: =IF(G26,(E26-G26)/G26,IF(ISBLANK(G26),"",IF(E26,IF( E26 > 0,1,-1),"")))
A27: Commentaire:
A28: ● Indiquer la date de cession et la nature de l'immobilisation achetée et/ou cédée.
A29: ● Expliciter toute variation significative.

Sheet NOTE 6
A1: - 0 -
I2: NOTE 6 SYSTEME NORMAL
A3: Dénomination sociale de l'entité : | C3: ='NOTE 1'!C3
A4: Adresse : | B4: ='NOTE 1'!B4 | I4: Sigle usuel : | J4: ='NOTE 1'!I4
A5: N° IFU : | C5: ='NOTE 1'!C5 | E5: Exercice clos le : | F5: ='NOTE 1'!G5 | I5: Durée (en mois) : | J5: ='NOTE 1'!I5
A6: N° de télédéclarant (NES): | C6: ='NOTE 1'!C6
A7: NOTE 6 : STOCKS ET EN COURS (1)
A8: Libellés | E8: Année N | G8: Année N-1 | I8: Variation de stock en valeur absolue | J8: Variation en %
A9: Marchandises | I9: =ABS(E9-G9) | J9: =IF(G9,(E9-G9)/G9,IF(ISBLANK(G9),"",IF(E9,IF( E9 > 0,1,-1),"")))
A10: Matières premières et fournitures liées
A11: Autres approvisionnements
A12: Produits en cours
A13: Services en cours
A14: Produits finis
A15: Produits intermédiaires
A16: Stocks en cours de route, en consignation ou en dépôt
A17: TOTAL BRUT STOCKS ET EN COURS | E17: =SUM(E9:F16) | G17: =SUM(G9:H16) | I17: =ABS(E17-G17) | J17: =IF(G17,(E17-G17)/G17,IF(ISBLANK(G17),"",IF(E17,IF( E17 > 0,1,-1),"")))
A18: Dépréciations des stocks | I18: =ABS(E18-G18) | J18: =IF(G18,(E18-G18)/G18,IF(ISBLANK(G18),"",IF(E18,IF( E18 > 0,1,-1),"")))
A19: TOTAL NET DE DEPRECIATIONS | E19: =E17+E18 | G19: =G17+G18 | I19: =ABS(E19-G19) | J19: =IF(G19,(E19-G19)/G19,IF(ISBLANK(G19),"",IF(E19,IF( E19 > 0,1,-1),"")))
A20: (1) Les stocks H.A.O. seront inscrits dans l'actif circulant H.A.O. que lorsque leur montant total est significatif (supérieur à 5 % du total de l'actif circulant).
A21: Commentaire :
A22: ● Indiquer la date de prise d'inventaire et décrire brièvement la procédure, les méthodes comptables adoptées pour évaluer le stock.
A23: ● Commenter toute variation significative des stocks.
A24: ● Indiquer le détail des stocks dépréciés et les évènements et circonstances qui ont conduit à la dépréciation et à la reprise.

Sheet NOTE 7
A1: - 0 -
I2: NOTE 7 SYSTEME NORMAL
A3: Dénomination sociale de l'entité : | C3: ='NOTE 1'!C3
A4: Adresse : | B4: ='NOTE 1'!B4 | I4: Sigle usuel : | J4: ='NOTE 1'!I4
A5: N° IFU : | C5: ='NOTE 1'!C5 | F5: Exercice clos le : | G5: ='NOTE 1'!G5 | I5: Durée (en mois) : | J5: ='NOTE 1'!I5
A6: N° de télédéclarant (NES): | C6: ='NOTE 1'!C6
A7: NOTE 7 : CLIENTS
A8: Libellés | E8: Année N | F8: Année N-1 | G8: Variation en % | H8: Créances à un an au plus | I8: Créances à plus d'un an et à deux ans au plus | J8: Créances à plus de deux ans
A9: Clients (hors réserves de propriété et Groupe) | E9: =+BILAN!F31 | F9: 0 | G9: =IF(F9,(E9-F9)/F9,IF(ISBLANK(F9),"",IF(E9,IF( E9 > 0,1,-1),"")))
A10: Clients effets à recevoir (hors réserves de propriété et groupe) | G10: =IF(F10,(E10-F10)/F10,IF(ISBLANK(F10),"",IF(E10,IF( E10 > 0,1,-1),"")))
A11: Clients avec réserves de propriété | G11: =IF(F11,(E11-F11)/F11,IF(ISBLANK(F11),"",IF(E11,IF( E11 > 0,1,-1),"")))
A12: Clients et effets à recevoir Groupe | G12: =IF(F12,(E12-F12)/F12,IF(ISBLANK(F12),"",IF(E12,IF( E12 > 0,1,-1),"")))
A13: Créances sur cession d'immobilisations | G13: =IF(F13,(E13-F13)/F13,IF(ISBLANK(F13),"",IF(E13,IF( E13 > 0,1,-1),"")))
A14: Clients effets escomptés et non échus | G14: =IF(F14,(E14-F14)/F14,IF(ISBLANK(F14),"",IF(E14,IF( E14 > 0,1,-1),"")))
A15: Créances litigieuses ou douteuses | G15: =IF(F15,(E15-F15)/F15,IF(ISBLANK(F15),"",IF(E15,IF( E15 > 0,1,-1),"")))
A16: Clients produits à recevoir | G16: =IF(F16,(E16-F16)/F16,IF(ISBLANK(F16),"",IF(E16,IF( E16 > 0,1,-1),"")))
A17: TOTAL BRUT CLIENTS | E17: =SUM(E9:E16) | F17: =SUM(F9:F16) | G17: =IF(F17,(E17-F17)/F17,IF(ISBLANK(F17),"",IF(E17,IF( E17 > 0,1,-1),""))) | H17: =SUM(H9:H16) | I17: =SUM(I9:I16) | J17: =SUM(J9:J16)
A18: Dépréciations des comptes clients | G18: =IF(F18,(E18-F18)/F18,IF(ISBLANK(F18),"",IF(E18,IF( E18 > 0,1,-1),"")))
A19: TOTAL NET DE DEPRECIATIONS | E19: =E17-E18 | F19: =F17-F18 | G19: =IF(F19,(E19-F19)/F19,IF(ISBLANK(F19),"",IF(E19,IF( E19 > 0,1,-1),"")))
A20: Clients, avances reçues hors groupe | G20: =IF(F20,(E20-F20)/F20,IF(ISBLANK(F20),"",IF(E20,IF( E20 > 0,1,-1),"")))
A21: Clients, avances reçues groupe | G21: =IF(F21,(E21-F21)/F21,IF(ISBLANK(F21),"",IF(E21,IF( E21 > 0,1,-1),"")))
A22: Autres clients créditeurs | G22: =IF(F22,(E22-F22)/F22,IF(ISBLANK(F22),"",IF(E22,IF( E22 > 0,1,-1),"")))
A23: TOTAL CLIENTS CREDITEURS | E23: =SUM(E20:E22) | F23: =SUM(F20:F22) | G23: =IF(F23,(E23-F23)/F23,IF(ISBLANK(F23),"",IF(E23,IF( E23 > 0,1,-1),""))) | H23: =SUM(H20:H22) | I23: =SUM(I20:I22) | J23: =SUM(J20:J22)
A24: Commentaire :
A25: ● Commenter toutes variations significatives.
A26: ● Indiquer pour les créances du groupe, le nom de la société du groupe et le % de titres détenues.
A27: ● Commenter les créances anciennes.
A28: ● Indiquer les événements et circonstances qui ont conduit à la dépréciation et à la reprise.

Sheet NOTE 8
A1: - 0 -
I2: NOTE 8 SYSTEME NORMAL
A3: Dénomination sociale de l'entité : | C3: ='NOTE 1'!C3
A4: Adresse : | B4: ='NOTE 1'!B4 | I4: Sigle usuel : | J4: ='NOTE 1'!I4
A5: N° IFU : | C5: ='NOTE 1'!C5 | F5: Exercice clos le : | G5: ='NOTE 1'!G5 | I5: Durée (en mois) : | J5: ='NOTE 1'!I5
A6: N° de télédéclarant (NES): | C6: ='NOTE 1'!C6
A7: NOTE 8 : AUTRES CREANCES
A8: Libellés | E8: Année N | F8: Année N-1 | G8: Variation en % | H8: Créances à un an au plus | I8: Créances à plus d'un an et à deux ans au plus | J8: Créances à plus de deux ans
A9: Personnel
A10: Organismes sociaux
A11: Etat et Collectivités publiques
A12: Organismes internationaux
A13: Apporteurs, associés et groupe
A14: Compte transitoire ajustement spécial lié à la révision du SYSCOHADA (Voir Notes 8A & 8C)
A15: Autres débiteurs divers
A16: Comptes permanents non bloqués des établissements et des succursales
A17: Comptes de liaison charges et produits
A18: Comptes de liaison des sociétés en participation
A19: TOTAL BRUT AUTRES CREANCES | E19: =SUM(E9:E18) | F19: =SUM(F9:F18) | G19: =IF(F19,(E19-F19)/F19,IF(ISBLANK(F19),"",IF(E19,IF( E19 > 0,1,-1),""))) | H19: =SUM(H9:H18) | I19: =SUM(I9:I18) | J19: =SUM(J9:J18)
A20: Dépréciations des autres créances | G20: =IF(F20,(E20-F20)/F20,IF(ISBLANK(F20),"",IF(E20,IF( E20 > 0,1,-1),"")))
A21: TOTAL NET DE DEPRECIATIONS | E21: =E19-E20 | F21: =F19-F20 | G21: =IF(F21,(E21-F21)/F21,IF(ISBLANK(F21),"",IF(E21,IF( E21 > 0,1,-1),"")))
A22: Commentaire :
A23: ● Justifier toute variation significative.
A24: ● Détailler les créances dont le montant est significatif.
A25: ● Justifier les créances anciennes.
A26: ● Indiquer les événements et circonstances qui ont conduit à la dépréciation et à la reprise.
A27: ● Compte transitoire ajustement spécial, indiquer le détail du compte et la durée restant pour l'apurement.

Sheet NOTE 8A
A1: - 0 -
I2: NOTE 8A SYSTEME NORMAL
A3: Dénomination sociale de l'entité : | C3: ='NOTE 1'!C3
A4: Adresse : | B4: ='NOTE 1'!B4 | I4: Sigle usuel : | J4: ='NOTE 1'!I4
A5: N° d'identification fiscale : | C5: ='NOTE 1'!C5 | F5: Exercice clos le : | G5: ='NOTE 1'!G5 | I5: Durée (en mois) : | J5: ='NOTE 1'!I5
A6: N° de télédéclarant (NTD): | C6: ='NOTE 1'!C6
A7: NOTE 8A : TABLEAU D’ETALEMENT DES CHARGES IMMOBILISEES
A8: Libellés | E8: Frais d'établissement | G8: Charges à repartir sur plusieurs exercices | I8: Primes de remboursement des obligations
A9: Compte transitoire à solder: 4751 compte transitoire, ajustement lié à la révision du SYSCOHADA, compte-actif
A10: Montant global à étaler au 1er janvier 2018
A11: Durée d'étalement retenue
A12: Exercice 2018 | E12: Comptes | F12: Montants | G12: Comptes | H12: Montants | I12: Comptes | J12: Montants
E13: 60... | G13: 60... | I13: 6714
E14: 61... | G14: 61...
E15: 62... | G15: 62...
E16: 63... | G16: 63...
E22: ... | G22: ...
A23: Total exercice 2018
A24: Total exercice 2019
A25: Total exercice 2020
A26: Total exercice 2021
A27: Total exercice 2022
A28: TOTAL GENERAL | F28: =SUM(F23:F27) | H28: =SUM(H23:H27) | J28: =SUM(J23:J27)

Sheet NOTE 8B
A1: - 0 -
H2: NOTE 8B SYSTEME NORMAL
A3: Dénomination sociale de l'entité : | C3: ='NOTE 1'!C3
A4: Adresse : | B4: ='NOTE 1'!B4 | H4: Sigle usuel : | I4: ='NOTE 1'!I4
A5: N° d'identification fiscale : | C5: ='NOTE 1'!C5 | E5: Exercice clos le : | H5: Durée (en mois) : | I5: ='NOTE 1'!I5
A6: N° de télédéclarant (NTD): | C6: ='NOTE 1'!C6
A7: NOTE 8B : TABLEAU D’ETALEMENT DE PROVISIONS POUR CHARGES A REPARTIR
A8: LIBELLES | E8: PROVISIONS POUR CHARGES A REPARTIR
A9: Compte transitoire à solder: 4752 compte transitoire ajustement spécial lié à la révision du SYSCOHADA, compte-passif
A10: Montant global à étaler au 1er janvier 2018
A11: Durée d'étalement retenue
E12: Comptes | H12: Montants
E13: 791 Reprises de provisions et dépréciations d'exploitation
A14: Total exercice 2018
A15: Total exercice 2019
A16: Total exercice 2020
A17: Total exercice 2021
A18: Total exercice 2022
A19: TOTAL GENERAL | H19: =SUM(H14:I18)

Sheet NOTE 8C
A1: - 0 -
H2: NOTE 8C SYSTEME NORMAL
A3: Dénomination sociale de l'entité : | C3: ='NOTE 1'!C3
A4: Adresse : | B4: ='NOTE 1'!B4 | H4: Sigle usuel : | I4: ='NOTE 1'!I4
A5: N° d'identification fiscale : | C5: ='NOTE 1'!C5 | E5: Exercice clos le : | H5: Durée (en mois) : | I5: ='NOTE 1'!I5
A6: N° de télédéclarant (NTD): | C6: ='NOTE 1'!C6
A7: NOTE 8C : TABLEAU D’ETALEMENT DE PROVISIONS POUR ENGAGEMENTS DE RETAITE
A8: Libellés | E8: PROVISIONS POUR PENSIONS ET OBLIGATIONS SIMILAIRES
A9: Compte transitoire à solder: 4752 compte transitoire ajustement spécial lié à la révision du SYSCOHADA, compte-passif
A10: Montant global à étaler au 1er janvier 2018
A11: Durée d'étalement retenue
E12: Comptes | H12: Montants
E13: 6911 Dotation aux provisions pour risques et charges
A14: Total exercice 2018
A15: Total exercice 2019
A16: Total exercice 2020
A17: Total exercice 2021
A18: Total exercice 2022
A19: TOTAL GENERAL | H19: =SUM(H14:I18)

Sheet NOTE 9
A1: - 0 -
H2: NOTE 9 SYSTEME NORMAL
A3: Dénomination sociale de l'entité : | C3: ='NOTE 1'!C3
A4: Adresse : | B4: ='NOTE 1'!B4 | H4: Sigle usuel : | I4: ='NOTE 1'!I4
A5: N° IFU : | C5: ='NOTE 1'!C5 | E5: Exercice clos le : | F5: ='NOTE 1'!G5 | H5: Durée (en mois) : | I5: ='NOTE 1'!I5
A6: N° de télédéclarant (NES): | C6: ='NOTE 1'!C6
A7: NOTE 9 : TITRES DE PLACEMENT
A8: Libellés | E8: Année N | G8: Année N-1 | I8: Variation en %
A9: Titres de trésor et bons de caisse à court terme | I9: =IF(G9,(E9-G9)/G9,IF(ISBLANK(G9),"",IF(E9,IF( E9 > 0,1,-1),"")))
A10: Actions | I10: =IF(G10,(E10-G10)/G10,IF(ISBLANK(G10),"",IF(E10,IF( E10 > 0,1,-1),"")))
A11: Obligations | I11: =IF(G11,(E11-G11)/G11,IF(ISBLANK(G11),"",IF(E11,IF( E11 > 0,1,-1),"")))
A12: Bons de souscription | I12: =IF(G12,(E12-G12)/G12,IF(ISBLANK(G12),"",IF(E12,IF( E12 > 0,1,-1),"")))
A13: Titres négociables hors régions | I13: =IF(G13,(E13-G13)/G13,IF(ISBLANK(G13),"",IF(E13,IF( E13 > 0,1,-1),"")))
A14: Intérêts courus | I14: =IF(G14,(E14-G14)/G14,IF(ISBLANK(G14),"",IF(E14,IF( E14 > 0,1,-1),"")))
A15: Autres valeurs assimilées | I15: =IF(G15,(E15-G15)/G15,IF(ISBLANK(G15),"",IF(E15,IF( E15 > 0,1,-1),"")))
A16: TOTAL BRUT TITRES | E16: =SUM(E9:F15) | G16: =SUM(G9:H15) | I16: =IF(G16,(E16-G16)/G16,IF(ISBLANK(G16),"",IF(E16,IF( E16 > 0,1,-1),"")))
A17: Dépréciations des titres | I17: =IF(G17,(E17-G17)/G17,IF(ISBLANK(G17),"",IF(E17,IF( E17 > 0,1,-1),"")))
A18: TOTAL NET DE DEPRECIATIONS | E18: =E16-E17 | G18: =G16-G17 | I18: =IF(G18,(E18-G18)/G18,IF(ISBLANK(G18),"",IF(E18,IF( E18 > 0,1,-1),"")))
A19: Commentaire:
A20: ● Justifier toute variation significative.
A21: ● Pour les titres cotés à une bourse de valeur : indiquer le nombre, le prix unitaire d'acquisition et le cours de la bourse au 31 décembre.
A22: ● Faire ressortir les actions ou parts propres et indiquer la date d'acquisition et le nombre de titres détenus.
A23: ● Indiquer les événements et circonstances qui ont conduit à la dépréciation et à la reprise.

Sheet NOTE 10
A1: - 0 -
H2: NOTE 10 SYSTEME NORMAL
A3: Dénomination sociale de l'entité : | C3: ='NOTE 1'!C3
A4: Adresse : | B4: ='NOTE 1'!B4 | H4: Sigle usuel : | I4: ='NOTE 1'!I4
A5: N° IFU : | C5: ='NOTE 1'!C5 | E5: Exercice clos le : | H5: Durée (en mois) : | I5: ='NOTE 1'!I5
A6: N° de télédéclarant (NES): | C6: ='NOTE 1'!C6
A7: NOTE 10 : VALEURS A ENCAISSER
A8: Libellés | E8: Année N | G8: Année N-1 | I8: Variation en %
A9: Effets à encaisser | I9: =IF(G9,(E9-G9)/G9,IF(ISBLANK(G9),"",IF(E9,IF( E9 > 0,1,-1),"")))
A10: Effets à l'encaissement | I10: =IF(G10,(E10-G10)/G10,IF(ISBLANK(G10),"",IF(E10,IF( E10 > 0,1,-1),"")))
A11: Chèques à encaisser | I11: =IF(G11,(E11-G11)/G11,IF(ISBLANK(G11),"",IF(E11,IF( E11 > 0,1,-1),"")))
A12: Chèques à l'encaissement | I12: =IF(G12,(E12-G12)/G12,IF(ISBLANK(G12),"",IF(E12,IF( E12 > 0,1,-1),"")))
A13: Cartes de crédit à encaisser | I13: =IF(G13,(E13-G13)/G13,IF(ISBLANK(G13),"",IF(E13,IF( E13 > 0,1,-1),"")))
A14: Autres valeurs à encaisser | I14: =IF(G14,(E14-G14)/G14,IF(ISBLANK(G14),"",IF(E14,IF( E14 > 0,1,-1),"")))
A15: TOTAL BRUT VALEURS A ENCAISSER | E15: =SUM(E9:F14) | G15: =SUM(G9:H14) | I15: =IF(G15,(E15-G15)/G15,IF(ISBLANK(G15),"",IF(E15,IF( E15 > 0,1,-1),"")))
A16: Dépréciations des valeurs à encaisser | I16: =IF(G16,(E16-G16)/G16,IF(ISBLANK(G16),"",IF(E16,IF( E16 > 0,1,-1),"")))
A17: TOTAL NET DE DEPRECIATIONS | E17: =E15-E16 | G17: =G15-G16 | I17: =IF(G17,(E17-G17)/G17,IF(ISBLANK(G17),"",IF(E17,IF( E17 > 0,1,-1),"")))
A18: Commentaire :
A19: ● Commenter toute variation significative ;
A20: ● Indiquer les événements et circonstances qui ont conduit à la dépréciation et à la reprise.

Sheet NOTE 11
A1: - 11 -
H2: NOTE 11 SYSTEME NORMAL
A3: Dénomination sociale de l'entité : | C3: =+'NOTE 10'!C3:I3
A4: Adresse : | B4: ='NOTE 10'!B4:G4 | H4: Sigle usuel : | I4: ='NOTE 10'!I4
A5: N° IFU du contribuable : | C5: ='NOTE 10'!C5:D5 | E5: Exercice clos le : | F5: ='NOTE 10'!F5:G5 | H5: Durée (en mois) : | I5: ='NOTE 10'!I5
A6: N° de télédéclarant (NES):
A7: NOTE 11 : DISPONIBILITES
A8: Libellés | E8: Année N | G8: Année N-1 | I8: Variation en %
A9: Banques locales | E9: =BILAN!H36
A10: Banques autres états région
A11: Banques, dépôt à terme
A12: Autres Banques | I12: =IF(G12,(E12-G12)/G12,IF(ISBLANK(G12),"",IF(E12,IF( E12 > 0,1,-1),"")))
A13: Banques intérêts courus | I13: =IF(G13,(E13-G13)/G13,IF(ISBLANK(G13),"",IF(E13,IF( E13 > 0,1,-1),"")))
A14: Chèques postaux | I14: =IF(G14,(E14-G14)/G14,IF(ISBLANK(G14),"",IF(E14,IF( E14 > 0,1,-1),"")))
A15: Autres établissement financiers | I15: =IF(G15,(E15-G15)/G15,IF(ISBLANK(G15),"",IF(E15,IF( E15 > 0,1,-1),"")))
A16: Etablissement financiers intérêts courus | I16: =IF(G16,(E16-G16)/G16,IF(ISBLANK(G16),"",IF(E16,IF( E16 > 0,1,-1),"")))
A17: Instruments de trésorerie | I17: =IF(G17,(E17-G17)/G17,IF(ISBLANK(G17),"",IF(E17,IF( E17 > 0,1,-1),"")))
A18: Instruments de monnaie électronique | I18: =IF(G18,(E18-G18)/G18,IF(ISBLANK(G18),"",IF(E18,IF( E18 > 0,1,-1),"")))
A19: Caisse | I19: =IF(G19,(E19-G19)/G19,IF(ISBLANK(G19),"",IF(E19,IF( E19 > 0,1,-1),"")))
A20: Régies d'avances et virements accréditifs | I20: =IF(G20,(E20-G20)/G20,IF(ISBLANK(G20),"",IF(E20,IF( E20 > 0,1,-1),"")))
A21: TOTAL BRUT DISPONIBILITES | E21: =SUM(E9:F20) | G21: =SUM(G9:H20) | I21: =IF(G21,(E21-G21)/G21,IF(ISBLANK(G21),"",IF(E21,IF( E21 > 0,1,-1),"")))
A22: Dépréciations | I22: =IF(G22,(E22-G22)/G22,IF(ISBLANK(G22),"",IF(E22,IF( E22 > 0,1,-1),"")))
A23: TOTAL NET DE DEPRECIATIONS | E23: =E21-E22 | G23: =G21-G22 | I23: =IF(G23,(E23-G23)/G23,IF(ISBLANK(G23),"",IF(E23,IF( E23 > 0,1,-1),"")))
A24: Commentaire :
A25: ● Indiquer la date de rapprochement des comptes bancaires.
A26: ● Indiquer la date d'inventaire de la caisse et des instruments de monnaie électronique.
A27: ● Justifier toute variation significative.
A28: ● Détailler les instruments de monnaie électronique si le montant est significatif.
A29: ● Indiquer les événements et circonstances qui ont conduit à la dépréciation et à la reprise.
A31: NB : Banques et intérêts courus et Etablissement financiers intérêts courus figurent dans cette rubrique en négatif si le compte principal attaché est débiteur

Sheet NOTE 12
A1: - 0 -
H2: NOTE 12 SYSTEME NORMAL
A3: Dénomination sociale de l'entité : | C3: ='NOTE 11'!C3
A4: Adresse : | B4: ='NOTE 11'!B4 | H4: Sigle usuel : | I4: ='NOTE 11'!I4
A5: N° IFU du contribuable : | C5: ='NOTE 11'!C5 | F5: Exercice clos le : | G5: ='NOTE 11'!F5 | H5: Durée (en mois) : | I5: ='NOTE 11'!I5
A6: N° de télédéclarant (NES): | C6: ='NOTE 11'!C6
A7: NOTE 12 : ECARTS DE CONVERSION ET TRANSFERTS DE CHARGES
A8: ECARTS DE CONVERSION
A9: Libellés | E9: Devises | F9: Montant en devises | G9: Cours UML Année acquisition | H9: Cours UML 31/12 | I9: Variation en valeur absolue
A10: Ecarts de conversion actif : détailler les créances et dettes concernées
I11: =ABS(F11*G11-F11*H11)
I12: =ABS(F12*G12-F12*H12)
I13: =ABS(F13*G13-F13*H13)
I14: =ABS(F14*G14-F14*H14)
I15: =ABS(F15*G15-F15*H15)
I16: =ABS(F16*G16-F16*H16)
A17: Ecart de conversion passif : détailler les créances et dettes concernées
I18: =ABS(F18*G18-F18*H18)
I19: =ABS(F19*G19-F19*H19)
I20: =ABS(F20*G20-F20*H20)
I21: =ABS(F21*G21-F21*H21)
I22: =ABS(F22*G22-F22*H22)
I23: =ABS(F23*G23-F23*H23)
I24: =ABS(F24*G24-F24*H24)
A25: UML : Unités Monétaires légales Commentaire: Faire un commentaire.
A26: TRANSFERTS DE CHARGES
A27: Libellés | G27: Année N | H27: Année N-1 | I27: Variation en %
A28: Transferts de charges d'exploitation : détailler la nature des charges transférées et leurs comptes de provenance (1)
I29: =IFERROR((G29-H29)/H29,"")
I30: =IFERROR((G30-H30)/H30,"")
I31: =IFERROR((G31-H31)/H31,"")
I32: =IFERROR((G32-H32)/H32,"")
I33: =IFERROR((G33-H33)/H33,"")
I34: =IFERROR((G34-H34)/H34,"")
A35: Transferts de charges financières : détailler la nature des charges transférées et leurs comptes de provenance (2)
I36: =IFERROR((G36-H36)/H36,"")
I37: =IFERROR((G37-H37)/H37,"")
I38: =IFERROR((G38-H38)/H38,"")
I39: =IFERROR((G39-H39)/H39,"")
I40: =IFERROR((G40-H40)/H40,"")
I41: =IFERROR((G41-H41)/H41,"")
I42: =IFERROR((G42-H42)/H42,"")
A43: (1): Leurs comptes d'origine: autrement dit indiquerles numéros de comptes d'où le transfert est effectué.
A44: Commentaire: Faire un commentaire.

Sheet NOTE 13
A1: - 12 -
K2: NOTE 13 SYSTEME NORMAL
A3: Dénomination sociale de l'entité : | C3: ='NOTE 11'!C3
A4: Adresse : | B4: ='NOTE 11'!B4 | K4: Sigle usuel : | L4: ='NOTE 11'!I4
A5: N° IFU : | C5: ='NOTE 11'!C5 | I5: Exercice clos le : | J5: ='NOTE 11'!F5 | K5: Durée (en mois) : | L5: ='NOTE 11'!I5
A6: N° de télédéclarant (NES): | C6: ='NOTE 11'!C6
A7: NOTE 13 : CAPITAL
I8: Valeur nominale des actions ou parts : | L8: 10000
A9: Nom et prénoms ou raison sociale | E9: N° de compte contribuable | F9: Nationalité | G9: Autres nationalités à préciser | H9: Pays de résidence | I9: Nature des actions ou parts (Ordinaires ou préférences) | J9: Nombre | K9: Montant total | L9: Cessions ou remboursements en cours d'exercice
A24: Apporteurs, capital non appelé
A25: TOTAL | K25: =SUM(K10:K24)
A26: Commentaire :
A27: ● Indiquer si possible le montant du capital à la constitution. | I27: ● Pour les attributions gratuites d'actions indiquer :
A28: ● Indiquer si possible les dates des AGE et le montant du capital augmenté en cas d'augmentation de capital. | I28: - Date de délibération de l’AGE qui décide de l’attribution des actions
A29: ● Indiquer si possible les dates des AGE et le montant du capital diminué en cas de réduction de capital. | I29: - Pourcentage maximum du capital social à attribuer au personnel salarié
A30: ● Indiquer les avantages accordés aux actions de préférence. | I30: - Pourcentage maximum du capital social à attribuer aux dirigeants
A31: ● Apporteurs, capital non appelé : indiquer le délai restant pour appeler le capital. | I31: - Nombre d’actions à attribuer gratuitement
I32: - Délai de conservation des actions par les bénéficiaires
I33: - Nombre de ses actions propres que la société détient

Sheet NOTE 14
A1: - 0 -
G2: NOTE 14 SYSTEME NORMAL
A3: Dénomination sociale de l'entité : | C3: ='NOTE 11'!C3
A4: Adresse : | B4: ='NOTE 11'!B4 | G4: Sigle usuel : | H4: ='NOTE 11'!I4
A5: N° IFU : | C5: ='NOTE 11'!C5 | E5: Exercice clos le : | G5: Durée (en mois) : | H5: ='NOTE 11'!I5
A6: N° de télédéclarant (NES): | C6: ='NOTE 11'!C6
A7: NOTE 14 : PRIMES ET RESERVES
A8: Libellés | F8: Année N | G8: Année N-1 | H8: Variation en valeur absolue
A9: Primes d'émission | H9: =ABS(F9-G9)
A10: Prime d'apport | H10: =ABS(F10-G10)
A11: Prime de fusion | H11: =ABS(F11-G11)
A12: Prime de conversion | H12: =ABS(F12-G12)
A13: Autres primes | H13: =ABS(F13-G13)
A14: TOTAL PRIMES | F14: =SUM(F9:F13) | G14: =SUM(G9:G13) | H14: =ABS(F14-G14)
A15: Réserves légales | H15: =ABS(F15-G15)
A16: Réserves statutaires | H16: =ABS(F16-G16)
A17: Réserves de plus-values nettes à long terme | H17: =ABS(F17-G17)
A18: Réserves d’attribution gratuite d’actions au personnel salarié et aux dirigeants | H18: =ABS(F18-G18)
A19: Autres réserves réglementées | H19: =ABS(F19-G19)
A20: TOTAL RESERVES INDISPONIBLES | F20: =SUM(F15:F19) | G20: =SUM(G15:G19) | H20: =ABS(F20-G20)
A21: Réserves libres | H21: =ABS(F21-G21)
A22: Report à nouveau
A23: Commentaire:
A24: ● Indiquer les dates de l'AGE qui a décidé des primes d'apport, d'émission de fusion.
A25: ● Indiquer le détail des réserves libres.
A26: ● Indiquer le montant restant à doter et le taux de dotation de la réserve légale.
A27: ● Indiquer la date de l'AGO qui justifie la variation des réserves et du report à nouveau.

Sheet NOTE 15A
A1: - 0 -
I2: NOTE 15A SYSTEME NORMAL
A3: Dénomination sociale de l'entité : | C3: ='NOTE 11'!C3
A4: Adresse : | B4: ='NOTE 11'!B4 | I4: Sigle usuel : | J4: ='NOTE 11'!I4
A5: N° IFU : | C5: ='NOTE 11'!C5 | F5: Exercice clos le : | I5: Durée (en mois) : | J5: ='NOTE 11'!I5
A6: N° de télédéclarant (NES): | C6: ='NOTE 11'!C6
A7: NOTE 15A : SUBVENTIONS D'INVESTISSEMENT ET PROVISIONS REGLEMENTEES
A8: Libellés | D8: NOTE | E8: Année N | F8: Année N-1 | G8: Variation en valeur absolue | H8: Variation en % | I8: Régime fiscal | J8: Echéances
A9: État | G9: =ABS(E9-F9) | H9: =IF(F9,(E9-F9)/F9,IF(ISBLANK(F9),"",IF(E9,IF( E9 > 0,1,-1),"")))
A10: Régions | G10: =ABS(E10-F10) | H10: =IF(F10,(E10-F10)/F10,IF(ISBLANK(F10),"",IF(E10,IF( E10 > 0,1,-1),"")))
A11: Départements | G11: =ABS(E11-F11) | H11: =IF(F11,(E11-F11)/F11,IF(ISBLANK(F11),"",IF(E11,IF( E11 > 0,1,-1),"")))
A12: Communes et collectivités publiques décentralisées | G12: =ABS(E12-F12) | H12: =IF(F12,(E12-F12)/F12,IF(ISBLANK(F12),"",IF(E12,IF( E12 > 0,1,-1),"")))
A13: Entités publiques ou mixtes | G13: =ABS(E13-F13) | H13: =IF(F13,(E13-F13)/F13,IF(ISBLANK(F13),"",IF(E13,IF( E13 > 0,1,-1),"")))
A14: Entités et organismes privés | G14: =ABS(E14-F14) | H14: =IF(F14,(E14-F14)/F14,IF(ISBLANK(F14),"",IF(E14,IF( E14 > 0,1,-1),"")))
A15: Organismes internationaux | G15: =ABS(E15-F15) | H15: =IF(F15,(E15-F15)/F15,IF(ISBLANK(F15),"",IF(E15,IF( E15 > 0,1,-1),"")))
A16: Autres | G16: =ABS(E16-F16) | H16: =IF(F16,(E16-F16)/F16,IF(ISBLANK(F16),"",IF(E16,IF( E16 > 0,1,-1),"")))
A17: TOTAL SUBVENTIONS | E17: =SUM(E9:E16) | F17: =SUM(F9:F16) | G17: =ABS(E17-F17) | H17: =IF(F17,(E17-F17)/F17,IF(ISBLANK(F17),"",IF(E17,IF( E17 > 0,1,-1),"")))
A18: Amortissements dérogatoires | G18: =ABS(E18-F18) | H18: =IF(F18,(E18-F18)/F18,IF(ISBLANK(F18),"",IF(E18,IF( E18 > 0,1,-1),"")))
A19: Plus-value de cession à réinvestir | G19: =ABS(E19-F19) | H19: =IF(F19,(E19-F19)/F19,IF(ISBLANK(F19),"",IF(E19,IF( E19 > 0,1,-1),"")))
A20: Provisions spéciales de réévaluation | D20: 3E | G20: =ABS(E20-F20) | H20: =IF(F20,(E20-F20)/F20,IF(ISBLANK(F20),"",IF(E20,IF( E20 > 0,1,-1),"")))
A21: Provisions réglementées relatives aux immobilisations | G21: =ABS(E21-F21) | H21: =IF(F21,(E21-F21)/F21,IF(ISBLANK(F21),"",IF(E21,IF( E21 > 0,1,-1),"")))
A22: Provisions réglementés relatives aux stocks | G22: =ABS(E22-F22) | H22: =IF(F22,(E22-F22)/F22,IF(ISBLANK(F22),"",IF(E22,IF( E22 > 0,1,-1),"")))
A23: Provisions pour investissement | G23: =ABS(E23-F23) | H23: =IF(F23,(E23-F23)/F23,IF(ISBLANK(F23),"",IF(E23,IF( E23 > 0,1,-1),"")))
A24: Autres provisions et fonds réglementées | G24: =ABS(E24-F24) | H24: =IF(F24,(E24-F24)/F24,IF(ISBLANK(F24),"",IF(E24,IF( E24 > 0,1,-1),"")))
A25: TOTAL PROVISIONS REGLEMENTEES | E25: =SUM(E18:E24) | F25: =SUM(F18:F24) | G25: =ABS(E25-F25) | H25: =IF(F25,(E25-F25)/F25,IF(ISBLANK(F25),"",IF(E25,IF( E25 > 0,1,-1),"")))
A26: TOTAL SUBVENTIONS ET PROVISIONS REGLEMENTEES | E26: =E17+E25 | F26: =F17+F25 | G26: =ABS(E26-F26) | H26: =IF(F26,(E26-F26)/F26,IF(ISBLANK(F26),"",IF(E26,IF( E26 > 0,1,-1),"")))
A27: Commentaire:
A28: ● Indiquer pour la subvention la date d’octroi, la nature, les obligations éventuelles.
A29: ● Pour les provisions réglementées, indiquer le texte de référence, les obligations. Commenter toute variation significative.
A30: ● Commenter toute variation significative.

Sheet NOTE 15B
A1: - 0 -
J2: NOTE 15B SYSTEME NORMAL
A3: Dénomination sociale de l'entité : | C3: ='NOTE 11'!C3
A4: Adresse : | B4: ='NOTE 11'!B4 | J4: Sigle usuel : | K4: ='NOTE 11'!I4
A5: N° IFU : | C5: ='NOTE 11'!C5 | G5: Exercice clos le : | J5: Durée (en mois) : | K5: ='NOTE 11'!I5
A6: N° de télédéclarant (NES): | C6: ='NOTE 11'!C6
A7: NOTE 15B : AUTRES FONDS PROPRES (1)
A8: Libellés | F8: NOTE | G8: Année N | H8: Année N-1 | I8: Variation en valeur absolue | J8: Variation en % | K8: Echéances
A9: Titres participatifs | I9: =ABS(G9-H9) | J9: =IF(H9,(G9-H9)/H9,IF(ISBLANK(H9),"",IF(G9,IF( G9 > 0,1,-1),"")))
A10: Avances conditionnées | I10: =ABS(G10-H10) | J10: =IF(H10,(G10-H10)/H10,IF(ISBLANK(H10),"",IF(G10,IF( G10 > 0,1,-1),"")))
A11: Titres subordonnés à durée indéterminée (T.S.D.I.) | I11: =ABS(G11-H11) | J11: =IF(H11,(G11-H11)/H11,IF(ISBLANK(H11),"",IF(G11,IF( G11 > 0,1,-1),"")))
A12: Obligations remboursables en actions (O.R.A.) | I12: =ABS(G12-H12) | J12: =IF(H12,(G12-H12)/H12,IF(ISBLANK(H12),"",IF(G12,IF( G12 > 0,1,-1),"")))
A13: Autres avances et dettes assorties de conditions particulières | I13: =ABS(G13-H13) | J13: =IF(H13,(G13-H13)/H13,IF(ISBLANK(H13),"",IF(G13,IF( G13 > 0,1,-1),"")))
A14: TOTAL AUTRES FONDS PROPRES | G14: =SUM(G9:G13) | H14: =SUM(H9:H13) | I14: =ABS(G14-H14) | J14: =IF(H14,(G14-H14)/H14,IF(ISBLANK(H14),"",IF(G14,IF( G14 > 0,1,-1),"")))
A16: (1) Le cas échéant, une rubrique "Autres fonds propres" (montant des émissions de titres participatifs, avances conditionnées, ...) sur une ligne séparée est intercalée entre les rubriques "Total capitaux propres et ressources assimilées " et "Emprunts et dettes financières" si le montant des autres fonds propres est significatif.
A17: Commentaire:
A18: ● Justifier l'inscription de ces dettes dans une rubrique spécifique du passif du bilan "autres fonds propres"(faible probabilité de remboursement, absence d’échéancier...)
A19: ● Justifier le caractère significatif du montant total de cette rubrique
A20: ● Commenter toute variation significative

Sheet NOTE 16A
A1: - 0 -
J2: NOTE 16A SYSTEME NORMAL
A3: Dénomination sociale de l'entité : | C3: ='NOTE 11'!C3
A4: Adresse : | B4: ='NOTE 11'!B4 | J4: Sigle usuel : | K4: ='NOTE 11'!I4
A5: N° IFU : | C5: ='NOTE 11'!C5 | G5: Exercice clos le : | J5: Durée (en mois) : | K5: ='NOTE 11'!I5
A6: N° de télédéclarant (NES): | C6: ='NOTE 11'!C6
A7: NOTE 16A : DETTES FINANCIERES ET RESSOURCES ASSIMILES
A8: Libellés | E8: Année N | F8: Année N-1 | G8: Variation en valeur absolue | H8: Variation en % | I8: Dettes à un an au plus | J8: Dettes à plus d'un an et à deux ans au plus | K8: Dettes à plus de deux ans
A9: Emprunts obligataires | F9: 0 | G9: =ABS(E9-F9) | H9: =IF(F9,(E9-F9)/F9,IF(ISBLANK(F9),"",IF(E9,IF( E9 > 0,1,-1),"")))
A10: Emprunts et dettes auprès des établissements de crédit
A11: Avances reçues de l'Etat | G11: =ABS(E11-F11) | H11: =IF(F11,(E11-F11)/F11,IF(ISBLANK(F11),"",IF(E11,IF( E11 > 0,1,-1),"")))
A12: Avances reçues et comptes courants bloqués | G12: =ABS(E12-F12) | H12: =IF(F12,(E12-F12)/F12,IF(ISBLANK(F12),"",IF(E12,IF( E12 > 0,1,-1),"")))
A13: Dépôts et cautionnements reçus | G13: =ABS(E13-F13) | H13: =IF(F13,(E13-F13)/F13,IF(ISBLANK(F13),"",IF(E13,IF( E13 > 0,1,-1),"")))
A14: Intérêts courus | G14: =ABS(E14-F14) | H14: =IF(F14,(E14-F14)/F14,IF(ISBLANK(F14),"",IF(E14,IF( E14 > 0,1,-1),"")))
A15: Avances et dettes assorties de conditions particulières | G15: =ABS(E15-F15) | H15: =IF(F15,(E15-F15)/F15,IF(ISBLANK(F15),"",IF(E15,IF( E15 > 0,1,-1),"")))
A16: Autres emprunts et dettes | G16: =ABS(E16-F16) | H16: =IF(F16,(E16-F16)/F16,IF(ISBLANK(F16),"",IF(E16,IF( E16 > 0,1,-1),"")))
A17: Dettes liées à des participations et sociétés en participation | G17: =ABS(E17-F17) | H17: =IF(F17,(E17-F17)/F17,IF(ISBLANK(F17),"",IF(E17,IF( E17 > 0,1,-1),"")))
A18: Comptes permanents bloqués des établissements et succursales | G18: =ABS(E18-F18) | H18: =IF(F18,(E18-F18)/F18,IF(ISBLANK(F18),"",IF(E18,IF( E18 > 0,1,-1),"")))
A19: TOTAL EMPRUNTS ET DETTES FINANCIERES | E19: =SUM(E9:E18) | F19: =SUM(F9:F18) | G19: =ABS(E19-F19) | H19: =IF(F19,(E19-F19)/F19,IF(ISBLANK(F19),"",IF(E19,IF( E19 > 0,1,-1),""))) | I19: =SUM(I9:I18) | J19: =SUM(J9:J18) | K19: =SUM(K9:K18)
A20: Crédit bail immobilier | G20: =ABS(E20-F20) | H20: =IF(F20,(E20-F20)/F20,IF(ISBLANK(F20),"",IF(E20,IF( E20 > 0,1,-1),"")))
A21: Crédit bail mobilier | G21: =ABS(E21-F21) | H21: =IF(F21,(E21-F21)/F21,IF(ISBLANK(F21),"",IF(E21,IF( E21 > 0,1,-1),"")))
A22: Location vente | G22: =ABS(E22-F22) | H22: =IF(F22,(E22-F22)/F22,IF(ISBLANK(F22),"",IF(E22,IF( E22 > 0,1,-1),"")))
A23: Intérêts courus | G23: =ABS(E23-F23) | H23: =IF(F23,(E23-F23)/F23,IF(ISBLANK(F23),"",IF(E23,IF( E23 > 0,1,-1),"")))
A24: Autres dettes de location acquisition | G24: =ABS(E24-F24) | H24: =IF(F24,(E24-F24)/F24,IF(ISBLANK(F24),"",IF(E24,IF( E24 > 0,1,-1),"")))
A25: TOTAL DETTES DE LOCATION ACQUISITION | E25: =SUM(E20:E24) | F25: =SUM(F20:F24) | G25: =ABS(E25-F25) | H25: =IF(F25,(E25-F25)/F25,IF(ISBLANK(F25),"",IF(E25,IF( E25 > 0,1,-1),""))) | I25: =SUM(I20:I24) | J25: =SUM(J20:J24) | K25: =SUM(K20:K24)
A26: Provisions pour litiges | G26: =ABS(E26-F26) | H26: =IF(F26,(E26-F26)/F26,IF(ISBLANK(F26),"",IF(E26,IF( E26 > 0,1,-1),"")))
A27: Provisions pour garantie donnés aux clients | G27: =ABS(E27-F27) | H27: =IF(F27,(E27-F27)/F27,IF(ISBLANK(F27),"",IF(E27,IF( E27 > 0,1,-1),"")))
A28: Provisions pour pertes sur marchés à achèvement futur | G28: =ABS(E28-F28) | H28: =IF(F28,(E28-F28)/F28,IF(ISBLANK(F28),"",IF(E28,IF( E28 > 0,1,-1),"")))
A29: Provisions pour pertes de change | G29: =ABS(E29-F29) | H29: =IF(F29,(E29-F29)/F29,IF(ISBLANK(F29),"",IF(E29,IF( E29 > 0,1,-1),"")))
A30: Provisions pour impôts | G30: =ABS(E30-F30) | H30: =IF(F30,(E30-F30)/F30,IF(ISBLANK(F30),"",IF(E30,IF( E30 > 0,1,-1),"")))
A31: Provisions pour pensions et obligations assimilées - engagements de retraite | G31: =ABS(E31-F31) | H31: =IF(F31,(E31-F31)/F31,IF(ISBLANK(F31),"",IF(E31,IF( E31 > 0,1,-1),"")))
A32: Actif du régime de retraite (1) | G32: =ABS(E32-F32) | H32: =IF(F32,(E32-F32)/F32,IF(ISBLANK(F32),"",IF(E32,IF( E32 > 0,1,-1),"")))
A33: Provisions pour restructuration | G33: =ABS(E33-F33) | H33: =IF(F33,(E33-F33)/F33,IF(ISBLANK(F33),"",IF(E33,IF( E33 > 0,1,-1),"")))
A34: Provisions pour amendes et pénalités | G34: =ABS(E34-F34) | H34: =IF(F34,(E34-F34)/F34,IF(ISBLANK(F34),"",IF(E34,IF( E34 > 0,1,-1),"")))
A35: Provisions pour propre assureur | G35: =ABS(E35-F35) | H35: =IF(F35,(E35-F35)/F35,IF(ISBLANK(F35),"",IF(E35,IF( E35 > 0,1,-1),"")))
A36: Provisions pour démantèlement et remise en état | G36: =ABS(E36-F36) | H36: =IF(F36,(E36-F36)/F36,IF(ISBLANK(F36),"",IF(E36,IF( E36 > 0,1,-1),"")))
A37: Provisions de droits à réduction ou avantage en nature | G37: =ABS(E37-F37) | H37: =IF(F37,(E37-F37)/F37,IF(ISBLANK(F37),"",IF(E37,IF( E37 > 0,1,-1),"")))
A38: Autres provisions | G38: =ABS(E38-F38) | H38: =IF(F38,(E38-F38)/F38,IF(ISBLANK(F38),"",IF(E38,IF( E38 > 0,1,-1),"")))
A39: TOTAL PROVISIONS POUR RISQUES ET CHARGES | E39: =SUM(E26:E38) | F39: =SUM(F26:F38) | G39: =ABS(E39-F39) | H39: =IF(F39,(E39-F39)/F39,IF(ISBLANK(F39),"",IF(E39,IF( E39 > 0,1,-1),"")))
A40: (1): Le solde de ce compte est débiteur
A41: Commentaire:
A42: Pour chaque emprunt et dette de location acquisition: mentionner la date d'octroi, le nom de l'organisme financier, le montant initial de l'emprunt ou de la dette, la durée du crédit, les garanties données par la société.
A43: ● Indiquer les événements et circonstances qui ont conduit à la provision et à la reprise.
A44: ● Pour les pensions et obligations de retraite, indiquer :
A45: - la méthode d'évaluation retenue
A46: - le nom de la compagnie d'assurance ou du fonds de pension, le descriptif de la convention signée avec l'organisme, la périodicité des versements, le montant et la durée de la convention, pour les actifs du régime.

Sheet NOTE 16B
A1: - 0 -
H2: NOTE 16B SYSTEME NORMAL
A3: Dénomination sociale de l'entité : | C3: ='NOTE 11'!C3
A4: Adresse : | B4: ='NOTE 11'!B4 | H4: Sigle usuel : | I4: ='NOTE 11'!I4
A5: N° IFU : | C5: ='NOTE 11'!C5 | F5: Exercice clos le : | H5: Durée (en mois) : | I5: ='NOTE 11'!I5
A6: N° de télédéclarant (NES): | C6: ='NOTE 11'!C6
A7: NOTE 16B : ENGAGEMENTS DE RETRAITE ET AVANTAGES ASSIMILES : (METHODE ACTUARIELLE)
A8: HYPOTHESES ACTUARIELLES
A9: Libellés | H9: Année N | I9: Année N-1
A10: Taux d'augmentation des salaires
A11: Taux d'actualisation
A12: Taux d'inflation
A13: Probabilité d'être présent dans l'entité à la date de départ à la retraite (expérience passée)
A14: Probabilité d'être en vie à l'âge de départ à la retraite (table de mortalité)
A15: Taux de rendement effectif des actifs du régime
A16: Commentaire :
A17: ● Commenter les variations d'hypothèses actuarielles utilisées pour le calcul des engagements de retraite et avantages assimilés.
A19: VARIATION DE LA VALEUR DE L'ENGAGEMENT DE RETRAITE AU COURS DE L'EXERCICE
A20: Libellés | H20: Année N | I20: Année N-1
A21: Obligation au titre des engagements de retraite à l'ouverture
A22: Coût des services rendus au cours de l'exercice
A23: Coût financier
A24: Pertes actuarielles / (gain)
A25: Prestations payées au cours de l'exercice
A26: Coût des services passés
A27: Obligation au titre des engagements de retraite à la clôture
A28: Commentaire :
A29: ● Indiquer le montant de la charge par nature comptabilisée au cours de exercice
A31: ANALYSE DE SENSIBILITE DES HYPOTHESES ACTUARIELLES
A32: Libellés | F32: Année N | H32: Année N-1
F33: Augmentation | G33: Diminution | H33: Augmentation | I33: Diminution
A34: Taux d'actualisation (variation de ...%)
A35: Taux de progression des salaires (variation de ...%)
A36: Taux de départ du personnel (variation de ...%)
A37: Commentaire :
A38: ● Indiquer l’impact des variations obtenues sur le montant des engagements de retraite.

Sheet NOTE 16B BIS
A1: - 0 -
H2: NOTE 16B BIS SYSTEME NORMAL
A3: Dénomination sociale de l'entité : | C3: ='NOTE 11'!C3
A4: Adresse : | B4: ='NOTE 11'!B4 | H4: Sigle usuel : | I4: ='NOTE 11'!I4
A5: N° IFU : | C5: ='NOTE 11'!C5 | F5: Exercice clos le : | G5: ='NOTE 11'!F5 | H5: Durée (en mois) : | I5: ='NOTE 11'!I5
A6: N° de télédéclarant (NES): | C6: ='NOTE 11'!C6
A7: NOTE 16B BIS : ENGAGEMENTS DE RETRAITE ET AVANTAGES ASSIMILES : (METHODE ACTUARIELLE SUITE)
A8: ACTIF/PASSIF NET COMPTABILISE AU TITRE DES REGIMES FINANCES
A9: Libellés | H9: Année N | I9: Année N-1
A10: Valeur actuelle de l'obligation résultant de régimes financés
A11: Valeur actuelle des actifs affectés aux plans de retraite
A12: Excédent / Déficit de régime
A13: Commentaire :
A14: ● Indiquer le montant comptabilisé au passif (ou actif) à la clôture de l'exercice.
A16: VALEUR ACTUELLE DES ACTIFS DU REGIME
A17: Libellés | F17: Année N | H17: Année N-1
F18: Rendement attendu | G18: Juste valeur des actifs | H18: Rendement attendu | I18: Juste valeur des actifs
A19: Actions
A20: Obligations
A21: Autres
A22: Total | F22: =SUM(F19:F21) | G22: =SUM(G19:G21) | H22: =SUM(H19:H21) | I22: =SUM(I19:I21)
A23: Commentaire :
A24: ● Expliquer comment les taux de rendement par catégorie d’actifs et global ont été déterminés
A25: ● Indiquer le montant des rendements réels des actifs affectés aux plans en N et N-1

Sheet NOTE 16C
A1: - 0 -
G2: NOTE 16C SYSTEME NORMAL
A3: Dénomination sociale de l'entité : | C3: ='NOTE 11'!C3
A4: Adresse : | B4: ='NOTE 11'!B4 | G4: Sigle usuel : | H4: ='NOTE 11'!I4
A5: N° IFU : | C5: ='NOTE 11'!C5 | E5: Exercice clos le : | F5: ='NOTE 11'!F5 | G5: Durée (en mois) : | H5: ='NOTE 11'!I5
A6: N° de télédéclarant (NES): | C6: ='NOTE 11'!C6
A7: NOTE 16C : ACTIFS ET PASSIFS EVENTUELS
A8: Libellés | G8: Année N | H8: Année N-1
A9: Actif éventuel | G9: =SUM(G11:G18) | H9: =SUM(H11:H18)
A10: Litiges
A19: Passif éventuel | G19: =SUM(G21:G28) | H19: =SUM(H21:H28)
A20: Litiges
A29: Commentaire :
A30: ● Décrire les principales caractéristiques des actifs / passifs éventuels, l’horizon de temps auquel les encaissements / décaissements sont attendus et les éventuels remboursements à percevoir.

Sheet NOTE 17
A1: - 13 -
J2: NOTE 17 SYSTEME NORMAL
A3: Dénomination sociale de l'entité : | C3: ='NOTE 11'!C3
A4: Adresse : | B4: ='NOTE 11'!B4 | J4: Sigle usuel : | K4: ='NOTE 11'!I4
A5: N° IFU : | C5: ='NOTE 11'!C5 | F5: Exercice clos le : | G5: ='NOTE 11'!F5 | J5: Durée (en mois) : | K5: ='NOTE 11'!I5
A6: N° de télédéclarant (NES): | C6: ='NOTE 11'!C6
A7: NOTE 17 : FOURNISSEURS D'EXPLOITATION
A8: Libellés | F8: Année N | G8: Année N-1 | H8: Variation en % | I8: Dettes à un an au plus | J8: Dettes à plus d'un an et à deux ans au plus | K8: Dettes à plus de deux ans
A9: Fournisseurs dettes en compte (hors groupe)
A10: Fournisseurs effets à payer (hors groupe)
A11: Fournisseurs, dettes et effets à payer groupe
A12: Fournisseurs factures non parvenues (hors groupe)
A13: Fournisseurs factures non parvenues groupe | H13: =IF(G13,(F13-G13)/G13,IF(ISBLANK(G13),"",IF(F13,IF( F13 > 0,1,-1),"")))
A14: TOTAL FOURNISSEURS | F14: =SUM(F9:F13) | G14: =SUM(G9:G13) | H14: =IF(G14,(F14-G14)/G14,IF(ISBLANK(G14),"",IF(F14,IF( F14 > 0,1,-1),""))) | I14: =SUM(I9:I13) | J14: =SUM(J9:J13) | K14: =SUM(K9:K13)
A15: Fournisseurs, avances et acomptes (hors groupe) | F15: =+BILAN!F30
A16: Fournisseurs, avances et acomptes groupe | H16: =IF(G16,(F16-G16)/G16,IF(ISBLANK(G16),"",IF(F16,IF( F16 > 0,1,-1),"")))
A17: Autres fournisseurs débiteurs | F17: 0 | H17: =IF(G17,(F17-G17)/G17,IF(ISBLANK(G17),"",IF(F17,IF( F17 > 0,1,-1),"")))
A18: TOTAL FOURNISSEURS DEBITEURS | F18: =SUM(F15:F17) | G18: =SUM(G15:G17) | H18: =IF(G18,(F18-G18)/G18,IF(ISBLANK(G18),"",IF(F18,IF( F18 > 0,1,-1),""))) | I18: =SUM(I15:I17) | J18: =SUM(J15:J17) | K18: =SUM(K15:K17)
A19: Commentaire:
A20: ● Commenter toutes variations significatives.
A21: ● Indiquer pour les dettes du groupe le nom de la société du groupe et le % de titres détenus.
A22: ● Commenter les dettes anciennes.

Sheet NOTE 18
A1: - 0 -
J2: NOTE 18 SYSTEME NORMAL
A3: Dénomination sociale de l'entité : | C3: ='NOTE 11'!C3
A4: Adresse : | B4: ='NOTE 11'!B4 | J4: Sigle usuel : | K4: ='NOTE 11'!I4
A5: N° IFU : | C5: ='NOTE 11'!C5 | G5: Exercice clos le : | H5: ='NOTE 11'!F5 | J5: Durée (en mois) : | K5: ='NOTE 11'!I5
A6: N° de télédéclarant (NES): | C6: ='NOTE 11'!C6
A7: NOTE 18 : DETTES FISCALES ET SOCIALES
A8: Libellés | E8: Année N | F8: Année N-1 | G8: Variation en valeur absolue | H8: Variation en % | I8: Dettes à un an au plus | J8: Dettes à plus d'un an et à deux ans au plus | K8: Dettes à plus de deux ans
A9: Personnel avances et acomptes
A10: Personnel rémunérations dues
A11: Autres personnel
A12: Caisse de sécurité sociale
A13: Caisse de retraite
A14: Autres organismes sociaux
A15: TOTAL DETTES SOCIALES | I15: =SUM(I9:I14) | J15: =SUM(J9:J14) | K15: =SUM(K9:K14)
A16: Etat, impôts sur les bénéfices
A17: Etat, impôts et taxes
A18: Etat, TVA
A19: Etat, impôts retenus à la source
A20: Autres dettes Etat
A21: TOTAL DETTES FISCALES | E21: =SUM(E16:E20) | F21: =SUM(F16:F20) | G21: =SUM(G16:G20) | H21: =IF(F21,(E21-F21)/F21,IF(ISBLANK(F21),"",IF(E21,IF( E21 > 0,1,-1),""))) | I21: =SUM(I16:I20) | J21: =SUM(J16:J20) | K21: =SUM(K16:K20)
A22: TOTAL DETTES SOCIALES ET FISCALES | E22: =E15+E21 | F22: =F15+F21 | G22: =G15+G21 | H22: =IF(F22,(E22-F22)/F22,IF(ISBLANK(F22),"",IF(E22,IF( E22 > 0,1,-1),""))) | I22: =I15+I21 | J22: =J15+J21 | K22: =K15+K21
A23: Commentaire:
A24: ● Commenter toute variation significative.
A25: ● Commenter les dettes anciennes

Sheet NOTE 19
A1: - 14 -
J2: NOTE 19 SYSTEME NORMAL
A3: Dénomination sociale de l'entité : | C3: ='NOTE 11'!C3
A4: Adresse : | B4: ='NOTE 11'!B4 | J4: Sigle usuel : | K4: ='NOTE 11'!I4
A5: N° IFU : | C5: ='NOTE 11'!C5 | G5: Exercice clos le : | I5: ='NOTE 11'!F5 | J5: Durée (en mois) : | K5: ='NOTE 11'!I5
A6: N° de télédéclarant (NES): | C6: ='NOTE 11'!C6
A7: NOTE 19 : AUTRES DETTES ET PROVISIONS POUR RISQUES ET CHARGES A COURT TERME
A8: Libellés | E8: Année N | F8: Année N-1 | G8: Variation en valeur absolue | H8: Variation en % | I8: Dettes à un an au plus | J8: Dettes à plus d'un an et à deux ans au plus | K8: Dettes à plus de deux ans
A9: Organismes internationaux | G9: =ABS(E9-F9) | H9: =IF(F9,(E9-F9)/F9,IF(ISBLANK(F9),"",IF(E9,IF( E9 > 0,1,-1),"")))
A10: Apporteurs, opérations sur le capital | G10: =ABS(E10-F10) | H10: =IF(F10,(E10-F10)/F10,IF(ISBLANK(F10),"",IF(E10,IF( E10 > 0,1,-1),"")))
A11: Associés, compte courant | K11: =+G11
A12: Associés dividendes à payer
A13: Groupe, comptes courants | G13: =ABS(E13-F13) | H13: =IF(F13,(E13-F13)/F13,IF(ISBLANK(F13),"",IF(E13,IF( E13 > 0,1,-1),"")))
A14: Autres dettes associés | G14: =ABS(E14-F14) | H14: =IF(F14,(E14-F14)/F14,IF(ISBLANK(F14),"",IF(E14,IF( E14 > 0,1,-1),"")))
A15: TOTAL DETTES ASSOCIES | E15: =SUM(E9:E14) | F15: =SUM(F9:F14) | G15: =SUM(G9:G14) | H15: =IF(F15,(E15-F15)/F15,IF(ISBLANK(F15),"",IF(E15,IF( E15 > 0,1,-1),""))) | I15: =SUM(I9:I14) | J15: =SUM(J9:J14) | K15: =SUM(K9:K14)
A16: Créditeurs divers | G16: =ABS(E16-F16) | H16: =IF(F16,(E16-F16)/F16,IF(ISBLANK(F16),"",IF(E16,IF( E16 > 0,1,-1),"")))
A17: Obligataires | G17: =ABS(E17-F17) | H17: =IF(F17,(E17-F17)/F17,IF(ISBLANK(F17),"",IF(E17,IF( E17 > 0,1,-1),"")))
A18: Rémunérations d'administrateurs | G18: =ABS(E18-F18) | H18: =IF(F18,(E18-F18)/F18,IF(ISBLANK(F18),"",IF(E18,IF( E18 > 0,1,-1),"")))
A19: Compte d'affacturage et de titrisation | G19: =ABS(E19-F19) | H19: =IF(F19,(E19-F19)/F19,IF(ISBLANK(F19),"",IF(E19,IF( E19 > 0,1,-1),"")))
A20: Versements restant à effectuer sur titres de placement non libérés | G20: =ABS(E20-F20) | H20: =IF(F20,(E20-F20)/F20,IF(ISBLANK(F20),"",IF(E20,IF( E20 > 0,1,-1),"")))
A21: Compte transitoire ajustement spécial lié à la révision du SYSCOHADA (Voir Note 8B) | G21: =ABS(E21-F21) | H21: =IF(F21,(E21-F21)/F21,IF(ISBLANK(F21),"",IF(E21,IF( E21 > 0,1,-1),"")))
A22: Autres créditeurs divers | G22: =ABS(E22-F22) | H22: =IF(F22,(E22-F22)/F22,IF(ISBLANK(F22),"",IF(E22,IF( E22 > 0,1,-1),"")))
A23: TOTAL CREDITEURS DIVERS | E23: =SUM(E16:E22) | F23: =SUM(F16:F22) | G23: =SUM(G16:G22) | H23: =IF(F23,(E23-F23)/F23,IF(ISBLANK(F23),"",IF(E23,IF( E23 > 0,1,-1),""))) | I23: =SUM(I16:I22) | J23: =SUM(J16:J22) | K23: =SUM(K16:K22)
A24: Comptes permanents non bloqués des établissements et des succursales | G24: =ABS(E24-F24) | H24: =IF(F24,(E24-F24)/F24,IF(ISBLANK(F24),"",IF(E24,IF( E24 > 0,1,-1),"")))
A25: Comptes de liaison charges et produits | G25: =ABS(E25-F25) | H25: =IF(F25,(E25-F25)/F25,IF(ISBLANK(F25),"",IF(E25,IF( E25 > 0,1,-1),"")))
A26: Comptes de liaison des sociétés en participation | G26: =ABS(E26-F26) | H26: =IF(F26,(E26-F26)/F26,IF(ISBLANK(F26),"",IF(E26,IF( E26 > 0,1,-1),"")))
A27: TOTAL COMPTES DE LIAISON | E27: =SUM(E24:E26) | F27: =SUM(F24:F26) | G27: =SUM(G24:G26) | H27: =IF(F27,(E27-F27)/F27,IF(ISBLANK(F27),"",IF(E27,IF( E27 > 0,1,-1),""))) | I27: =SUM(I24:I26) | J27: =SUM(J24:J26) | K27: =SUM(K24:K26)
A28: TOTAL AUTRES DETTES | E28: =E15+E23+E27 | F28: =F15+F23+F27 | G28: =G15+G23+G27 | H28: =IF(F28,(E28-F28)/F28,IF(ISBLANK(F28),"",IF(E28,IF( E28 > 0,1,-1),""))) | I28: =I15+I23+I27 | J28: =J15+J23+J27 | K28: =K15+K23+K27
A29: Provisions pour risques et charges à court terme (voir note 28) | G29: =ABS(E29-F29) | H29: =IF(F29,(E29-F29)/F29,IF(ISBLANK(F29),"",IF(E29,IF( E29 > 0,1,-1),"")))
A30: Commentaire:
A31: ● Commenter toute variation significative.
A32: ● Indiquer le taux de rémunération si compte courant rémunéré.
A33: ● Commenter les dettes anciennes.
A34: ● Compte transitoire ajustement spécial, indiquer le détail du compte et la durée restant pour l'apurement.

Sheet NOTE 20
A1: - 0 -
G2: NOTE 20 SYSTEME NORMAL
A3: Dénomination sociale de l'entité : | C3: ='NOTE 11'!C3
A4: Adresse : | B4: ='NOTE 11'!B4 | G4: Sigle usuel : | H4: ='NOTE 11'!I4
A5: N° IFU : | C5: ='NOTE 11'!C5 | E5: Exercice clos le : | F5: ='NOTE 11'!F5 | G5: Durée (en mois) : | H5: ='NOTE 11'!I5
A6: N° de télédéclarant (NES): | C6: ='NOTE 11'!C6
A7: NOTE 20 : BANQUES, CREDIT D'ESCOMPTE ET DE TRESORERIE
A8: Libellés | F8: Année N | G8: Année N-1 | H8: Variation en %
A9: Escomptes de crédit de campagne | H9: =IF(G9,(F9-G9)/G9,IF(ISBLANK(G9),"",IF(F9,IF( F9 > 0,1,-1),"")))
A10: Escomptes de crédit ordinaires | H10: =IF(G10,(F10-G10)/G10,IF(ISBLANK(G10),"",IF(F10,IF( F10 > 0,1,-1),"")))
A11: TOTAL: BANQUES, CREDITS D'ESCOMPTE ET DE TRESORERIE | F11: =SUM(F9:F10) | G11: =SUM(G9:G10) | H11: =IF(G11,(F11-G11)/G11,IF(ISBLANK(G11),"",IF(F11,IF( F11 > 0,1,-1),"")))
A12: Banques locales | F12: =+BILAN!M36
A13: Banques autres états région | H13: =IF(G13,(F13-G13)/G13,IF(ISBLANK(G13),"",IF(F13,IF( F13 > 0,1,-1),"")))
A14: Autres Banques | H14: =IF(G14,(F14-G14)/G14,IF(ISBLANK(G14),"",IF(F14,IF( F14 > 0,1,-1),"")))
A15: Banques intérêts courus | H15: =IF(G15,(F15-G15)/G15,IF(ISBLANK(G15),"",IF(F15,IF( F15 > 0,1,-1),"")))
A16: Crédit de trésorerie
A17: TOTAL: BANQUES, CREDITS DE TRESORERIE | F17: =SUM(F12:F15) | G17: =SUM(G12:G15) | H17: =IF(G17,(F17-G17)/G17,IF(ISBLANK(G17),"",IF(F17,IF( F17 > 0,1,-1),"")))
A18: TOTAL GENERAL | F18: =F11+F17 | G18: =G11+G17 | H18: =IF(G18,(F18-G18)/G18,IF(ISBLANK(G18),"",IF(F18,IF( F18 > 0,1,-1),"")))
A19: Commentaire:
A20: ● Commenter toute variation significative.
A21: ● Indiquer le nom de l'organisme les conditions de crédit, le taux d'intérêt, la durée du crédit.
A23: NB : Banques et intérêts courus figurent dans cette rubrique si le compte principal attaché est créditeur.

Sheet NOTE 21
A1: - 15 -
G2: NOTE 21 SYSTEME NORMAL
A3: Dénomination sociale de l'entité : | C3: ='NOTE 20'!C3:H3
A4: Adresse : | B4: ='NOTE 20'!B4:F4 | G4: Sigle usuel : | H4: ='NOTE 20'!H4
A5: N° IFU : | C5: ='NOTE 20'!C5:D5 | E5: Exercice clos le : | F5: ='NOTE 20'!F5 | G5: Durée (en mois) : | H5: ='NOTE 20'!H5
A6: N° de télédéclarant (NES):
A7: NOTE 21 : CHIFFRE D’AFFAIRES ET AUTRES PRODUITS
A8: Libellés | F8: Année N | G8: Année N-1 | H8: Variation en %
A9: Ventes de marchandises dans l'Etat partie | H9: =IF(G9,(F9-G9)/G9,IF(ISBLANK(G9),"",IF(F9,IF( F9 > 0,1,-1),"")))
A10: Ventes de marchandises dans les autres Etats parties de la Région | H10: =IF(G10,(F10-G10)/G10,IF(ISBLANK(G10),"",IF(F10,IF( F10 > 0,1,-1),"")))
A11: Ventes de marchandises hors Région | H11: =IF(G11,(F11-G11)/G11,IF(ISBLANK(G11),"",IF(F11,IF( F11 > 0,1,-1),"")))
A12: Ventes de marchandises groupe | H12: =IF(G12,(F12-G12)/G12,IF(ISBLANK(G12),"",IF(F12,IF( F12 > 0,1,-1),"")))
A13: Ventes de marchandises sur internet | H13: =IF(G13,(F13-G13)/G13,IF(ISBLANK(G13),"",IF(F13,IF( F13 > 0,1,-1),"")))
A14: TOTAL : VENTES MARCHANDISES | F14: =SUM(F9:F13) | G14: =SUM(G9:G13) | H14: =IF(G14,(F14-G14)/G14,IF(ISBLANK(G14),"",IF(F14,IF( F14 > 0,1,-1),"")))
A15: Ventes de produits fabriqués dans l'Etat partie | F15: =+RESULTAT!I18 | H15: =IF(G15,(F15-G15)/G15,IF(ISBLANK(G15),"",IF(F15,IF( F15 > 0,1,-1),"")))
A16: Ventes de produits fabriqués dans les autres Etats parties de la Région | H16: =IF(G16,(F16-G16)/G16,IF(ISBLANK(G16),"",IF(F16,IF( F16 > 0,1,-1),"")))
A17: Ventes de produits fabriqués hors Région | H17: =IF(G17,(F17-G17)/G17,IF(ISBLANK(G17),"",IF(F17,IF( F17 > 0,1,-1),"")))
A18: Ventes de produits fabriqués groupe | H18: =IF(G18,(F18-G18)/G18,IF(ISBLANK(G18),"",IF(F18,IF( F18 > 0,1,-1),"")))
A19: Ventes de produits fabriqués sur internet | H19: =IF(G19,(F19-G19)/G19,IF(ISBLANK(G19),"",IF(F19,IF( F19 > 0,1,-1),"")))
A20: TOTAL : VENTES DE PRODUITS FABRIQUES | F20: =SUM(F15:F19) | G20: =SUM(G15:G19) | H20: =IF(G20,(F20-G20)/G20,IF(ISBLANK(G20),"",IF(F20,IF( F20 > 0,1,-1),"")))
A21: Ventes de travaux et services dans l'Etat partie | H21: =IF(G21,(F21-G21)/G21,IF(ISBLANK(G21),"",IF(F21,IF( F21 > 0,1,-1),"")))
A22: Ventes de travaux et services dans les autres Etats parties de la Région | H22: =IF(G22,(F22-G22)/G22,IF(ISBLANK(G22),"",IF(F22,IF( F22 > 0,1,-1),"")))
A23: Ventes de travaux et services hors Région | H23: =IF(G23,(F23-G23)/G23,IF(ISBLANK(G23),"",IF(F23,IF( F23 > 0,1,-1),"")))
A24: Ventes de travaux et services groupe | H24: =IF(G24,(F24-G24)/G24,IF(ISBLANK(G24),"",IF(F24,IF( F24 > 0,1,-1),"")))
A25: Ventes de travaux et services sur internet | H25: =IF(G25,(F25-G25)/G25,IF(ISBLANK(G25),"",IF(F25,IF( F25 > 0,1,-1),"")))
A26: TOTAL : VENTES DE TRAVAUX ET SERVICES VENDUS | F26: =SUM(F21:F25) | G26: =SUM(G21:G25) | H26: =IF(G26,(F26-G26)/G26,IF(ISBLANK(G26),"",IF(F26,IF( F26 > 0,1,-1),"")))
A27: Produits accessoires à détailler par nature d'activité économique : dont le détail de la rubrique "Divers" de la FIRD 2 | F27: =SUM(F28:F35) | G27: =SUM(G28:G35) | H27: =IF(G27,(F27-G27)/G27,IF(ISBLANK(G27),"",IF(F27,IF( F27 > 0,1,-1),"")))
H28: =IF(G28,(F28-G28)/G28,IF(ISBLANK(G28),"",IF(F28,IF( F28 > 0,1,-1),"")))
H29: =IF(G29,(F29-G29)/G29,IF(ISBLANK(G29),"",IF(F29,IF( F29 > 0,1,-1),"")))
H30: =IF(G30,(F30-G30)/G30,IF(ISBLANK(G30),"",IF(F30,IF( F30 > 0,1,-1),"")))
H31: =IF(G31,(F31-G31)/G31,IF(ISBLANK(G31),"",IF(F31,IF( F31 > 0,1,-1),"")))
H32: =IF(G32,(F32-G32)/G32,IF(ISBLANK(G32),"",IF(F32,IF( F32 > 0,1,-1),"")))
H33: =IF(G33,(F33-G33)/G33,IF(ISBLANK(G33),"",IF(F33,IF( F33 > 0,1,-1),"")))
H34: =IF(G34,(F34-G34)/G34,IF(ISBLANK(G34),"",IF(F34,IF( F34 > 0,1,-1),"")))
H35: =IF(G35,(F35-G35)/G35,IF(ISBLANK(G35),"",IF(F35,IF( F35 > 0,1,-1),"")))
A36: TOTAL : CHIFFRES D'AFFAIRES | F36: =F14+F20+F26+F27 | G36: =G14+G20+G26+G27 | H36: =IF(G36,(F36-G36)/G36,IF(ISBLANK(G36),"",IF(F36,IF( F36 > 0,1,-1),"")))
A37: Production immobilisée | H37: =IF(G37,(F37-G37)/G37,IF(ISBLANK(G37),"",IF(F37,IF( F37 > 0,1,-1),"")))
A38: Subventions d'exploitation | H38: =IF(G38,(F38-G38)/G38,IF(ISBLANK(G38),"",IF(F38,IF( F38 > 0,1,-1),"")))
A39: Autres produits (1)
A40: TOTAL : AUTRES PRODUITS | F40: =F38+F39 | G40: =G38+G39 | H40: =IF(G40,(F40-G40)/G40,IF(ISBLANK(G40),"",IF(F40,IF( F40 > 0,1,-1),"")))
A41: TOTAL | F41: =F36+F37+F40 | G41: =G36+G37+G40 | H41: =IF(G41,(F41-G41)/G41,IF(ISBLANK(G41),"",IF(F41,IF( F41 > 0,1,-1),"")))
A42: (1): Sous cette rubrique, les "Divers" de la FIRD 2 ne doivent pas figurer. Il s'agit ici des comptes 75…
A43: Commentaire:
A44: ● Justifier toute variation significative.
A45: ● Détailler: produits intermédiaires, produits résiduels, produits accessoires et autres produits si significatifs.
A46: ● Dans le cas de location-financement fournir les informations suivantes :
A47: - Résultat de la vente
A48: - Produits financiers sur l’investissement net
A49: - Revenus locatifs liés aux loyers variables non inclus dans l’investissement net
A50: - Echéances des loyers à recevoir :
A51: • jusqu’à 1 an • de 1 an à 5 ans • à plus de 5 ans

Sheet NOTE 22
A1: - 16 -
G2: NOTE 22 SYSTEME NORMAL
A3: Dénomination sociale de l'entité : | C3: ='NOTE 21'!C3
A4: Adresse : | B4: ='NOTE 21'!B4 | G4: Sigle usuel : | H4: ='NOTE 21'!H4
A5: N° IFU : | C5: ='NOTE 21'!C5 | E5: Exercice clos le : | F5: ='NOTE 21'!F5 | G5: Durée (en mois) : | H5: ='NOTE 21'!H5
A6: N° de télédéclarant (NES): | C6: ='NOTE 21'!C6
A7: NOTE 22 : ACHATS
A8: Libellés | F8: Année N | G8: Année N-1 | H8: Variation en %
A9: Achats de marchandises dans l'Etat partie | H9: =IF(G9,(F9-G9)/G9,IF(ISBLANK(G9),"",IF(F9,IF( F9 > 0,1,-1),"")))
A10: Achats de marchandises dans les autres Etats parties de la Région | H10: =IF(G10,(F10-G10)/G10,IF(ISBLANK(G10),"",IF(F10,IF( F10 > 0,1,-1),"")))
A11: Achats de marchandises hors Région | H11: =IF(G11,(F11-G11)/G11,IF(ISBLANK(G11),"",IF(F11,IF( F11 > 0,1,-1),"")))
A12: Achats de marchandises groupe | H12: =IF(G12,(F12-G12)/G12,IF(ISBLANK(G12),"",IF(F12,IF( F12 > 0,1,-1),"")))
A13: TOTAL : ACHATS DE MARCHANDISES | F13: =SUM(F9:F12) | G13: =SUM(G9:G12) | H13: =IF(G13,(F13-G13)/G13,IF(ISBLANK(G13),"",IF(F13,IF( F13 > 0,1,-1),"")))
A14: Achats de matières premières et fournitures liées dans l'Etat partie
A15: Achats de matères premières et fournitures liées dans les autres Etats parties de la Région
A16: Achats matières premières et fournitures liées hors Région
A17: Achats matières premières et fournitures liées groupe
A18: TOTAL : ACHATS MATIERES PREMIERES ET FOURNITURES LIEES
A19: Matières consommables
A20: Matières combustibles
A21: Produits d'entretien
A22: Fournitures d'atelier, d'usine et de magasin
A23: Eau
A24: Electricité
A25: Autres énergies
... A36: ● Commenter toute variation significative.

Sheet NOTE 23
A1: - 17 -
G2: NOTE 23 SYSTEME NORMAL
A3: Dénomination sociale de l'entité : | C3: ='NOTE 21'!C3
A4: Adresse : | B4: ='NOTE 21'!B4 | G4: Sigle usuel : | H4: ='NOTE 21'!H4
A5: N° IFU : | C5: ='NOTE 21'!C5 | E5: Exercice clos le : | F5: ='NOTE 21'!F5 | G5: Durée (en mois) : | H5: ='NOTE 21'!H5
A6: N° de télédéclarant (NES): | C6: ='NOTE 21'!C6
A7: NOTE 23 : TRANSPORTS
A8: Libellés | F8: Année N | G8: Année N-1 | H8: Variation en %
A9: Transports sur ventes
A10: Transports pour le compte de tiers
A11: Transport du personnel
A12: Transports de plis
A13: Voyage déplacement (transport)
A14: Transport entre établissements ou chantiers
A15: Transports administratifs
A16: TOTAL | F16: =SUM(F9:F15) | G16: =SUM(G9:G15) | H16: =IF(G16,(F16-G16)/G16,IF(ISBLANK(G16),"",IF(F16,IF( F16 > 0,1,-1),"")))
A17: Commentaire :
A18: ● Commenter toute variation significative.

Sheet NOTE 24
A1: - 18 -
G2: NOTE 24 SYSTEME NORMAL
A3: Dénomination sociale de l'entité : | C3: ='NOTE 21'!C3
A4: Adresse : | B4: ='NOTE 21'!B4 | G4: Sigle usuel : | H4: ='NOTE 21'!H4
A5: N° IFU : | C5: ='NOTE 21'!C5 | E5: Exercice clos le : | F5: ='NOTE 21'!F5 | G5: Durée (en mois) : | H5: ='NOTE 21'!H5
A6: N° de télédéclarant (NES): | C6: ='NOTE 21'!C6
A7: NOTE 24 : SERVICES EXTERIEURS
A8: Libellés | F8: Année N | G8: Année N-1 | H8: Variation en %
A9: Sous-traitance générale | H9: =IF(G9,(F9-G9)/G9,IF(ISBLANK(G9),"",IF(F9,IF( F9 > 0,1,-1),"")))
A10: Locations et charges locatives
A11: Redevances de location acquisition
A12: Entretien, réparations et maintenance
A13: Primes d'assurance
A14: Etudes, recherches et documentation
A15: Publicité, publications, relations publiques
A16: Frais de télécommunications
A17: Frais bancaires
A18: Rémunérations d'intermédiaires et de conseils
A19: Frais de formation du personnel
A20: Redevances pour brevets, licences, logiciels, concession et droits similaires
A21: Cotisations
... A23: Autres charges externes
A24: TOTAL | F24: =SUM(F9:F23) | G24: =SUM(G9:G23) | H24: =IF(G24,(F24-G24)/G24,IF(ISBLANK(G24),"",IF(F24,IF( F24 > 0,1,-1),"")))
A25: Commentaire :
A26: ● Commenter toute variation significative.

Sheet NOTE 25
A1: - 19 -
G2: NOTE 25 SYSTEME NORMAL
A3: Dénomination sociale de l'entité : | C3: ='NOTE 21'!C3
A4: Adresse : | B4: ='NOTE 21'!B4 | G4: Sigle usuel : | H4: ='NOTE 21'!H4
A5: N° IFU : | C5: ='NOTE 21'!C5 | E5: Exercice clos le : | F5: ='NOTE 21'!F5 | G5: Durée (en mois) : | H5: ='NOTE 21'!H5
A6: N° de télédéclarant (NES): | C6: ='NOTE 21'!C6
A7: NOTE 25 : IMPOTS ET TAXES
A8: Libellés | F8: Année N | G8: Année N-1 | H8: Variation en %
A9: Impôts et taxes directs
A10: Impôts et taxes indirects
A11: Droits d'enregistrement
A12: Pénalités et amendes fiscales
A13: Autres impôts et taxes
A14: TOTAL | F14: =SUM(F9:F13) | G14: =SUM(G9:G13) | H14: =IF(G14,(F14-G14)/G14,IF(ISBLANK(G14),"",IF(F14,IF( F14 > 0,1,-1),"")))
A15: Commentaire:
A16: ● Commenter toute variation significative.
A17: ● Détailler les pénalités et amendes et indiquer la cause.

Sheet NOTE 26
A1: - 0 -
G2: NOTE 26 SYSTEME NORMAL
A3: Dénomination sociale de l'entité : | C3: ='NOTE 21'!C3
A4: Adresse : | B4: ='NOTE 21'!B4 | G4: Sigle usuel : | H4: ='NOTE 21'!H4
A5: N° IFU : | C5: ='NOTE 21'!C5 | E5: Exercice clos le : | F5: ='NOTE 21'!F5 | G5: Durée (en mois) : | H5: ='NOTE 21'!H5
A6: N° de télédéclarant (NES): | C6: ='NOTE 21'!C6
A7: NOTE 26 : AUTRES CHARGES
A8: Libellés | F8: Année N | G8: Année N-1 | H8: Variation en %
A9: Pertes sur créances clients | H9: =IF(G9,(F9-G9)/G9,IF(ISBLANK(G9),"",IF(F9,IF( F9 > 0,1,-1),"")))
A10: Pertes sur autres débiteurs
A11: Quote-part de résultat sur opérations faites en commun
A12: Valeur comptable des cessions courantes d'immobilisations
A13: Perte de change sur créances et dettes commerciales
A14: Pénalités et amendes pénales
A15: Indemnités de fonction et autres rémunérations d'administrateurs
A16: Dons et mécénat
A17: Autres charges diverses
A18: Charges pour dépréciations et provisions pour risques à court terme d'exploitation (voir note 28) | H18: =IF(G18,(F18-G18)/G18,IF(ISBLANK(G18),"",IF(F18,IF( F18 > 0,1,-1),"")))
A19: TOTAL | F19: =SUM(F9:F18) | G19: =SUM(G9:G18) | H19: =IF(G19,(F19-G19)/G19,IF(ISBLANK(G19),"",IF(F19,IF( F19 > 0,1,-1),"")))
A20: Commentaire :
A21: ● Commenter toute variation significative.
A22: ● Indiquer la date du PV de l'AGO ou du CA qui fixe les rémunérations des administrateurs.
A23: ● Indiquer les organismes bénéficiaires des dons.

Sheet NOTE 27A
A1: - 0 -
G2: NOTE 27A SYSTEME NORMAL
A3: Dénomination sociale de l'entité : | D3: ='NOTE 20'!C3
A4: Adresse : | B4: ='NOTE 21'!B4 | G4: Sigle usuel : | H4: ='NOTE 21'!H4
A5: N° IFU : | C5: ='NOTE 21'!C5 | E5: Exercice clos le : | F5: ='NOTE 21'!F5 | G5: Durée (en mois) : | H5: ='NOTE 21'!H5
A6: N° de télédéclarant (NES): | C6: ='NOTE 21'!C6
A7: NOTE 27A : CHARGES DE PERSONNEL
A8: Libellés | F8: Année N | G8: Année N-1 | H8: Variation en %
A9: Rémunérations directes versées au personnel national
A10: Rémunérations directes versées au personnel non national
A11: Indemnités forfaitaires versées au personnel
A12: Charges de sécurité sociale (personnel national)
A13: Charges de sécurité sociale (personnel non national)
A14: Rémunérations et charges sociales de l'exploitant individuel
A15: Rémunération transférée de personnel extérieur
A16: Autres charges sociales
A17: TOTAL | F17: =SUM(F9:F16) | G17: =SUM(G9:G16) | H17: =IF(G17,(F17-G17)/G17,IF(ISBLANK(G17),"",IF(F17,IF( F17 > 0,1,-1),"")))
A18: Commentaire :
A19: ● Commenter toute variation significative.
A20: ● Indiquer la nature et la durée du contrat du personnel extérieur.

Sheet NOTE 27B
A1: - 20 -
R2: NOTE 27B SYSTEME NORMAL
A3: Dénomination sociale de l'entité : | D3: ='NOTE 21'!C3
A4: Adresse : | C4: ='NOTE 21'!B4 | Q4: Sigle usuel : | R4: ='NOTE 21'!H4
A5: N° IFU : | D5: ='NOTE 21'!C5 | L5: Exercice clos le : | O5: ='NOTE 21'!F5 | R5: Durée (en mois) : | S5: ='NOTE 21'!H5
A6: N° de télédéclarant (NES): | D6: ='NOTE 21'!C6
A7: NOTE 27B : EFFECTIFS, MASSE SALARIALE ET PERSONNEL EXTERIEUR
B8: EFFECTIF ET MASSE SALARIALE | E8: EFFECTIFS | L8: MASSE SALARIALE
E9: Nationaux | G9: Autres Etats de l'OHADA | I9: Hors OHADA | K9: TOTAL | L9: Nationaux | O9: Autres Etats de l'OHADA | Q9: Hors OHADA | S9: TOTAL
B11: QUALIFICATIONS | E11: M | F11: F | G11: M | H11: F | I11: M | J11: F | L11: M | M11: F | O11: M | P11: F | Q11: M | R11: F
A12: YA | B12: 1. Cadres supérieurs | S12: =L12+M12+O12+P12+Q12+R12
A13: YB | B13: 2. Techniciens supérieurs et cadres moyens | S13: =L13+M13+O13+P13+Q13+R13
A14: YC | B14: 3. Techniciens, agents de maîtrise et ouvriers qualifiés | S14: =L14+M14+O14+P14+Q14+R14
A15: YD | B15: 4. Employés, manœuvres, ouvriers, et apprentis | S15: =L15+M15+O15+P15+Q15+R15
A16: YE | B16: TOTAL (1) (A) | E16: =SUM(E12:E15) | F16: =SUM(F12:F15) | G16: =SUM(G12:G15) | H16: =SUM(H12:H15) | I16: =SUM(I12:I15) | J16: =SUM(J12:J15) | K16: =SUM(K12:K15) | L16: =SUM(L12:L15) | M16: =SUM(M12:M15) | O16: =SUM(O12:O15) | P16: =SUM(P12:P15) | Q16: =SUM(Q12:Q15) | R16: =SUM(R12:R15) | S16: =L16+M16+O16+P16+Q16+R16
A17: YF | B17: Permanents | K17: =SUM(E17:J17) | S17: =L17+M17+O17+P17+Q17+R17
A18: YG | B18: Saisonniers | K18: =SUM(E18:J18) | S18: =L18+M18+O18+P18+Q18+R18
L20: Facturation à l'entité | S20: Note n°/référence aus autres parties des états financiers
B21: 2. Personnel extérieur
A22: YH | B22: 1. Cadres supérieurs | K22: =SUM(E22:J22) | O22: B - Montants comptabilisés non rapportés dans l'état 301 (2)
A23: YI | B23: 2. Techniciens supérieurs et cadres moyens | K23: =SUM(E23:J23)
A24: YJ | B24: 3. Techniciens, agents de maîtrise et ouvriers qualifiés | K24: =SUM(E24:J24) | O24: C - Montants des avantages en nature et en espèces comptabilisés en comptes decharges de personnel
A25: YK | B25: 4. Employés, manœuvres, ouvriers, et apprentis | K25: =SUM(E25:J25) | O25: Total frais de personnel ligne RK ( A + B + C) | R25: =S16+R22+R24
A26: YL | B26: TOTAL (2) | E26: =SUM(E22:E25) | F26: =SUM(F22:F25) | G26: =SUM(G22:G25) | H26: =SUM(H22:H25) | I26: =SUM(I22:I25) | J26: =SUM(J22:J25) | K26: =SUM(K22:K25) | L26: =SUM(L22:L25) | M26: =SUM(M22:M25) | O26: (1): Montants indiqués dans l'état 301 hors avantages en nature et en espèces
A27: YM | B27: Permanents | K27: =SUM(E27:J27) | O27: (2): dont provisions pour congés payés
A28: YN | B28: Saisonniers | K28: =SUM(E28:J28) | O28: M : Masculin
A29: YO | B29: TOTAL (1 + 2) | E29: =E16+E26 | F29: =F16+F26 | G29: =G16+G26 | H29: =H16+H26 | I29: =I16+I26 | J29: =J16+J26 | K29: =K16+K26 | O29: F: Féminin
A30: Commentaire:
A31: ● Faire un commentaire si nécessaire en cas de mouvement significatif du personnel

Sheet NOTE 28
A1: - 0 -
K2: NOTE 28 SYSTEME NORMAL
A3: Dénomination sociale de l'entité : | D3: ='NOTE 21'!C3
A4: Adresse : | B4: ='NOTE 21'!B4 | J4: Sigle usuel : | K4: ='NOTE 21'!H4
A5: N° IFU : | C5: ='NOTE 21'!C5 | G5: Exercice clos le : | H5: ='NOTE 21'!F5 | J5: Durée (en mois) : | K5: ='NOTE 21'!H5
A6: N° de télédéclarant (NES): | C6: ='NOTE 21'!C6
A7: NOTE 28 : DOTATIONS ET CHARGES POUR PROVISIONS ET DEPRECIATIONS
A8: SITUATIONS ET MOUVEMENTS | E8: A | F8: B | I8: C | L8: D = A + B - C
E9: PROVISIONS A L'OUVERTURE DE L'EXERCICE | F9: AUGMENTATIONS : DOTATIONS | I9: DIMINUTIONS : REPRISES | L9: PROVISIONS A LA CLOTURE DE L'EXERCICE
A10: NATURE | F10: D'EXPLOITATION | G10: FINANCIERES | H10: HORS ACTIVITES ORDINAIRES | I10: D'EXPLOITATION | J10: FINANCIERES | K10: HORS ACTIVITES ORDINAIRES
A11: Provisions réglementées | L11: =E11+F11+G11+H11-I11-J11-K11
A12: Provisions financières pour risques et charges | L12: =E12+F12+G12+H12-I12-J12-K12
A13: Dépréciations des immobilisations | L13: =E13+F13+G13+H13-I13-J13-K13
A14: TOTAL DOTATIONS | E14: =SUM(E11:E13) | F14: =SUM(F11:F13) | G14: =SUM(G11:G13) | H14: =SUM(H11:H13) | I14: =SUM(I11:I13) | J14: =SUM(J11:J13) | K14: =SUM(K11:K13) | L14: =E14+F14+G14+H14-I14-J14-K14
A15: Dépréciations des stocks et en cours | L15: =E15+F15+G15+H15-I15-J15-K15
A16: Dépréciations des comptes fournisseurs | L16: =E16+F16+G16+H16-I16-J16-K16
A17: Dépréciations des comptes clients | L17: =E17+F17+G17+H17-I17-J17-K17
A18: Dépréciations autres créances d'exploitation | L18: =E18+F18+G18+H18-I18-J18-K18
A19: Dépréciations des comptes de créances HAO | L19: =E19+F19+G19+H19-I19-J19-K19
A20: Dépréciations des titres de placement | L20: =E20+F20+G20+H20-I20-J20-K20
A21: Dépréciations des titres et valeurs à encaisser | L21: =E21+F21+G21+H21-I21-J21-K21
A22: Dépréciations des comptes banques | L22: =E22+F22+G22+H22-I22-J22-K22
A23: Dépréciations des comptes établissements financiers et assimilés | L23: =E23+F23+G23+H23-I23-J23-K23
A24: Dépréciations des comptes d'instruments de trésorerie | L24: =E24+F24+G24+H24-I24-J24-K24
A25: Provisions pour risques à court terme d'exploitation | L25: =E25+F25+G25+H25-I25-J25-K25
A26: Provisions pour risques à court terme HAO | L26: =E26+F26+G26+H26-I26-J26-K26
A27: Provisions pour risques à court terme à caractère financier | L27: =E27+F27+G27+H27-I27-J27-K27
A28: TOTAL CHARGES POUR DEPRECIATIONS ET PROVISIONS A COURT TERME | E28: =SUM(E15:E27) | F28: =SUM(F15:F27) | G28: =SUM(G15:G27) | H28: =SUM(H15:H27) | I28: =SUM(I15:I27) | J28: =SUM(J15:J27) | K28: =SUM(K15:K27) | L28: =E28+F28+G28+H28-I28-J28-K28
A29: TOTAL | E29: =E14+E28 | F29: =F14+F28 | G29: =G14+G28 | H29: =H14+H28 | I29: =I14+I28 | J29: =J14+J28 | K29: =K14+K28 | L29: =E29+F29+G29+H29-I29-J29-K29
A30: Commentaire:
A31: ● Indiquer les événements et circonstances qui ont conduit à la constitution et à la reprise de la provision.

Sheet NOTE 29
A1: - 0 -
G2: NOTE 29 SYSTEME NORMAL
A3: Dénomination sociale de l'entité : | C3: ='NOTE 21'!C3
A4: Adresse : | B4: ='NOTE 21'!B4 | G4: Sigle usuel : | H4: ='NOTE 21'!H4
A5: N° IFU : | C5: ='NOTE 21'!C5 | E5: Exercice clos le : | F5: ='NOTE 21'!F5 | G5: Durée (en mois) : | H5: ='NOTE 21'!H5
A6: N° de télédéclarant (NES): | C6: ='NOTE 21'!C6
A7: NOTE 29 : CHARGES ET REVENUS FINANCIERS
A8: Libellés | F8: Année N | G8: Année N-1 | H8: Variation en %
A9: Intérêts des emprunts
A10: Intérêts dans loyers de locations acquisition
A11: Escomptes accordés
A12: Autres intérêts
A13: Escomptes des effets de commerce
A14: Pertes de change financières | H14: =IF(G14,(F14-G14)/G14,IF(ISBLANK(G14),"",IF(F14,IF( F14 > 0,1,-1),"")))
A15: Pertes sur cessions de titres de placement | H15: =IF(G15,(F15-G15)/G15,IF(ISBLANK(G15),"",IF(F15,IF( F15 > 0,1,-1),"")))
A16: Malis provenant d’attribution gratuite d’actions au personnel salarié et aux dirigeants | H16: =IF(G16,(F16-G16)/G16,IF(ISBLANK(G16),"",IF(F16,IF( F16 > 0,1,-1),"")))
A17: Pertes et charges sur risques financiers | H17: =IF(G17,(F17-G17)/G17,IF(ISBLANK(G17),"",IF(F17,IF( F17 > 0,1,-1),"")))
A18: Charges pour dépréciation et provisions à court terme à caractère financier (voir note 28) | H18: =IF(G18,(F18-G18)/G18,IF(ISBLANK(G18),"",IF(F18,IF( F18 > 0,1,-1),"")))
A19: SOUS TOTAL : FRAIS FINANCIERS (A) | F19: =SUM(F9:F18) | G19: =SUM(G9:G18) | H19: =IF(G19,(F19-G19)/G19,IF(ISBLANK(G19),"",IF(F19,IF( F19 > 0,1,-1),"")))
A20: Intérêts de prêts et créances diverses
A21: Revenus de participations et autres titres immobilisés
A22: Escomptes obtenus
A23: Revenus de placement
A24: Intérêts dans loyers de location-financement
A25: Gains de change financiers
A26: Gains sur cessions de titres de placement
A27: Gains sur risques financiers
A28: Reprises de charges pour dépréciation et provisions à court terme à caractère financier (voir note 28)
A29: SOUS TOTAL : REVENUS FINANCIERS (B) | F29: =SUM(F20:F28) | G29: =SUM(G20:G28) | H29: =IF(G29,(F29-G29)/G29,IF(ISBLANK(G29),"",IF(F29,IF( F29 > 0,1,-1),"")))
A30: SOUS TOTAL (contrôle) : RESULTAT FINANCIER (B) - (A) | F30: =F29-F19 | G30: =G29-G19 | H30: =IF(G30,(F30-G30)/G30,IF(ISBLANK(G30),"",IF(F30,IF( F30 > 0,1,-1),"")))
A31: Commentaire :
A32: ● Commenter toute variation significative
A33: ● En cas de paiement à terme, indiquer :
A34: -la différence entre le total non actualisé des paiements futurs et la valeur actualisée de ces paiements si celle-ci est significative,
A35: - le taux d'actualisation
A36: ● En cas d'incorporation du coût d'emprunt, indiquer :
A37: -le montant des coûts d'emprunt incorporés dans le coût d'actifs au cours de l'exercice; et,
A38: - le taux de capitalisation utilisé pour déterminer le montant des coûts d'emprunt pouvant être incorporés dans le coût d'actifs.

Sheet NOTE 30
A1: - 0 -
G2: NOTE 30 SYSTEME NORMAL
A3: Dénomination sociale de l'entité : | C3: ='NOTE 21'!C3
A4: Adresse : | B4: ='NOTE 21'!B4 | G4: Sigle usuel : | H4: ='NOTE 21'!H4
A5: N° IFU : | C5: ='NOTE 21'!C5 | E5: Exercice clos le : | F5: ='NOTE 21'!F5 | G5: Durée (en mois) : | H5: ='NOTE 21'!H5
A6: N° de télédéclarant (NES): | C6: ='NOTE 21'!C6
A7: NOTE 30 : AUTRES CHARGES ET PRODUITS HAO
A8: Libellés | F8: Année N | G8: Année N-1 | H8: Variation en %
A9: Charges HAO constatées (compte 831) à détailler (1) : | H9: =IF(G9,(F9-G9)/G9,IF(ISBLANK(G9),"",IF(F9,IF( F9 > 0,1,-1),"")))
H10: =IF(G10,(F10-G10)/G10,IF(ISBLANK(G10),"",IF(F10,IF( F10 > 0,1,-1),"")))
H11: =IF(G11,(F11-G11)/G11,IF(ISBLANK(G11),"",IF(F11,IF( F11 > 0,1,-1),"")))
H12: =IF(G12,(F12-G12)/G12,IF(ISBLANK(G12),"",IF(F12,IF( F12 > 0,1,-1),"")))
H13: =IF(G13,(F13-G13)/G13,IF(ISBLANK(G13),"",IF(F13,IF( F13 > 0,1,-1),"")))
H14: =IF(G14,(F14-G14)/G14,IF(ISBLANK(G14),"",IF(F14,IF( F14 > 0,1,-1),"")))
H15: =IF(G15,(F15-G15)/G15,IF(ISBLANK(G15),"",IF(F15,IF( F15 > 0,1,-1),"")))
A16: Charges liées aux opéations de restructuration | H16: =IF(G16,(F16-G16)/G16,IF(ISBLANK(G16),"",IF(F16,IF( F16 > 0,1,-1),"")))
A17: Pertes sur créances HAO | H17: =IF(G17,(F17-G17)/G17,IF(ISBLANK(G17),"",IF(F17,IF( F17 > 0,1,-1),"")))
A18: Dons et libéralités accordés | H18: =IF(G18,(F18-G18)/G18,IF(ISBLANK(G18),"",IF(F18,IF( F18 > 0,1,-1),"")))
A19: Abandons de créances consentis | H19: =IF(G19,(F19-G19)/G19,IF(ISBLANK(G19),"",IF(F19,IF( F19 > 0,1,-1),"")))
A20: Charges pour dépréciations et provisions pour risques à court terme HAO | H20: =IF(G20,(F20-G20)/G20,IF(ISBLANK(G20),"",IF(F20,IF( F20 > 0,1,-1),"")))
A21: Dotations hors activités ordinaires | H21: =IF(G21,(F21-G21)/G21,IF(ISBLANK(G21),"",IF(F21,IF( F21 > 0,1,-1),"")))
A22: Participation des travailleurs | H22: =IF(G22,(F22-G22)/G22,IF(ISBLANK(G22),"",IF(F22,IF( F22 > 0,1,-1),"")))
A23: SOUS TOTAL : AUTRES CHARGES HAO (ligne RP du CR) | F23: =SUM(F10:F22) | G23: =SUM(G10:G22) | H23: =IF(G23,(F23-G23)/G23,IF(ISBLANK(G23),"",IF(F23,IF( F23 > 0,1,-1),"")))
A24: Produits HAO constatés (compte 841) à détailler(1) : | H24: =IF(G24,(F24-G24)/G24,IF(ISBLANK(G24),"",IF(F24,IF( F24 > 0,1,-1),"")))
H25: =IF(G25,(F25-G25)/G25,IF(ISBLANK(G25),"",IF(F25,IF( F25 > 0,1,-1),"")))
H26: =IF(G26,(F26-G26)/G26,IF(ISBLANK(G26),"",IF(F26,IF( F26 > 0,1,-1),"")))
H27: =IF(G27,(F27-G27)/G27,IF(ISBLANK(G27),"",IF(F27,IF( F27 > 0,1,-1),"")))
H28: =IF(G28,(F28-G28)/G28,IF(ISBLANK(G28),"",IF(F28,IF( F28 > 0,1,-1),"")))
H29: =IF(G29,(F29-G29)/G29,IF(ISBLANK(G29),"",IF(F29,IF( F29 > 0,1,-1),"")))
H30: =IF(G30,(F30-G30)/G30,IF(ISBLANK(G30),"",IF(F30,IF( F30 > 0,1,-1),"")))
A31: Produits liés aux opéations de restructuration | H31: =IF(G31,(F31-G31)/G31,IF(ISBLANK(G31),"",IF(F31,IF( F31 > 0,1,-1),"")))
A32: Indemnités et subventions HAO (entité agricole) | H32: =IF(G32,(F32-G32)/G32,IF(ISBLANK(G32),"",IF(F32,IF( F32 > 0,1,-1),"")))
A33: Dons et libéralités obtenus | H33: =IF(G33,(F33-G33)/G33,IF(ISBLANK(G33),"",IF(F33,IF( F33 > 0,1,-1),"")))
A34: Abandons de créances obtenus | H34: =IF(G34,(F34-G34)/G34,IF(ISBLANK(G34),"",IF(F34,IF( F34 > 0,1,-1),"")))
A35: Transfert de charges H.A.O | H35: =IF(G35,(F35-G35)/G35,IF(ISBLANK(G35),"",IF(F35,IF( F35 > 0,1,-1),"")))
A36: Reprises de charges pour dépréciations et provisions pour risques à court terme HAO | H36: =IF(G36,(F36-G36)/G36,IF(ISBLANK(G36),"",IF(F36,IF( F36 > 0,1,-1),"")))
A37: Reprises des charges, provisions et dépréciations H.A.O | H37: =IF(G37,(F37-G37)/G37,IF(ISBLANK(G37),"",IF(F37,IF( F37 > 0,1,-1),"")))
A38: Subventions d'équilibre | H38: =IF(G38,(F38-G38)/G38,IF(ISBLANK(G38),"",IF(F38,IF( F38 > 0,1,-1),"")))
A39: SOUS TOTAL : AUTRES PRODUITS HAO (ligne TO du CR) | F39: =SUM(F25:F38) | G39: =SUM(G25:G38) | H39: =IF(G39,(F39-G39)/G39,IF(ISBLANK(G39),"",IF(F39,IF( F39 > 0,1,-1),"")))
A40: (CR): Compte de résultat
A41: Commentaire :
A42: ● Commenter toute variation significative.

Sheet NOTE 31
A1: - 21 -
J2: NOTE 31 SYSTEME NORMAL
A3: Dénomination sociale de l'entité : | C3: ='NOTE 30'!C3:H3
A4: Adresse : | B4: ='NOTE 30'!B4:F4 | J4: Sigle usuel : | K4: ='NOTE 30'!H4
A5: N° IFU : | C5: ='NOTE 30'!C5:D5 | G5: Exercice clos le : | H5: ='NOTE 30'!F5 | J5: Durée (en mois) : | K5: ='NOTE 30'!H5
A6: N° de télédéclarant (NES):
A7: NOTE 31 : REPARTITION DU RESULTAT ET AUTRES ELEMENTS CARACTERISTIQUES DES CINQ DERNIERS EXERCICES
A8: EXERCICES CONCERNES (1) | G8: N | H8: N-1 | I8: N - 2 | J8: N - 3 | K8: N - 4
A9: NATURE DES INDICATIONS
A10: STRUCTURE DU CAPITAL A LA CLOTURE DE L'EXERCICE (2) | G10: =SUM(G11:G16) | H10: =SUM(H11:H16) | I10: =SUM(I11:I16) | J10: =SUM(J11:J16) | K10: =SUM(K11:K16)
A11: Capital social
A12: Actions ordinaires
A13: Actions à dividendes prioritaires (A.D.P) sans droit de vote
A14: Actions nouvelles à émettre :
A15: - par conversion d'obligations
A16: - par exercice de droits de souscription
A17: OPERATIONS ET RESULTATS DE L'EXERCICE (3) | G17: =SUM(G18:G22) | H17: =SUM(H18:H22) | I17: =SUM(I18:I22) | J17: =SUM(J18:J22) | K17: =SUM(K18:K22)
A18: Chiffre d'affaires hors taxes | G18: =RESULTAT!I18
A19: Résultat des activités ordinaires (R.A.O) hors dotations et reprises (exploitation et financières)
A20: Participation des travailleurs aux bénéfices
A21: Impôt sur le résultat
A22: Résultat net (4)
A23: RESULTAT ET DIVIDENDE DISTRIBUES | K23: =SUM(K24:K25)
A24: Résultat distribué (5)
A25: Dividende attribué à chaque action
A26: PERSONNEL ET POLITIQUE SALARIALE | K26: =SUM(K29:K31)
A27: Effectif moyen des travailleurs au cours de l'exercice (6)
A28: Effectif moyen de personnel extérieur
A29: Masse salariale distribuée au cours de l'exercice (7)
A30: Avantages sociaux versés au cours de l'exercice (8) [Sécurité sociale, œuvres sociales]
A31: Personnel extérieur facturé à l'entité (9) | H31: 0
A33: (1) Y compris l'exercice dont les états financiers sont soumis à l'approbation de l'Assemblée | G33: (6) Personnel propre
A34: (2) Indication, en cas de libération partielle du capital, du montant du capital non appelé | G34: (7) Total des comptes 661, 662, 663
A35: (3) Les éléments de cette rubrique sont ceux figurant au compte de résultat | G35: (8) Total des comptes 664, 668
A36: (4) Le résultat, lorsqu'il est négatif, doit être mis entre parenthèses | G36: (9) Compte 667
A37: (5) L'exercice N correspond au dividende proposé du dernier exercice

Sheet NOTE 32
A1: - 0 -
O2: NOTE 32 SYSTEME NORMAL
A3: Dénomination sociale de l'entité : | C3: ='NOTE 31'!C3
A4: Adresse : | B4: ='NOTE 31'!B4 | N4: Sigle usuel : | O4: ='NOTE 31'!K4
A5: N° IFU : | C5: ='NOTE 31'!C5 | H5: Exercice clos le : | J5: ='NOTE 31'!H5 | N5: Durée (en mois) : | O5: ='NOTE 31'!K5
A6: N° de télédéclarant (NES): | C6: ='NOTE 31'!C6
A7: NOTE 32 : PRODUCTION DE L'EXERCICE
A8: DESIGNATION DU PRODUIT | D8: UNITE DE QUANTITE CHOISIE | E8: PRODUCTION VENDUE DANS LE PAYS | G8: PRODUCTION VENDUE DANS LES AUTRES PAYS DE L'OHADA | I8: PRODUCTION VENDUE HORS OHADA | K8: PRODUCTION IMMOBILISEE | M8: STOCK OUVERTURE DE L'EXERCICE | O8: STOCK CLOTURE DE L'EXERCICE
E10: Quantité | F10: Valeur | G10: Quantité | H10: Valeur | I10: Quantité | J10: Valeur | K10: Quantité | L10: Valeur | M10: Quantité | N10: Valeur | O10: Quantité | P10: Valeur
A29: NON VENTILE (1)
A30: TOTAL | E30: =SUM(E11:E29) | F30: =SUM(F11:F29) | G30: =SUM(G11:G29) | H30: =SUM(H11:H29) | I30: =SUM(I11:I29) | J30: =SUM(J11:J29) | K30: =SUM(K11:K29) | L30: =SUM(L11:L29) | ... P30: =SUM(P11:P29)
A31: (1) Le montant doit être inférieur ou égal à 1% du total des produits

Sheet NOTE 33
A1: - 0 -
K2: NOTE 33 SYSTEME NORMAL
A3: Dénomination sociale de l'entité : | C3: ='NOTE 31'!C3
A4: Adresse : | B4: ='NOTE 31'!B4 | J4: Sigle usuel : | K4: ='NOTE 31'!K4
A5: N° IFU : | C5: ='NOTE 31'!C5 | E5: Exercice clos le : | G5: ='NOTE 31'!H5 | I5: Durée (en mois) : | K5: ='NOTE 31'!K5
A6: N° de télédéclarant (NES): | C6: ='NOTE 31'!C6
A7: NOTE 33 : ACHATS DESTINES A LA PRODUCTION
A8: DESIGNATION DES MATIERES ET PRODUITS | E8: UNITE DE QUANTITE CHOISIE | F8: ACHATS EFFECTUES AU COURS DE L'EXERCICE | L8: VARIATION DES STOCKS (en valeur)
F9: PRODUITS DE L'ETAT | H9: PRODUITS IMPORTES
H10: ACHETES DANS L'ETAT | J10: ACHETES HORS DE L'ETAT
F11: Quantité | G11: Valeur | H11: Quantité | I11: Valeur | J11: Quantité | K11: Valeur
A30: NON VENTILES (1)
A31: TOTAL | F31: =SUM(F12:F30) | G31: =SUM(G12:G30) | H31: =SUM(H12:H30) | I31: =SUM(I12:I30) | J31: =SUM(J12:J30) | K31: =SUM(K12:K30) | L31: =SUM(L12:L30)
A32: (1) Le montant doit être inférieur ou égal à 1% du total des achats

Sheet NOTE 34
A1: - 22 -
G2: NOTE 34 SYSTEME NORMAL
A3: Dénomination sociale de l'entité : | C3: ='NOTE 31'!C3
A4: Adresse : | B4: ='NOTE 31'!B4 | F4: Sigle usuel : | G4: ='NOTE 31'!K4
A5: N° IFU : | C5: ='NOTE 31'!C5 | E5: Exercice clos le : | G5: Durée (en mois) : | H5: ='NOTE 31'!K5
A6: N° de télédéclarant (NES): | C6: ='NOTE 31'!C6
A7: NOTE 34 : FICHE DE SYNTHESE DES PRINCIPAUX INDICATEURS FINANCIERS
A8: ( EN MILLIERS DE FRANCS) | F8: Année N | G8: Année N-1 | H8: Variation en %
A9: ANALYSE DE L'ACTIVITE
A10: SOLDES INTERMEDIAIRES DE GESTION
A11: CHIFFRE D'AFFAIRES | F11: =RESULTAT!I18 | G11: =RESULTAT!J18
A12: MARGE COMMERCIALE | F12: =RESULTAT!I14 | G12: =RESULTAT!J14
A13: VALEUR AJOUTEE | F13: =RESULTAT!I32 | G13: =RESULTAT!J32
A14: EXCEDENT BRUT D'EXPLOITATION (EBE) | F14: =RESULTAT!I34 | G14: =RESULTAT!J34
A15: RESULTAT D'EXPLOITATION | F15: =RESULTAT!I37 | G15: =RESULTAT!J37
A16: RESULTAT FINANCIER | F16: =RESULTAT!I43 | G16: =RESULTAT!J43
A17: RESULTAT DES ACTIVITES ORDINAIRES | F17: =RESULTAT!I44 | G17: =RESULTAT!J44
A18: RESULTAT HORS ACTIVITES ORDINAIRES | F18: =RESULTAT!I49 | G18: =RESULTAT!J49
A19: RESULTAT NET | F19: =RESULTAT!I52 | G19: =RESULTAT!J52
A20: DETERMINATION DE LA CAPACITE D'AUTOFINANCEMENT
A21: Excédent brut d'exploitation (EBE) | F21: =F14 | G21: =G14
A22: + Valeurs comptables des cessions courantes d’immobilisation (compte 654) | F22: =CtaCptSolde("654*") | G22: =CtaCptSoldeNm1("654*")
A23: - Produits des cessions courantes d’immobilisation (compte 754) | F23: =CtaCptSolde("754*") | G23: =CtaCptSoldeNm1("754*")
A24: = CAPACITE D'AUTOFINANCEMENT D'EXPLOITATION | F24: =F21+F22-F23 | G24: =G21+G22-G23 | H24: =IF(G24,(F24-G24)/G24,IF(ISBLANK(G24),"",IF(F24,IF( F24 > 0,1,-1),"")))
A25: + Revenus financiers | F25: =-CtaCptSolde("77*") | G25: =-CtaCptSoldeNm1("77*")
A26: + Gains de change financiers | F26: =-CtaCptSolde("766*") | G26: =-CtaCptSoldeNm1("766*")
A27: + Transferts de charges financières | F27: =CtaCptSolde("787*") | G27: =CtaCptSoldeNm1("787*")
A28: + Produits HAO | F28: =CtaCptSolde("84*") | G28: =CtaCptSoldeNm1("84*")
A29: + Transferts de charges HAO | F29: =CtaCptSolde("788*") | G29: =CtaCptSoldeNm1("788*")
A30: - Frais financiers | F30: =CtaCptSolde("67*") | G30: =CtaCptSoldeNm1("67*")
A31: - Pertes de change financières | F31: =CtaCptSolde("666*") | G31: =CtaCptSoldeNm1("666*")
A32: - Charges HAO | F32: =CtaCptSolde("85*") | G32: =CtaCptSoldeNm1("85*")
A33: - Participations | F33: =CtaCptSolde("87*") | G33: =CtaCptSoldeNm1("87*")
A34: - Impôts sur les résultats | F34: =CtaCptSolde("89*") | G34: =CtaCptSoldeNm1("89*")
A35: = CAPACITE D'AUTOFINANCEMENT GLOBALE (C.A.F.G.) | F35: =F24+F25+F26+F27+F28+F29-F30-F31-F32-F33-F34 | G35: =G24+G25+G26+G27+G28+G29-G30-G31-G32-G33-G34
A36: - Distributions de dividendes opérées durant l'exercice
A37: = AUTOFINANCEMENT | F37: =F35-F36 | G37: =G35-G36
A38: ANALYSE DE LA RENTABILITE
A39: Rentabilité économique = Résultat d’exploitation (a)/Capitaux propres + dettes financières | F39: =RESULTAT!I37/(BILAN!M21+BILAN!M25) | G39: =RESULTAT!J37/(BILAN!N21+BILAN!N25) | H39: =TEXT(100*(F39-G39),"0") & " points"
A40: Rentabilité financière = Résultat net/Capitaux propres | F40: =RESULTAT!I52/BILAN!M21 | G40: =RESULTAT!J52/BILAN!N21 | H40: =TEXT(100*(F40-G40),"0") & " points"
A41: ANALYSE DE LA STRUCTURE FINANCIERE
A42: + Capitaux propres et ressources assimilées | F42: =BILAN!M21 | G42: =BILAN!N21
A43: + Dettes financières* et autres ressources assimilées (b) | F43: =BILAN!M25 | G43: =BILAN!N25
A44: = ressources stables | F44: =F42+F43 | G44: =G42+G43
A45: - Actif immobilisé (b) | F45: =BILAN!H26 | G45: =BILAN!I26
A46: = FONDS DE ROULEMENT (1) | F46: =F44-F45 | G46: =G44-G45
A47: + Actif circulant d'exploitation (b) | F47: =BILAN!H33-BILAN!H27 | G47: =BILAN!I33-BILAN!I27
A48: - Passif circulant d'exploitation (b) | F48: =BILAN!M33-BILAN!M27 | G48: =BILAN!N33-BILAN!N27
A49: = BESOIN DE FINANCEMENT D'EXPLOITATION (2) | F49: =F47-F48 | G49: =G47-G48
A50: + Actif circulant HAO (b) | F50: =BILAN!H27 | G50: =BILAN!I27
A51: - Passif circulant HAO (b) | F51: =BILAN!M27 | G51: =BILAN!N27
A52: = BESOIN DE FINANCEMENT HAO (3) | F52: =F50-F51 | G52: =G50-G51
A53: BESOIN DE FINANCEMENT GLOBAL (4) = (2) + (3) | F53: =F49+F52 | G53: =G49+G52
A54: TRESORERIE NETTE (5) = (1) - (4) | F54: =F46-F53 | G54: =G46-G53
A55: CONTRÔLE : TRESORERIE NETTE = (TRESORERIE - ACTIF) - (TRESORERIE - PASSIF) | F55: =BILAN!H37-BILAN!M37 | G55: =BILAN!I37-BILAN!N37 | H55: =IF(G55,(F55-G55)/G55,IF(ISBLANK(G55),"",IF(F55,IF( F55 > 0,1,-1),"")))
A56: ANALYSE DE LA VARIATION DE LA TRESORERIE
A57: + Flux de trésorerie des activités opérationnelles | F57: =TFT!I19
A58: - Flux de trésorerie des activités d'investissement | F58: =TFT!I26
A59: + Flux de trésorerie des activités de financement | F59: =TFT!I38
A60: = VARIATION de LA TRESORERIE NETTE de LA PERIODE | F60: =F57+F58+F59
A61: ANALYSE DE LA VARIATION DE L’ENDETTEMENT FINANCIER NET
A62: Endettement financier brut (Dettes financières* + Trésorerie – passif) | F62: =+BILAN!M25+BILAN!M36
A63: - Trésorerie - actif | F63: =-BILAN!F37
A64: = ENDETTEMENT FINANCIER NET | F64: =F62+F63 | G64: =G62+G63 | H64: =IF(G64,(F64-G64)/G64,IF(ISBLANK(G64),"",IF(F64,IF( F64 > 0,1,-1),"")))
A65: (a) Résultat d’exploitation après impôt théorique sur le bénéfice. (b) Les écarts de conversion doivent être éliminés afin de ramener les créances et les dettes concernées à leur valeur initiale. Dettes financières* = emprunts et dettes financières diverses + dettes de location acquisition.

Sheet NOTE 35
A1: - 0 -
H2: NOTE 35 SYSTEME NORMAL
A3: Dénomination sociale de l'entité : | C3: ='NOTE 31'!C3
A4: Adresse : | B4: ='NOTE 31'!B4 | H4: Sigle usuel : | I4: ='NOTE 31'!K4
A5: N° IFU : | C5: ='NOTE 31'!C5 | E5: Exercice clos le : | H5: Durée (en mois) : | I5: ='NOTE 31'!K5
A6: N° de télédéclarant (NES): | C6: ='NOTE 31'!C6
A7: NOTE 35 : LISTE DES INFORMATIONS SOCIALES, ENVIRONNEMENTALES ET SOCIETALES A FOURNIR
A8: Note obligatoire pour les entités ayant un effectif de plus de 250 salariés
A9: Liste des informations sociales, environnementales et sociétales à fournir
A10: INFORMATIONS SOCIALES
A11: Emplois :
A12: • l'effectif total et la répartition des salariés par sexe, âge et zone géographique ;
A13: • les embauches et les licenciements ;
A14: • les rémunérations et leur évolution.
A15: Relations sociales :
A16: • l'organisation du dialogue social ;
A17: • le bilan des accords collectifs.
A18: Santé et sécurité :
... A52: • la prise en compte dans la politique d'achat des enjeux sociaux et environnementaux.

Sheet NOTE 37
A1: - 0 -
H2: NOTE 37 SYSTEME NORMAL
A3: Dénomination sociale de l'entité : | C3: ='NOTE 31'!C3
A4: Adresse : | B4: ='NOTE 31'!B4 | H4: Sigle usuel : | I4: ='NOTE 31'!K4
A5: N° IFU : | C5: ='NOTE 31'!C5 | E5: Exercice clos le : | H5: Durée (en mois) : | I5: ='NOTE 31'!K5
A6: N° de télédéclarant (NES): | C6: ='NOTE 31'!C6
A7: NOTE 37 : EVENEMENTS POSTERIEURS A LA CLOTURE DE L'EXERCICE
A8: Date d'arrêté des états financiers :
A10: Organe ayant autorisé la publication des comptes :
A12: A - EVENEMENTS POSTERIEURS A LA DATE DE CLOTURE DONNANT LIEU A DES AJUSTEMENTS DES ETATS FINANCIERS
A14: Commentaire :
A16: Indiquer la nature des événements postérieurs à la date de clôture donnant lieu à des ajustements des états financiers.
A17: Pour chaque événement, donnez des précisions sur les comptes qui ont fait l'objet d'un ajustement.
A19: B - EVENEMENTS POSTERIEURS A LA DATE DE CLOTURE NE DONNANT LIEU A DES AJUSTEMENTS DES ETATS FINANCIERS
A21: Commentaire :
A23: Procéder à une estimation de l'impact financier de chaque événement ou l'indication que cette estimation ne peut être fournie.
A25: C - EVENEMENTS REMETTANT EN CAUSE L'HYPOTHESE DE BASE DE CONTINUITE D'EXPLOITATION
A27: Commentaire :
... A30: Donner des précisions sur les valeurs liquidatives retenues

Sheet NOTE 38
A1: - 0 -
H2: NOTE 38 SYSTEME NORMAL
A3: Dénomination sociale de l'entité : | C3: ='NOTE 31'!C3
A4: Adresse : | B4: ='NOTE 31'!B4 | H4: Sigle usuel : | I4: ='NOTE 31'!K4
A5: N° IFU : | C5: ='NOTE 31'!C5 | E5: Exercice clos le : | F5: ='NOTE 31'!H5 | H5: Durée (en mois) : | I5: ='NOTE 31'!K5
A6: N° de télédéclarant (NES): | C6: ='NOTE 31'!C6
A7: NOTE 38 : CHANGEMENTS DE METHODES COMPTABLES, D'ESTIMATIONS ET CORRECTIONS D'ERREURS
A9: A – CHANGEMENTS DE METHODES COMPTABLES
A11: 1. Changement de réglementation comptable
A12: Commentaire :
A13: • l’entité doit indiquer l’impact du changement de réglementation comptable (par exemple lors du passage
A14: au SYSCOHADA révisé) déterminé à l’ouverture en précisant les postes concernés ;
A16: • l’entité doit présenter les principaux postes des exercices antérieurs présentés, retraités selon la
A17: nouvelle méthode en cas de changement de réglementation comptable appliqué de manière rétrospective,
A19: • l’entité doit indiquer l’impact du changement sur les principaux postes concernés de l’exercice en cas
A20: de changement de réglementation comptable appliqué de manière prospective.
A22: 2. Changement de méthode à l’initiative de l’entité
A23: Commentaire :
... A46: d’un exercice antérieur.

Sheet PAGE GARDE COMMENTAIRES
E26: NOTE 39 : COMMENTAIRES

Sheet NOTE 39 COMMENTAIRES
A1: NOTE 39 | D1: TABLE DES COMMENTAIRES | G1: COMMENTAIRES PAGE 1/9
A2: Dénomination sociale de l'entité : | C2: ='NOTE 38'!C3:H3
A3: Adresse : | B3: ='NOTE 38'!B4:E4 | F3: Sigle usuel : | G3: ='NOTE 38'!I4
A4: N° IFU : | C4: ='NOTE 38'!C5:D5 | E4: Exercice clos le : | G4: Durée (en mois) : | H4: ='NOTE 38'!I5
A5: N° de télédéclarant (NES):
A6: NOTE 1 | B6: DETTES GARANTIES PAR DES SURETES REELLES
A8: NOTE 3A | B8: IMMOBILISATIONS (BRUTES)
A10: NOTE 3B | B10: BIENS PRIS EN LOCATION-ACQUISITION
A12: NOTE 3C | B12: IMMOBILISATIONS (AMORTISSEMENTS)
A14: NOTE 3D | B14: IMMOBILISATIONS (PLUS-VALUES ET MOINS- VALUES DE CESSION)
A16: TABLE DES COMMENTAIRES | G16: COMMENTAIRES PAGE 2/9
A17: Dénomination sociale de l'entité : | C17: =C2
A18: Adresse : | B18: =B3 | F18: Sigle usuel : | G18: =G3
A19: N° IFU : | C19: =C4 | E19: Exercice clos le : | F19: =F4 | G19: Durée (en mois) : | H19: =H4
A20: N° de télédéclarant (NES): | C20: =C5
A21: NOTE 4 | B21: IMMOBILISATIONS FINANCIERES
A23: NOTE 5 | B23: ACTIF CIRCULANT ET DETTES CIRCULANTES HAO
A24: ACTIF CIRCULANT HAO
A26: DETTES CIRCULANTES HAO
A28: NOTE 6 | B28: STOCKS ET EN COURS (1)
A30: NOTE 7 | B30: CLIENTS
A32: TABLE DES COMMENTAIRES | G32: COMMENTAIRES PAGE 3/9
A33: Dénomination sociale de l'entité : | C33: =C17
A34: Adresse : | B34: =B18 | F34: Sigle usuel : | G34: =G18
A35: N° IFU : | C35: =C19 | E35: Exercice clos le : | G35: Durée (en mois) : | H35: =H19
A36: N° de télédéclarant (NES): | C36: =C20
A37: NOTE 8 | B37: AUTRES CREANCES
A39: NOTE 9 | B39: TITRES DE PLACEMENT
A41: NOTE 10 | B41: VALEURS A ENCAISSER
A43: NOTE 11 | B43: DISPONIBILITES
A45: TABLE DES COMMENTAIRES | G45: COMMENTAIRES PAGE 4/9
A46: Dénomination sociale de l'entité : | C46: =C33
A47: Adresse : | B47: =B34 | F47: Sigle usuel : | G47: =G34
A48: N° de compte contribuable (NCC) : | C48: =C35 | E48: Exercice clos le : | G48: Durée (en mois) : | H48: =H35
A49: N° de télédéclarant (NTD) : | C49: =C36
A50: NOTE 12 | B50: ECARTS DE CONVERSION ET TRANSFERTS DE CHARGES
A51: ECARTS DE CONVERSION
A53: TRANSFERTS DE CHARGES
A55: NOTE 13 | B55: CAPITAL
A57: NOTE 14 | B57: PRIMES ET RESERVES
A59: NOTE 15A | B59: TOTAL SUBVENTIONS D'INVESTISSEMENT ET PROVISIONS REGLEMENTEES
A61: TABLE DES COMMENTAIRES | G61: COMMENTAIRES PAGE 5/9
A62: Dénomination sociale de l'entité : | C62: =C46
A63: Adresse : | B63: =B47 | F63: Sigle usuel : | G63: =G47
A64: N° IFU : | C64: =C48 | E64: Exercice clos le : | G64: Durée (en mois) : | H64: =H48
A65: N° de télédéclarant (NES): | C65: =C49
A66: NOTE 15B | B66: AUTRES FONDS PROPRES
A68: NOTE 16A | B68: DETTES FINANCIERES ET RESSOURCES ASSIMILEES
A70: NOTE 16B | B70: ENGAGEMENTS DE RETRAITE ET AVANTAGES ASSIMILES : PARTIE 1 (METHODE ACTUARIELLE)
A71: HYPOTHESES ACTUARIELLES
A73: VARIATION DE LA VALEUR DE L'ENGAGEM ENT DE RETRAITE AU COURS DE L'EXERCICE
A75: ANALYSE DE SENSIBILITE DES HY POTHESES ACTUA R IELLES
A77: TABLE DES COMMENTAIRES | G77: COMMENTAIRES PAGE 6/9
A78: Dénomination sociale de l'entité : | C78: =C62
A79: Adresse : | B79: =B63 | F79: Sigle usuel : | G79: =G63
A80: N° IFU : | C80: =C64 | E80: Exercice clos le : | F80: =F64 | G80: Durée (en mois) : | H80: =H64
A81: N° de télédéclarant (NES): | C81: =C65
A82: NOTE 16B bis | B82: ENGAGEMENTS DE RETRAITE ET AVANTAGES ASSIMILES : PARTIE 2 (METHODE ACTUARIELLE)
A83: ACTIF/PASSIF NET COMPTABILISE AU TITRE DES REGIMES FINANCES
A85: VALEUR ACTUELLE DES ACTI FS DU REGIME
A87: NOTE 16C | B87: ACTIFS ET PASSIFS EVENTUELS
A89: NOTE 17 | B89: FOURNISSEURS D'EXPLOITATION
A91: NOTE 18 | B91: DETTES FISCALES ET SOCIALES
A93: TABLE DES COMMENTAIRES | G93: COMMENTAIRES PAGE 7/9
A94: Dénomination sociale de l'entité : | C94: =C78
A95: Adresse : | B95: =B79 | F95: Sigle usuel : | G95: =G79
A96: N° IFU : | C96: =C80 | E96: Exercice clos le : | F96: =F80 | G96: Durée (en mois) : | H96: =H80
A97: N° de télédéclarant (NES): | C97: =C81
A98: NOTE 19 | B98: AUTRES DETTES ET PROVISIONS POUR RISQUES A COURT TERME
A100: NOTE 20 | B100: BANQUES, CREDIT D'ESCOMPTE ET DE TRESORERIE
A102: NOTE 21 | B102: CHIFFRE D'AFFAIRES ET AUTRES PRODUITS
A104: NOTE 22 | B104: ACHATS
A106: NOTE 23 | B106: TRANSPORTS
A108: TABLE DES COMMENTAIRES | G108: COMMENTAIRES PAGE 8/9
A109: Dénomination sociale de l'entité : | C109: =C94
A110: Adresse : | B110: =B95 | F110: Sigle usuel : | G110: =G95
A111: N° IFU : | C111: =C96 | E111: Exercice clos le : | F111: =F96 | G111: Durée (en mois) : | H111: =H96
A112: N° de télédéclarant (NES): | C112: =C97
A113: NOTE 24 | B113: SERVICES EXTERIEURS
A115: NOTE 25 | B115: IMPOTS ET TAXES
A117: NOTE 26 | B117: AUTRES CHARGES
A119: NOTE 27A | B119: CHARGES DE PERSONNEL
A121: NOTE 27B | B121: EFFECTIFS, MASSE SALARIALE ET PERSONNEL EXTERIEUR
A123: TABLE DES COMMENTAIRES | G123: COMMENTAIRES PAGE 9/9
A124: Dénomination sociale de l'entité : | C124: =C109
A125: Adresse : | B125: =B110 | F125: Sigle usuel : | G125: =G110
A126: N° IFU : | C126: =C111 | E126: Exercice clos le : | F126: =F111 | G126: Durée (en mois) : | H126: =H111
A127: N° de télédéclarant (NES): | C127: =C112
A128: NOTE 28A | B128: PROVISIONS ET DEPRECIATIONS INSCRITES AU BILAN
A130: NOTE 28B | B130: DEPRECIATIONS DES IMMOBILISATIONS
A132: NOTE 28C | B132: AUTRES DEPRECIATIONS
A134: NOTE 29 | B134: CHARGES ET REVENUS FINANCIERS
A136: NOTE 30 | B136: AUTRES CHARGES ET PRODUITS HAO

Sheet GARDE (DGI)
E23: ETATS SUPPLEMENTAIRES DIRECTION GENERALE DES IMPOTS

Sheet Liste ETATS SUPPL DGI
A1: - 24 -
I2: LISTE ETATS DGI
A3: Dénomination sociale de l'entité : | C3: ='NOTE 38'!C3:H3
A4: Adresse : | B4: ='NOTE 38'!B4:E4 | H4: Sigle usuel : | I4: ='SUPPL1-CHARGES'!J3
A5: N° IFU : | C5: ='NOTE 38'!C5:D5 | E5: Exercice clos le : | F5: ='NOTE 38'!F5 | H5: Durée (en mois) : | I5: ='NOTE 39 COMMENTAIRES'!H4
A6: N° de télédéclarant (NES):
A7: FICHE RECAPITULATIVE DES ETATS SUPPLEMENTAIRES DGI PRESENTES (1)
A8: ETATS | B8: INTITULES | I8: A | J8: N/A
A9: Etat supplémentaire 1 | B9: DETAIL DES CHARGES | I9: x
A10: Etat supplémentaire 2 | B10: DETAIL DES PRODUITS | I10: x
A11: Etat supplémentaire 3 | B11: TVA | I11: x
A12: Etat supplémentaire 4 | B12: ETAT COMPLEMENTAIRE POUR l'INSD: TVA SUPPORTEE NON DEDUCTIBLE
A13: Etat supplémentaire 5 | B13: ELEMENTS STATISTIQUES UEMOA
A14: Etat supplémentaire 6 | B14: REPARTITION DU RESULTAT FISCAL DES SOCIETES DE PERSONNES
A15: Etat supplémentaire 7 | B15: COMPLEMENT INFORMATIONS ENTITES INDIVIDUELLES
A16: Etat supplémentaire 8 | B16: TABLEAU DES IMMOBILISATIONS ET DES AMORTISSEMENTS | I16: x
A17: Etat supplémentaire 9 | B17: DETAIL DES FRAIS ACCESSOIRES SUR ACHATS | I17: x
A18: Etat supplémentaire 10 | B18: DETAIL DES AVANTAGES EN NATURE ALLOUES AU PERSONNEL
A19: Etat supplémentaire 11 | B19: CREANCES ET DETTES ECHUES DE L'EXERCICE
A20: Etat supplémentaire 12 | B20: ETAT ANNUEL DES SALAIRES | I20: x
A21: Etat supplémentaire 13 | B21: ETAT ANNUEL des commissions, courtages, ristournes, honoraires, droits d'auteurs et autres rémunérations versées à des tiers
A22: Etat supplémentaire 14 | B22: ETAT ANNUEL des rémunérations des sassociés et des parts de bénéfices sociaux et autres rémunérations
A23: Etat supplémentaire 15 | B23: Relevé détaillé des loyers d'immeubles passés en charges avec indication de l'identité et de l'adresse des bailleurs | I23: x
A24: Etat supplémentaire 16 | B24: Etat des honoraires rétrocédés avec indication de l'identité complète de chaque bénéficiaire
A25: Etat supplémentaire 17 | B25: Liste des principaux clients | I25: x
A26: Etat supplémentaire 18 | B26: Liste des principaux fournisseurs | I26: x
A27: Etat supplémentaire 19 | B27: TABLEAU DE DETERMINATION DU RESULTAT FISCAL | I27: x
A28: Etat supplémentaire 20 | B28: BORDEREAU AVIS DE VERSEMENT (IS, IBICA ou IBNC) | I28: x
A29: A INSERER AUX PAGES APPROPRIEES | B29: PAGE de garde Détermination du réultat fiscal et de l'IS | I29: x
B30: PAGE de garde Détermination du réultat fiscal et de l'IBICA | I30: x
B31: PAGE de garde Détermination du réultat fiscal et de l'IBNC
A34: (1) les Notes non documentées ne doivent pas être jointes aux états financiers. Leur contenu peut être amélioré par les entités
A35: (2) Bénéfice industriel ou commercial pour le calcul de l'IS ou de l'IBICA
A36: (3): Le contribuable peut insérer autant de déclarations fiscales supplémentaires qu'il le souhaite.
A37: A : Applicable N/A : Non applicable.

Sheet Balance 2023 (2)
A1: N° compte | B1: Libellés | C1: Débit | D1: Crédit | E1: Débit | F1: Crédit | G1: Débit | H1: Crédit
A2: 101200 | B2: Capital souscrit, appelé, non | C2: 0 | D2: 0 | E2: 193000000 | F2: 193000000 | G2: 0 | H2: 0
A3: 101300 | B3: Capital souscrit, appelé, vers | C3: 0 | D3: 100000000 | E3: 0 | F3: 1e+10 | G3: 0 | H3: 10100000000
A4: 129000 | B4: REPORT À NOUVEAU DÉBITEUR | C4: 2748292 | D4: 0 | E4: 20055904 | F4: 0 | G4: 22804196 | H4: 0
A5: 139000 | B5: RÉSULTAT NET : PERTE | C5: 20055904 | D5: 0 | E5: 0 | F5: 20055904 | G5: 0 | H5: 0
A6: 160000 | B6: EMPRUNTS ET DETTES ASSIMILÉES | C6: 0 | D6: 5125000000 | E6: 5125000000 | F6: 0 | G6: 0 | H6: 0
A7: 161100 | B7: Emprunts obligataires ordinair | C7: 0 | D7: 7500000000 | E7: 7500000000 | F7: 0 | G7: 0 | H7: 0
A8: 162010 | B8: EMPRUNT CORIS BANK | C8: 0 | D8: 0 | E8: 247062318 | F8: 500000000 | G8: 0 | H8: 252937682
A9: 162020 | B9: EMPRUNT VISTA | C9: 0 | D9: 0 | E9: 0 | F9: 15000000000 | G9: 0 | H9: 15000000000
A10: 162030 | B10: EMPRUNT WBI | C10: 0 | D10: 0 | E10: 539354385 | F10: 5e+09 | G10: 0 | H10: 4.4606456e+09
A11: 213100 | B11: LOGICIELS | C11: 0 | D11: 0 | E11: 64245912 | F11: 0 | G11: 64245912 | H11: 0
A12: 221800 | B12: AUTRES TERRAINS | C12: 0 | D12: 0 | E12: 962734139 | F12: 0 | G12: 962734139 | H12: 0
A13: 222800 | B13: TERRAINS RIVERAINS | C13: 3000000 | D13: 0 | E13: 437179000 | F13: 4400000 | G13: 435779000 | H13: 0
... A286: 779000 | B286: REPRISES DE CHARGES POUR DEPRE | C286: 0 | D286: 0 | E286: 0 | F286: 925930 | G286: 0 | H286: 925930
A287: Total bilan | C287: 0 | D287: 3.0517578e-07 | E287: 2.1757276e+11 | F287: 2.1704661e+11 | G287: 5.2614863e+08 | H287: 0
A288: Total gestion | C288: 0 | D288: 0 | E288: 3.0379781e+10 | F288: 30905929932 | G288: 0 | H288: 5.2614863e+08
A289: Total hors-bilan | C289: 0 | D289: 0 | E289: 0 | F289: 0 | G289: 0 | H289: 0
A290: TOTAL SOCIETE | C290: 0 | D290: 3.0517578e-07 | E290: 2.4795254e+11 | F290: 2.4795254e+11 | G290: 0 | H290: 0
D292: =SUM(D2:D291) | E292: =SUM(E2:E291)

Sheet SUPPL1-CHARGES
A1: SYSTEME NORMAL | D1: - 25 - | H1: ETAT SUPPLEMENTAIRE N°1
A2: Dénomination sociale de l'entité : | C2: ='Liste ETATS SUPPL DGI'!C3
A3: Adresse : | B3: ='Liste ETATS SUPPL DGI'!B4 | I3: Sigle usuel : | J3: ='NOTE 38'!I4
A4: N° IFU : | C4: ='Liste ETATS SUPPL DGI'!C5 | G4: Exercice clos le : | H4: ='Liste ETATS SUPPL DGI'!F5 | I4: Durée (en mois) : | J4: ='NOTE 38'!I5
A5: N° de télédéclarant (NES): | C5: ='Liste ETATS SUPPL DGI'!C6
A7: ETAT SUPPLEMENTAIRE DIRECTION GENERALE DES IMPOTS/COMPTABILITE NATIONALE
A9: DETAIL DES CHARGES EN FCFA | G9: Exercice N | H9: Exercice N-1 | I9: Variation N/N-1
I10: En valeur | J10: En %
A11: 6011 | B11: Achats de marchandises dans la région | I11: =G11-H11 | J11: =IF(H11,(G11-H11)/H11,IF(ISBLANK(H11),"",IF(G11,IF( G11 > 0,1,-1),"")))
A12: 6012 | B12: Achats de marchandises hors région | I12: =G12-H12 | J12: =IF(H12,(G12-H12)/H12,IF(ISBLANK(H12),"",IF(G12,IF( G12 > 0,1,-1),"")))
A13: 6013 | B13: Achats de marchandises aux entités du groupe dans la région | I13: =G13-H13 | J13: =IF(H13,(G13-H13)/H13,IF(ISBLANK(H13),"",IF(G13,IF( G13 > 0,1,-1),"")))
A14: 6014 | B14: Achats de marchandises aux entités du groupe hors région | I14: =G14-H14 | J14: =IF(H14,(G14-H14)/H14,IF(ISBLANK(H14),"",IF(G14,IF( G14 > 0,1,-1),"")))
A15: 6015 | B15: Frais sur achats | I15: =G15-H15 | J15: =IF(H15,(G15-H15)/H15,IF(ISBLANK(H15),"",IF(G15,IF( G15 > 0,1,-1),"")))
A16: 6019 | B16: Rabais, remises et ristournes obtenus (non ventilés) | I16: =G16-H16 | J16: =IF(H16,(G16-H16)/H16,IF(ISBLANK(H16),"",IF(G16,IF( G16 > 0,1,-1),"")))
A17: RA | C17: Achats de marchandises | G17: 0 | H17: =SUM(H11:H16) | I17: =G17-H17 | J17: =IF(H17,(G17-H17)/H17,IF(ISBLANK(H17),"",IF(G17,IF( G17 > 0,1,-1),"")))
A18: 6031 | B18: Variation des stocks de marchandises | I18: =G18-H18 | J18: =IF(H18,(G18-H18)/H18,IF(ISBLANK(H18),"",IF(G18,IF( G18 > 0,1,-1),"")))
A19: RB | C19: Variation de stocks | G19: 0 | H19: =H18 | I19: =G19-H19 | J19: =IF(H19,(G19-H19)/H19,IF(ISBLANK(H19),"",IF(G19,IF( G19 > 0,1,-1),"")))
A20: 6021 | B20: Achats de matières premières et fournitures liées dans la région
A21: 6022 | B21: Achats de matières premières et fournitures liées hors région
A22: 6023 | B22: Achats de matières premières et fournitures liées aux entités du groupe dans la région
A23: 6024 | B23: Achats de matières premières et fournitures liées aux entités du groupe hors région
A24: 6025 | B24: Frais sur achats
A25: 6029 | B25: Rabais, remises et ristournes obtenus (non ventilés)
A26: RC | C26: Achats de matières premières et fournitures liées
A27: 6032 | B27: Variation des stocks de matières premières et fournitures liées
A28: RD | C28: Variation de stocks de matières premières
A29: 6041 | B29: Matières consommables
A30: 6042 | B30: Matières combustibles
A31: 6043 | B31: Produits d'entretien
A32: 6044 | B32: Fournitures d'atelier et d'usine
A33: 6045 | B33: Frais sur achats
A34: 6046 | B34: Fournitures de magasin
A35: 6047 | B35: Fournitures de bureau
A36: 6049 | B36: Rabais, remises et ristournes obtenus (non ventilés)
A37: 6051 | B37: Fournitures non stockables-Eau
A38: 6052 | B38: Fournitures non stockables-Electricité
A39: 6053 | B39: Fournitures non stockables-Autres énergies
A40: 6054 | B40: Fournitures d'entretien non stockables
... A50: 6089 | B50: Rabais, remises et ristournes obtenus (non ventilés)
A51: RE | C51: Autres achats
A52: 6033 | B52: Variation des stocks d'autres approvisionnements
A53: RF | C53: Variation de stocks d'autres approvisionnements
A54: 612 | B54: Transports sur ventes
A55: 613 | B55: Transports pour le compte de tiers
A56: 614 | B56: Transports du personnel
A57: 616 | B57: Transports de plis
A58: 6181 | B58: Voyages et déplacements
A59: 6182 | B59: Transports entre établissements et chantiers
A60: 6183 | B60: Transports administratifs
A61: 619 | B61: Rabais, remises et ristournes obtenus (non ventilés)
A62: RG | C62: Transports
A63: 621 | B63: Sous-traitance générale
A64: 6221 | B64: Location de terrains
A65: 6222 | B65: Location de bâtiments
A66: 6223 | B66: Location de matériels et outillages
A67: 6224 | B67: Malis sur emballages
A68: 6225 | B68: Locations d'emballages
A69: 6226 | B69: Fermages et loyers du foncier
A70: 6228 | B70: Locations et charges locatives diverses
A71: 6232 | B71: Crédit-bail immobilier
A72: 6233 | B72: Crédit-bail mobilier
A73: 6234 | B73: Location-vente
A75: SYSTEME NORMAL | D75: - 26 - | H75: ETAT SUPPLEMENTAIRE N°1
A76: Dénomination sociale de l'entité : | C76: =C2
A77: Adresse : | B77: =B3 | I77: Sigle usuel : | J77: =J3
A78: N° IFU : | C78: =C4 | G78: Exercice clos le : | H78: =H4 | I78: Durée (en mois) : | J78: =J4
A79: N° de télédéclarant (NES): | C79: =C5
A81: ETAT COMPLEMENTAIRE DIRECTION GENERALE DES IMPOTS/COMPTABILITE NATIONALE
A83: DETAIL DES CHARGES EN FCFA | G83: Exercice N | H83: Exercice N-1 | I83: Variation N/N-1
I84: En valeur | J84: En %
A85: 6238 | B85: Autres contrats de location-acquisition | H85: 0 | I85: =G85-H85 | J85: =IF(H85,(G85-H85)/H85,IF(ISBLANK(H85),"",IF(G85,IF( G85 > 0,1,-1),"")))
A86: 6241 | B86: Entretien et réparation des biens immobiliers
A87: 6242 | B87: Entretien et réparation des biens mobiliers
A88: 6243 | B88: Maintenance
A89: 6244 | B89: Charges de démentellement et remise en état
A90: 6248 | B90: Autre entretiens et réparation
A91: 6251 | B91: Assurances multirisques
A92: 6252 | B92: Assurances matériels de transport
A93: 6253 | B93: Assurances risques d'exploitation
A94: 6254 | B94: Assurances responsabilité du producteur
A95: 6255 | B95: Assurances insolvabilité clients
A96: 6257 | B96: Assurances transport sur ventes
A97: 6258 | B97: Autres primes d'assurances
... A143: 6388 | B143: Charges externes diverses
A144: RH | C144: Services extérieurs
A145: 6411 | B145: Impôts fonciers et taxes annexes
A146: 6412 | B146: Patentes, licences et taxes annexes
A147: 6413 | B147: Taxe sur appointements et salaires
A148: 6414 | B148: Taxes d'apprentissage
A150: SYSTEME NORMAL | D150: - 27 - | H150: ETAT SUPPLEMENTAIRE N°1
A151: Dénomination sociale de l'entité : | C151: =C2
A152: Adresse : | B152: =B3 | I152: Sigle usuel : | J152: =J3
A153: N° IFU : | C153: =C4 | G153: Exercice clos le : | H153: =H4 | I153: Durée (en mois) : | J153: =J4
A154: N° de télédéclarant (NES): | C154: =C5
A156: ETAT COMPLEMENTAIRE DIRECTION GENERALE DES IMPOTS/COMPTABILITE NATIONALE
A158: DETAIL DES CHARGES EN FCFA | G158: Exercice N | H158: Exercice N-1 | I158: Variation N/N-1
I159: En valeur | J159: En %
A160: 6415 | B160: Formation professionnelle continue | I160: =G160-H160 | J160: =IF(H160,(G160-H160)/H160,IF(ISBLANK(H160),"",IF(G160,IF( G160 > 0,1,-1),"")))
A161: 6418 | B161: Autres impôts et taxes directs
A162: 645 | B162: Impôts et taxes indirects
...

Sheet SUPPL2-PRODUITS
A1: SYSTEME NORMAL | D1: - 29 - | H1: ETAT SUPPLEMENTAIRE N°2
A2: Dénomination sociale de l'entité : | C2: ='Liste ETATS SUPPL DGI'!C3
A3: Adresse : | B3: ='Liste ETATS SUPPL DGI'!B4 | I3: Sigle usuel : | J3: ='SUPPL1-CHARGES'!J3
A4: N° IFU : | C4: ='Liste ETATS SUPPL DGI'!C5 | G4: Exercice clos le : | H4: ='Liste ETATS SUPPL DGI'!F5 | I4: Durée (en mois) : | J4: ='SUPPL1-CHARGES'!J4
A5: N° de télédéclarant (NES): | C5: ='Liste ETATS SUPPL DGI'!C6
A7: ETAT SUPPLEMENTAIRE DIRECTION GENERALE DES IMPOTS/COMPTABILITE NATIONALE
A9: DETAIL DES PRODUITS EN FCFA | G9: Exercice N | H9: Exercice N-1 | I9: Variation N/N-1
I10: En valeur | J10: En %
A11: 70 | B11: VENTES
A12: 71 | B12: SUBVENTIONS D'EXPLOITATION
A13: 72 | B13: PRODUCTION IMMOBILISEE
A14: 73 | B14: VARIATIONS DE STOCKS DE BIENS ET DE SERVICES PRODUITS
A15: 75 | B15: AUTRES PRODUITS
A16: 77 | B16: REVENUS FINANCIERS ET ASSIMILES
A17: 78 | B17: TRANSFERTS DE CHARGES
A18: 79 | B18: REPRISES DE PROVISIONS DE DEPRECIATIONS ET AUTRES
A23: TOTAL DES PRODUITS | G23: =SUM(G11:G22) | H23: =SUM(H11:H22) | I23: =SUM(I11:I22) | J23: =SUM(J11:J22)
A24: NB: tous les sous-comptes utilisés devront être indiqués en détail

Sheet SUPPL3-TVA (1)
A1: SYSTEME NORMAL | E1: - 0 - | G1: ETAT SUPPLEMENTAIRE N°3
A2: Dénomination sociale de l'entité : | C2: ='Liste ETATS SUPPL DGI'!C3
A3: Adresse : | B3: ='Liste ETATS SUPPL DGI'!B4 | G3: Sigle usuel : | H3: ='SUPPL2-PRODUITS'!J3
A4: N° IFU : | C4: ='Liste ETATS SUPPL DGI'!C5 | E4: Exercice clos le : | F4: ='Liste ETATS SUPPL DGI'!F5 | G4: Durée (en mois) : | H4: ='SUPPL2-PRODUITS'!J4
A5: N° de télédéclarant (NES): | C5: ='Liste ETATS SUPPL DGI'!C6
A7: ETAT SUPPLEMENTAIRE DIRECTION GENERALE DES IMPOTS/COMPTABILITE NATIONALE
A9: ETAT TVA (Inscrire les mouvements de la période et non les soldes des comptes) | G9: Exercice N | H9: Exercice N-1
B10: T.V.A. facturée sur ventes de la période
B11: T.V.A. facturée sur prestations de services de la période
B12: T.V.A. facturée sur travaux de la période
B13: T.V.A. facturée sur production livrée à soi-même de la période
B14: T.V.A. sur factures à établir de la période
C15: T.V.A. facturée de la période | H15: =SUM(H10:H14)
C16: T.V.A. exigible de la période
B17: T.V.A. récupérable sur immobilisations de la période
B18: T.V.A. récupérable sur achats de la période
B19: T.V.A. récupérable sur transport de la période
B20: T.V.A. récupérable sur services extérieurs et autres charges de la période
B21: T.V.A. récupérable sur factures non parvenues de la période
B22: T.V.A. transférée par d'autres entités de la période
C23: T.V.A. Récupérable de la période | G23: =SUM(G17:G22) | H23: =SUM(H17:H22)
C24: T.V.A. Récupérée de la période
C25: Prorata de déduction
B26: État, T.V.A. due
B27: État, crédit de T.V.A. à reporter
C28: T.V.A. Due ou crédit de T.V.A. | G28: =SUM(G26:G27) | H28: =SUM(H26:H27)

Sheet SUPPL4-TVA (2)
A1: SYSTEME NORMAL | E1: - 0 - | G1: ETAT SUPPLEMENTAIRE N°4
A2: Dénomination sociale de l'entité : | C2: ='Liste ETATS SUPPL DGI'!C3
A3: Adresse : | B3: ='Liste ETATS SUPPL DGI'!B4 | G3: Sigle usuel : | H3: ='SUPPL3-TVA (1)'!H3
A4: N° IFU : | C4: ='Liste ETATS SUPPL DGI'!C5 | E4: Exercice clos le : | F4: ='Liste ETATS SUPPL DGI'!F5 | G4: Durée (en mois) : | H4: ='SUPPL3-TVA (1)'!H4
A5: N° de télédéclarant (NES): | C5: ='Liste ETATS SUPPL DGI'!C6
A7: ETAT SUPPLEMENTAIRE COMPTABILITE NATIONALE
A9: ETAT TVA SUPPORTEE NON DEDUCTIBLE (Inscrire les mouvements de la période et non les soldes des comptes) | G9: Exercice N | H9: Exercice N-1
B10: T.V.A. supportée non déductible sur les immobilisations
B11: T.V.A. supportée non déductible sur les achats de biens et de services
C12: Total T.V.A. supportée non déductible de la période | G12: =SUM(G10:G11) | H12: =SUM(H10:H11)

Sheet SUPPL5
A1: - 0 -
L2: ETAT SUPPLEMENTAIRE N°5
A3: Dénomination sociale de l'entité : | B3: ='Liste ETATS SUPPL DGI'!C3
A4: Adresse : | B4: ='Liste ETATS SUPPL DGI'!B4 | L4: Sigle usuel : | M4: ='SUPPL4-TVA (2)'!H3
A5: N° IFU : | B5: ='Liste ETATS SUPPL DGI'!C5 | I5: Exercice clos le : | J5: ='Liste ETATS SUPPL DGI'!F5 | M5: Durée (en mois) : | N5: ='SUPPL4-TVA (2)'!H4
A6: N° de télédéclarant (NES): | B6: ='Liste ETATS SUPPL DGI'!C6
A7: ETAT SUPPLEMENTAIRE : ELEMENTS STATISTIQUES UEMOA
A8: COMPLEMENT NOTE ANNEXE (Valeur en francs CFA) | I8: COMPLEMENT NOTE 32 (Valeurs en francs CFA)
A9: COMPLEMENT ETAT ANNEXE | D9: Montant autres Etats de l'UEMOA | F9: Montant autres Etats de la Région hors de l'UEMOA | I9: DESIGNATION DU PRODUIT | J9: UNITE DE QUANTITE CHOISIE | K9: PRODUCTION VENDUE DANS LES AUTRES ETATS DE L'UEMOA | M9: PRODUCTION VENDUE AUTRES ETATS DE LA REGION HORS DE L'UEMOA
K12: Quantité | L12: Valeur | M12: Quantité | N12: Valeur
A14: I - B12 - 1 DETAIL DE PRODUITS :
A17: Redevances pour brevets, concessions,
A18: licences, marques et droits similaires :
A19: Redevances pour location de terrains agricoles :
A21: I - C1 - BIENS ACQUIS D'OCCASION :
I30: NON VENTILE
I31: TOTAL | K31: =SUM(K13:K30) | L31: =SUM(L13:L30) | M31: =SUM(M13:M30) | N31: =SUM(N13:N30)
A33: COMPLEMENT NOTE 27 B | B33: AUTRE ETATS DE L'UEMOA | I33: COMPLEMENT NOTE 33 ACHATS DESTINES A LA PRODUCTION EN F CFA | M33: Exercice N
A34: PERSONNEL PROPRE | B34: EFFECTIFS | D34: MASSE SALARIALE | I34: Achats de marchandises dans l'UEMOA
B35: M | C35: F | D35: M | F35: F | I35: Achats de marchandises au groupe dans
A36: 1. CADRE SUPERIEURS | I36: l'UEMOA
A37: 2. TECHNICIENS SUPERIEURS ET CADRES MOYENS | I37: Achats de marchandises | M37: =SUM(M34:N36)
A38: 3. TECHNICIENS, AGENTS DE MAITRISE ET OUVRIERS QUALIFIES | I38: Achats de matières premières dans l'UEMOA
A39: 4. EMPLOYES, MANŒUVRES, OUVRIERS ET APPRENTIS | I39: Achats de matières premières au groupe dans l'UEMOA
A40: TOTAL | B40: =SUM(B36:B39) | C40: =SUM(C36:C39) | D40: =SUM(D36:E39) | F40: =SUM(F36:G39)
A41: PERMANENTS
A42: SAISONNIERS | I42: Achats de matières premières | M42: =SUM(M38:N41)

Sheet SUPPL6
A1: - 0 -
I2: ETAT SUPPLEMENTAIRE N°6
A3: Dénomination sociale de l'entité : | C3: ='Liste ETATS SUPPL DGI'!C3
A4: Adresse : | B4: ='Liste ETATS SUPPL DGI'!B4 | I4: Sigle usuel : | J4: =SUPPL5!M4
A5: N° IFU : | C5: ='Liste ETATS SUPPL DGI'!C5 | G5: Exercice clos le : | H5: ='Liste ETATS SUPPL DGI'!F5 | I5: Durée (en mois) : | J5: =SUPPL5!N5
A6: N° de télédéclarant (NES): | C6: ='Liste ETATS SUPPL DGI'!C6
A7: REPARTITION DU RESULTAT FISCAL DES SOCIETES DE PERSONNES
A8: Nom et Prénoms des Associés | C8: Adresse du Domicile Fiscal | F8: N° de Compte Contribuable | G8: Part des résultats avant réintégration de leurs rémunération et AN et part de l'IMF | H8: Rémunération et avantages en nature et part de l'IMF leur revenant | I8: Total imposable au nom de chaque associé | J8: N° note / ref autres parties états financiers
A31: TOTAL | G31: =SUM(G9:G30) | H31: =SUM(H9:H30) | I31: =SUM(I9:I30) | J31: =SUM(J9:J30)

Sheet SUPPL7
A1: - 0 -
J2: ETAT SUPPLEMENTAIRE N°7
A3: Dénomination sociale de l'entité : | C3: ='Liste ETATS SUPPL DGI'!C3
A4: Adresse : | B4: ='Liste ETATS SUPPL DGI'!B4 | J4: Sigle usuel : | K4: =SUPPL6!J4
A5: N° IFU : | C5: ='Liste ETATS SUPPL DGI'!C5 | G5: Exercice clos le : | H5: ='Liste ETATS SUPPL DGI'!F5 | J5: Durée (en mois) : | K5: ='Liste ETATS SUPPL DGI'!I5
A6: N° de télédéclarant (NES): | C6: ='Liste ETATS SUPPL DGI'!C6
A7: COMPLEMENT INFORMATIONS ENTITES INDIVIDUELLES
E8: EXPLOITANTS INDIVIDUELS | K8: N° note / ref autres parties des états financiers
A9: APPORTS FINANCIERS AU COURS EXERCICE
A10: PRELEVEMENTS FINANCIERS AU COURS EXERCICE
A11: AVANTAGES EN NATURE VALEUR REELLE
A12: REMUNERATIONS CONJOINT EXPLOITANT

Sheet SUPPL8
I2: ETAT SUPPLEMENTAIRE N°8
A3: Dénomination sociale de l'entité :
A4: Adresse : | C4: ='[1]Liste ETATS SUPPL DGI'!B4 | I4: Sigle usuel :
A5: N° IFU : | C5: ='[1]Liste ETATS SUPPL DGI'!C5 | G5: Exercice clos le : | H5: ='[1]Liste ETATS SUPPL DGI'!F5 | I5: Durée (en mois) : | J5: ='[1]Liste ETATS SUPPL DGI'!I5
A6: N° de télédéclarant (NES): | C6: ='[1]Liste ETATS SUPPL DGI'!C6
A7: TABLEAU DES IMMOBILISATIONS ET DES AMORTISSEMENTS
B8: DESIGNATION DES IMMOBILISATIONS | C8: ACQUISITIONS | E8: AMORTISEMENTS DE L'EXERCICE | H8: Amortissement antérieur | I8: Amortissement total | J8: Valeur résiduelle
C10: MOIS / ANNEE | D10: Prix de revient | E10: Taux | F10: Nbre de mois | G10: Dotation annuelle
B15: SOUS TOTAL

Sheet SUPPL9
A1: - 0 -
O2: ETAT SUPPLEMENTAIRE N°9
A3: Dénomination sociale de l'entité : | C3: ='Liste ETATS SUPPL DGI'!C3
A4: Adresse : | B4: ='Liste ETATS SUPPL DGI'!B4 | N4: Sigle usuel : | P4: =SUPPL8!J4
A5: N° IFU : | C5: ='Liste ETATS SUPPL DGI'!C5 | I5: Exercice clos le : | N5: Durée (en mois) : | P5: ='Liste ETATS SUPPL DGI'!I5
A6: N° de télédéclarant (NES): | C6: ='Liste ETATS SUPPL DGI'!C6
A7: DETAIL DES FRAIS ACCESSOIRES SUR ACHATS
D8: Achats de marchandises | F8: Achats de matières premières et fournitures liées | H8: Achats stockés de matières et fournitures consommables | J8: Achats d'emballages | L8: Autres achats | N8: Total rubriques | P8: Immobilisations
A9: Droits de douane | N9: =SUM(D9:M9)
A10: Frets et transports sur achats | N10: =SUM(D10:M10)
A11: Assurances transport sur achats | N11: =SUM(D11:M11)
A12: Commissions et courtages sur achats | N12: =SUM(D12:M12)
A13: Rémunération du transitaire | N13: =SUM(D13:M13)
A14: Autres frais accessoires d'achat | N14: =SUM(D14:M14)
A15: Total frais accessoires d'achats | D15: =SUM(D9:E14) | F15: =SUM(F9:G14) | H15: =SUM(H9:I14) | J15: =SUM(J9:K14) | L15: =SUM(L9:M14) | N15: =SUM(N9:O14) | P15: =SUM(P9:Q14)

Sheet SUPPL10
A1: - 0 -
G2: ETAT SUPPLEMENTAIRE N°10
A3: Dénomination sociale de l'entité : | C3: ='Liste ETATS SUPPL DGI'!C3
A4: Adresse : | B4: ='Liste ETATS SUPPL DGI'!B4 | G4: Sigle usuel : | H4: =SUPPL9!P4
A5: N° IFU : | C5: ='Liste ETATS SUPPL DGI'!C5 | E5: Exercice clos le : | G5: Durée (en mois) : | H5: ='Liste ETATS SUPPL DGI'!I5
A6: N° de télédéclarant (NES): | C6: ='Liste ETATS SUPPL DGI'!C6
A7: DETAIL DES AVANTAGES EN NATURE ALLOUES AU PERSONNEL
G8: Forfait (Barème) F.CFA | H8: Montant réel F.CFA
A9: Loyers de logement du personnel
A10: Bâtiment de logement mis à la disposition du personnel
A11: Eau logement du personnel
A12: Electricité logement du personnel
A13: Télécommunication logement du personnel
A14: Frais de téléphone mobile
A15: Gardiennage logement du personnel
A16: Voyages congés personnel
A17: Matériels de transport mis à disposition du personnel
A18: Autres à préciser
A24: TOTAL (1) | G24: =SUM(G9:G23) | H24: =SUM(H9:H23)

Sheet SUPPL  11
A1: - 0 -
H2: ETAT SUPPLEMENTAIRE N°11
A3: Dénomination sociale de l'entité : | C3: ='Liste ETATS SUPPL DGI'!C3
A4: Adresse : | B4: ='Liste ETATS SUPPL DGI'!B4 | H4: Sigle usuel : | I4: =SUPPL10!H4
A5: N° IFU : | C5: ='Liste ETATS SUPPL DGI'!C5 | E5: Exercice clos le : | H5: Durée (en mois) : | I5: ='Liste ETATS SUPPL DGI'!I5
A6: N° de télédéclarant (NES): | C6: ='Liste ETATS SUPPL DGI'!C6
A7: CREANCES & DETTES ECHUES DE L'EXERCICE
A8: CREANCES ECHUES DE L'EXERCICE | H8: PRINCIPAL | I8: INTERETS
A19: DETTES ECHUES DE L'EXERCICE | H19: PRINCIPAL | I19: INTERETS

Sheet SUPPL12
A1: - 0 -
I2: ETAT SUPPLEMENTAIRE N°12
A3: Dénomination sociale de l'entité : | C3: ='Liste ETATS SUPPL DGI'!C3
A4: Adresse : | B4: ='Liste ETATS SUPPL DGI'!B4 | I4: Sigle usuel : | J4: ='SUPPL 11'!I4
A5: N° IFU : | B5: ='Liste ETATS SUPPL DGI'!C5 | E5: Exercice clos le : | I5: Durée (en mois) : | J5: ='Liste ETATS SUPPL DGI'!I5
A6: N° de télédéclarant (NES): | C6: ='Liste ETATS SUPPL DGI'!C6
A7: ETAT ANNUEL DES SALAIRES
A8: DESIGNATION DES SALARIES | D8: MONTANT des traitements ou Salaires bruts 4 | E8: NOMBRE de personnes à charge 5 | F8: PERIODE 6 | G8: MONTANT des allocations à la fonction 7 | H8: INDEMNITE de logement 8 | I8: INDEMNITE de transport 9 | J8: RETENUES pour pension 11 | K8: RETENUES IUTS 12
A9: NOM ET PRENOMS 1 | B9: EMPLOI 2 | C9: ADRESSE AU 1er JANVIER ou dernière adresse 3
B10: AUTRE
B11: CADRE
B12: AUTRE
B13: AUTRE
B14: AUTRE
D16: =SUM(D10:D15) | E16: =SUM(E10:E15) | F16: =SUM(F10:F15) | G16: =SUM(G10:G15) | H16: =SUM(H10:H15) | I16: =SUM(I10:I15) | J16: =SUM(J10:J15) | K16: =SUM(K10:K15)

Sheet SUPPL13
F1: 31 | I1: ETAT SUPPLEMENTAIRE N°13
A2: Dénomination sociale de l'entité : | C2: =SUPPL12!C3
A3: Adresse : | C3: =SUPPL12!B4 | J3: Sigle usuel : | K3: =SUPPL12!J4
A4: N° IFU : | C4: =SUPPL12!B5 | F4: Exercice clos le : | H4: =SUPPL12!G5 | I4: Durée (en mois) : | K4: =SUPPL12!J5
A5: N° de télédéclarant (NES): | C5: =SUPPL12!C6
A6: ETAT ANNUEL DES COMMISSIONS, VACATIONS, COURTAGES, RISTOURNES, HONORAIRES ET DROITS D'AUTEUR
A7: N° IFU | B7: NOM, RAISON SOCIALE | E7: TELEPHONE | G7: NATURE DE L'OPERATION | I7: Montant annuel HTVA | J7: TVA | K7: TOTAL TTC
K8: =SUM(I8:J8)
K9: =SUM(I9:J9)
K10: =SUM(I10:J10)
K11: =SUM(I11:J11)
K12: =SUM(I12:J12)
K13: =SUM(I13:J13)
K14: =SUM(I14:J14)
K15: =SUM(I15:J15)
K16: =SUM(I16:J16)
K17: =SUM(I17:J17)
A19: TOTAL | I19: =SUM(I8:I18) | J19: =SUM(J9:J18) | K19: =SUM(K8:K18)

Sheet SUPPL14
H1: ETAT SUPPLEMENTAIRE N°14
A3: Dénomination sociale de l'entité : | C3: ='Liste ETATS SUPPL DGI'!C3
A4: Adresse : | C4: ='Liste ETATS SUPPL DGI'!B4 | H4: Sigle usuel : | I4: =SUPPL13!K3
A5: N° IFU : | C5: ='Liste ETATS SUPPL DGI'!C5 | E5: Exercice clos le : | H5: Durée (en mois) : | I5: ='Liste ETATS SUPPL DGI'!I5
A6: N° de télédéclarant (NES): | C6: ='Liste ETATS SUPPL DGI'!C6
A8: ETAT ANNUEL DES REMUNERATIONS VERSEES AUX ASSOCIES ET DES PARTS DE BENEFICES SOCIAUX
A10: N° IFU | B10: NOM, RAISON SOCIALE | E10: TELEPHONE | G10: Type de rémunération | I10: Montant perçu
A22: TOTAL | I22: =SUM(I11:I21)

Sheet SUPPL15
F1: ETAT SUPPLEMENTAIRE N°15
A2: Dénomination sociale de l'entité : | C2: =SUPPL14!C3
A3: Adresse : | C3: =SUPPL14!C4 | H3: Sigle usuel : | I3: =SUPPL14!I4
A4: N° IFU : | C4: =SUPPL14!C5 | E4: Exercice clos le : | F4: =SUPPL14!G5 | H4: Durée (en mois) : | I4: =SUPPL14!I5
A5: N° de télédéclarant (NES): | C5: =+SUPPL14!C6
A7: ETAT DES LOYERS PASSES EN CHARGES
A8: N° IFU du bailleur (éventuellement) | B8: NOM DU BAILLEUR | E8: Adresse, Téléphone | F8: Lieu de situation de l'immeuble loué | H8: Loyer mensuel | I8: Montant total loyers passés en charges
A20: TOTAL | I20: =SUM(I9:I19)

Sheet SUPPL16
I1: ETAT SUPPLEMENTAIRE N°16
A2: Dénomination sociale de l'entité : | E2: =SUPPL15!C2
A3: Adresse : | E3: =SUPPL15!C3 | I3: Sigle usuel : | J3: =SUPPL15!I3
A4: N° IFU : | E4: =SUPPL15!C4 | G4: Exercice clos le : | I4: Durée (en mois) : | J4: =SUPPL15!I4
A5: N° de télédéclarant (NES): | E5: =+SUPPL15!C5
A6: ETAT ANNUEL DES HONORAIRES RETROCEDES POUR DETERMINATION DE L'IBNC
A7: N° IFU du bénéficiaire | C7: NOM, RAISON SOCIALE | F7: TELEPHONE | G7: LOCALITE | H7: SERVICE DES IMPOTS DE RATTACHEMENT | I7: Montant total HTVA | J7: TVA | K7: TOTAL TTC
K8: =SUM(I8:J8)
K9: =SUM(I9:J9)
K10: =SUM(I10:J10)
K11: =SUM(I11:J11)
K12: =SUM(I12:J12)
K13: =SUM(I13:J13)
K14: =SUM(I14:J14)
K15: =SUM(I15:J15)
K16: =SUM(I16:J16)
K17: =SUM(I17:J17)
K18: =SUM(I18:J18)
A19: TOTAL | I19: =SUM(I8:I18) | J19: =SUM(J8:J18) | K19: =SUM(K8:K18)

Sheet SUPPL17
H2: ETAT SUPPLEMENTAIRE N°17
A3: Dénomination sociale de l'entité : | D3: =SUPPL16!E2
A4: Adresse : | B4: Sigle usuel : | D4: =SUPPL16!E3 | G4: Sigle usuel : | H4: =SUPPL16!J3
A5: N° IFU : | C5: =SUPPL16!E4 | E5: Exercice clos le : | H5: Durée (en mois) : | J5: =SUPPL16!J4
A6: N° de télédéclarant (NES): | C6: =+SUPPL16!E5
A7: LISTE DES PRINCIPAUX CLIENTS

Sheet SUPPL18
H2: ETAT SUPPLEMENTAIRE N°18
A3: Dénomination sociale de l'entité : | D3: =SUPPL17!D3
A4: Adresse : | C4: =SUPPL17!D4 | H4: Sigle usuel : | I4: =SUPPL17!H4
A5: N° IFU : | C5: =SUPPL17!C5 | E5: Exercice clos le : | I5: Durée (en mois) : | J5: =SUPPL17!J5
A6: N° de télédéclarant (NES): | C6: =+SUPPL17!C6
A7: LISTE DES PRINCIPAUX FOURNISSEURS

Sheet SUPPL19 RESULTAT FISCAL
A1: - 35 -
G2: ETAT SUPPLEMENTAIRE N° 19
A3: Dénomination sociale de l'entité : | C3: ='NOTE 31'!C3
A4: Adresse : | B4: ='NOTE 31'!B4 | G4: Sigle usuel : | H4: ='NOTE 31'!K4
A5: N° IFU : | C5: ='NOTE 31'!C5 | E5: Exercice clos le : | F5: ='NOTE 31'!H5 | G5: Durée (en mois) : | H5: ='NOTE 31'!K5
A6: N° de télédéclarant (NES): | C6: ='NOTE 31'!C6
A7: TABLEAU DE DETERMINATION DU RESULTAT FISCAL
A8: Libellés | H8: Montant
A9: 1 : RESULTAT NET COMPTABLE DE L'EXERCICE
A11: 2 : REINTEGRATIONS (1) | H11: =SUM(H12:H16)
A12: IMPÔT MINIMUN FORFAITAIRE
A13: AMENDES ET PENALITES DE TOUTE NATURE
A14: FRAIS D'HÔTEL - CADEAUX - DONS - LIBERALITES (NON DEDUCTIBLES)
A15: PRIMES D'ASSURANCES NON DEDUCTIBLES
A16: AUTRES REINTEGRATIONS
A17: 3 : DEDUCTIONS (1)
A18: QUOTE PART BENEFICE EXONERE
A23: 4 : RESULTAT IMPOSABLE AVANT DEDUCTION DES DEFICITS ( 4 = 1+2-3) | H23: =H9+H11-H17
A25: 5 : DEFICITS ANTERIEURS A L'EXERCICE (1) | H25: =SUM(H26:H27)
A26: DEFICITS ANTERIEURS IMPUTES SUR LE RESULTAT DE L'EXERCICE
A28: 6 : AMORTISSEMENTS REGULIEREMENT DIFFERES (1) | H28: =SUM(H29:H30)
A29: ……………..
A30: ……………..
A31: 7 : AMORTISSEMENTS DE L'EXERCICE A DIFFERER (1) | H31: =SUM(H32:H33)
A32: ……………..
A34: 8 : RESULTAT FISCAL DE L'EXERCICE (8= 4-5-6+7) | H34: =H23-H25-H28+H31
A36: 9: IMPOTS SUR LE RESULTAT AU TAUX DE : | D36: 0.275
A39: (1) A détailler

Sheet SUPPL20 BAV IS
A1: CACHET DU SERVICE | C1: DIRECTION GENERALE DES IMPOTS | G1: DATE DE RECEPTION
C5: BORDEREAU AVIS DE VERSEMENT
C6: DE L'IMPOT SUR LES SOCIETES (IS)
C7: Exercice comptable clos le : …............
B8: Réel normal d’imposition | E8: Réel simplifié d’imposition
A9: Supprimer cette ligne
A10: I. IDENTIFICATION DU CONTRIBUABLE
A11: N° Registre du commerce | F11: N° IFU
A12: Raison Sociale :
A13: Code Activité | D13: Regime agrément | F13: Adhérant CGA
A14: Activité :
A15: Adresse du siège: 01 BP 4928 OUAGADOUGOU 01 Localité : ,,,,,,,,,,,,, Tel : ,,,,,, E_mail :
A16: BP : | B16: Secteur: | D16: N° et rue: | E16: ………………… | F16: Section:……. | G16: Lot:…………… | H16: Parcelle:……
A17: Adresses des Etablissements Secondaires (joindre un intercalaire si nécessaire) :
A18: 1)………………………………………………………………………………………………………………………
A19: 2)………………………………………………………………………………………………………………………
A20: 3)………………………………………………………………………………………………………………………
A21: II. DETERMINATION DE L'IMPOT
A23: 01 | B23: CHIFFRE D'AFFAIRES HORS TVA
A25: 02 | B25: RESULTAT FISCAL : Bénéfice Perte | G25: 0
A27: 03 | B27: COTISATION IS EXIGIBLE (ou Minimum Forfaitaire de Perception)
A29: 04 | B29: ACOMPTES PROVISIONNELS DECLARES
A31: 05 | B31: IRVM SUBI (Attestation jointe) | G31: 0
A33: 06 | B33: IRC SUBI (Attestation jointe)
A35: 07 | B35: COTISATION IS DUE [03-(04+05+06)] | G35: =G27-(G29+G31+G33)
A37: 08 | B37: Prélèvements à la source à titre d'acompte d'impôt sur les
B38: bénéfices imputés ( déclaration des prélèvements supportés ci | G38: 0
B39: annexée Montant IV)
A41: 09 | B41: Retenues à la source subies imputées ( déclaration des retenues
B42: subies et attestations de retenues ci-jointes Montant T4)
A44: 10 | B44: COTISATION IS A PAYER [ 07 - (08+09)] * | G44: NEANT
A47: Règlement joint à l'ordre du receveur des impôts
A49: - Chèque barré sur ……………..………... N° …………..………….. du …………….…... Montant ………..……
A51: -Virement (avis de credit): …………………………………………………………………………………...
A52: - Espèces d'un montant de ………………………………..………………………………………………………
F54: A…Ouagadougou…., le
F56: Nom, Qualité et signature
A60: III- CADRE RESERVE A L'ADMINISTRATION
A61: PRISE EN RECETTE | C61: PRISE EN CHARGE | E61: PENALITE | G61: VISA DU RECEVEUR
A62: L.J | C62: L.J | E62: Base: | G62: Date-cachet-signature
A63: Réf . | C63: Réf . | E63: Taux :
A64: Quittance n° | C64: Réf . AMR | E64: Montant :
A65: Quittance date : | C65: Date :
A66: Montant : | C66: Montant :
A68: * Si la cotisation IS due est inférieure ou égale aux prélèvements supportés et aux rétenues subies, porter «zéro(0)» dans la case

Sheet PAGE GARDE IS
E21: DETERMINATION DU RESULTAT FISCAL ET DE L'IMPOT SUR LES SOCIETES (IS)

Sheet PAGE GARDE IBICA 
E21: DETERMINATION DU RESULTAT FISCAL ET DE L'IMPOT SUR LES BENEFICES INDUSTRIELS OU COMMERCIAUX (IBICA)

Sheet PAGE GARDE BNC
E21: DETERMINATION DU RESULTAT FISCAL ET DE L'IMPOT SUR LES DES BENEFICES NON COMMERCIAUX (IBNC)
